Workbook

Sheet README
A2: Routing policy selection — corrected research evidence
A4: 20 September 2026 | Supervisor workbook | Scientific checkpoint: MODIFY OBSERVER
A7: Question / point | B7: Explanation
A8: Research question | B8: When does adapting an established routing policy improve observed decision quality over a fixed policy?
A9: Current decision | B9: Hold the main experiment and ML. The route-order forecast screen failed despite acceptable selected-path average prediction error.
A10: Completed original pilot | B10: 270 runs, 30 contexts, 3 policies. DTT dominates original time/CO2 context means. Preserved separately.
A11: New completed evidence | B11: 432 development runs and 232 marginal route-probe runs. These are engineering/development evidence, not a final test set.
A12: Start here | B12: Open WEIGHTS; choose an amber context/profile; follow DECISION_MATRIX -> NORMALIZATION -> MCDM_CALCULATION.
A13: Primary MCDM | B13: Fixed-reference additive cost, time + CO2; declared analytical preference profiles. VIKOR is one sensitivity only.
A14: Key forecast finding | B14: Selected-path CO2 WAPE 14.71%; route-probe choice loss 21.62% against best observed route in fixed-replay panels.
A15: Headroom finding | B15: Four policy settings win development contexts; best fixed DTT has mean balanced headroom 0.02980 cost units. This is not an ML gain.
A16: Preference finding | B16: Three two-criterion profiles produce identical winners in all 24 contexts; do not exaggerate the MCDM contribution.
A17: Color / status key | B17: Green: completed observations; blue: formulas; amber: editable assumptions; gray: ungenerated; purple: hypothetical. Text labels also state status.
A18: Mathematical traceability | B18: EQUATIONS_TRACEABILITY gives sources and adaptations; SOURCES states access limits. No invisible invented formula.
... A48: SOURCES | B48: Verified bibliography and access status

Sheet LITERATURE_METHODS
A2: Method choice follows the decision problem
A4: ONE primary method; ONE VIKOR sensitivity. No fictitious TOPSIS/PROMETHEE results.
A7: Method | B7: Primary source | C7: Normalization | D7: Weights | E7: Ranking | F7: Assumptions | G7: Excel difficulty | H7: Role | I7: Why / value | J7: Limitation | K7: Transportation connection
A8: Additive value / SAW | B8: R12,R15,R16 | C8: Value functions; here x / fixed positive reference | D8: Multiply criterion values by nonnegative weights summing to 1 | E8: Minimize weighted sum of costs | F8: Preferential separability; linear compensation over chosen range | G8: Very easy | H8: PRIMARY | I8: Fixed references make cross-context regret interpretable | J8: Changing scale changes trade-off; no elicited stakeholder utility | K8: Transportation appraisal; weighted eco objectives are related, not identical
A9: TOPSIS | B9: R12,R13 | C9: Standard vector normalization within alternative matrix | D9: Weights scale normalized coordinates | E9: Maximize distance from worst / (distance to best + distance to worst) | F9: Euclidean geometry; ideal and worst depend on available alternatives | G9: Easy/moderate | H9: NOT NUMERICALLY ADDED | I9: Useful ideal-solution ranking, but adds little here | J9: Closeness differences across scenarios are not common monetary/value losses | K9: Crisp foundation; R29 transportation uses a fuzzy adaptation
A10: VIKOR | B10: R13; R30 section3.3 eqs7-11 | C10: Best/worst range, direction-aware | D10: Weighted normalized losses; additional v=.5 | E10: Minimize compromise Q; advantage + stability or compromise set | F10: Compromise between aggregate S and largest criterion loss R | G10: Moderate | H10: ONE SECONDARY METHOD | I10: Strong inspectable transport application; explains disagreement | J10: Scenario-dependent range; DQ convention differs between papers; not statistical robustness | K10: Rail alignment selection R30; planning problem differs from pre-trip policy
A11: PROMETHEE II | B11: R14 | C11: No universal normalization; criterion preference functions on pairwise differences | D11: Aggregate preference degrees with weights | E11: Descending positive minus negative preference flow | F11: Preference functions and often indifference/preference thresholds | G11: Moderate/many cells | H11: NOT ADDED | I11: Threshold-based outranking could matter after elicitation | J11: No justified thresholds; usual preference discards magnitude | K11: Walking route application R31
A12: AHP for weights | B12: R28 | C12: Pairwise judgments rather than outcome normalization | D12: Priority vector from actual pairwise comparisons | E12: Supplies weights; consistency assesses judgments | F12: Real judgments required | G12: Moderate | H12: DEFER | I12: Could support future elicitation | J12: No fabricated judgments; consistency is not empirical correctness | K12: Established decision support; not a routing algorithm
A13: Entropy / dispersion weights | B13: Not adopted | C13: Data distribution, often normalized proportions | D13: Weights follow dispersion | E13: Not a complete ranking method | F13: Variation proxies information, not preference | G13: Easy | H13: REJECT FOR PREFERENCES | I13: No need to equate noise/variation with importance | J13: Test-based weighting would leak outcomes | K13: No equation implemented; no stakeholder interpretation

Sheet ROUTING_STRATEGIES
A2: Four objectives; ECO / TECO release remains blocked
A4: Development TECO05/10/15 are parameter settings, not three new policy principles.
A7: Policy | B7: Source | C7: Objective | D7: Inputs | E7: Selection rule | F7: Timing | G7: Traffic information | H7: Environmental information | I7: SUMO adaptation | J7: Expected strength | K7: Limitation | L7: Literature versus adaptation
A8: SP | B8: R01; R05 section 2.3 | C8: Minimize route length | D8: Edge/movement lengths; legal catalogue | E8: argmin over routes of sum length | F8: Static pre-trip | G8: No dynamic data | H8: No | I8: Enumerate all 29 simple legal paths; lexicographic tie | J8: Stable baseline; avoids estimation errors | K8: Ignores congestion and emissions | L8: Literature objective; catalogue enumeration is our implementation
A9: DTT | B9: R03; R05 section 2.3 eq22 with time-only cost; R35 | C9: Minimize estimated in-network time | D9: Last complete 60-s edge/movement snapshot | E9: argmin sum estimated time | F9: Dynamic pre-trip | G9: Same lagged traffic data | H9: No environmental objective | I9: Refresh costs every 60 s; assign at request; no en-route changes | J9: Responds to changing delay | K9: Lag, synchronized diversions and insertion-time staleness | L9: Objective established; native snapshot route sum is our adaptation
A10: ECO | B10: R03; R40; R06 | C10: Minimize estimated in-network tailpipe CO2 | D10: Same snapshot per-vehicle edge emission estimates | E10: argmin sum estimated grams | F10: Dynamic pre-trip | G10: Same information coverage | H10: CO2 estimate | I10: Native CO2_perVeh / 1000 plus internal movement costs | J10: Environmental objective independent of distance/time proxy | K10: Forecast route-order gate failed; not a validated eco-navigation system | L10: Established objective; NOT reproduction of published GMR/SVM
A11: TECO | B11: R04 objective; R05 section2.3 eq23 time-budget concept | C11: Minimize estimated CO2 subject to estimated time budget | D11: ECO and DTT forecasts; allowance alpha | E11: min Ehat where That <= (1+alpha) min That | F11: Dynamic pre-trip | G11: Same information coverage | H11: CO2 estimate | I11: Filter the same 29 routes then minimize grams; 5/10/15% development | J11: Bounds estimated detour and may limit inefficient diversions | K11: No realized time guarantee; alpha not yet finally frozen | L11: Hard finite-candidate constraint is OUR adaptation; Huang uses soft sigmoid weighting

Sheet EQUATIONS_TRACEABILITY
A2: Where each mathematical step comes from
A4: Unretrieved equation numbers are marked unverified; no invented page or equation attribution.
A7: ID | B7: Concept | C7: Source / location | D7: Standard concept | E7: Our adaptation | F7: Code / Excel location | G7: Status
A8: E01 | B8: Minimum additive path cost | C8: Dijkstra R01; Huang R05 sec2.3 | D8: min over legal paths sum edge cost | E8: Length / lagged time / lagged grams replace generic cost; exhaustive catalogue search | F8: src/observer.py choose; ROUTING_STRATEGIES | G8: Objective established; implementation adaptation
A9: E02 | B9: Time-constrained eco objective | C9: Zeng2017 R04 objective; Huang R05 eq23 | D9: Huang tc=(1+epsilon)t* with soft weighting eq22 | E9: min Ehat(p) subject to That(p)<=(1+alpha)min That; hard filter | F9: src/observer.py choose; WORKED_EXAMPLE | G9: Adaptation; not a verbatim Huang equation; Zeng full equation number unverified
A10: E03 | B10: Native per-vehicle emissions | C10: SUMO1.25 source R36; R21 | D10: M_mg / sampled vehicle-seconds * estimated traversal seconds | E10: Divide by1000 and sum external + internal connectors | F10: src/observer.py; forecast_trip_pairs.csv.gz | G10: Native algebra verified; treating sum as future route cost is our forecasting adaptation
A11: E04 | B11: Experienced journey / emission mean | C11: R19,R20; arithmetic definition | D11: duration + departDelay; CO2_abs in mg | E11: Full requested primary cohort; convert grams; average within run then equal seed mean | F11: RAW_PERFORMANCE -> REDESIGN_RESULTS | G11: Our estimand/aggregation; no new estimator invention
A12: E05 | B12: Fixed-reference additive cost | C12: Keeney-Raiffa R15; DCLG R16 | D12: Additive value=sum criterion weights x single-criterion values | E12: Cost C=sum w_k*y_k/a_k, with positive frozen references | F12: NORMALIZATION; MCDM_CALCULATION; =SUM(weighted cells) | G12: Our linear reference-scaling adaptation; lower is preferred
A13: E06 | B13: Decision regret / headroom | C13: Robust optimization R24; algorithm selection R08-R10 | D13: Opportunity loss relative to best feasible alternative | E13: r_sa=C_sa-min_b C_sb; H_s=r_s,fixed | F13: ROBUSTNESS; =chosen_cost-MIN(policy_costs) | G13: Context-policy application; differs from VIKOR max criterion loss
A14: E07 | B14: Mean / minimax fixed | C14: R24; portfolio benchmark R09 | D14: Min expected cost; min worst opportunity loss | E14: Training-context equal mean; min maximum training regret | F14: Future fixed policy selected before validation/test | G14: Finite designed-context approximation, not guarantee beyond design
A15: E08 | B15: VIKOR S and R | C15: Kosijer R30 sec3.3 pp200-201 eqs7,8 | D15: S=sum w*(best-f)/(best-worst); R=max weighted ratio | E15: All cost criteria: (x-min)/(max-min); constant columns contribute0 | F15: MCDM_METHOD_COMPARISON; SUM and MAX | G15: Cost-direction algebra equivalent; zero-range convention explicit
A16: E09 | B16: VIKOR Q and acceptance | C16: Kosijer R30 eqs9-11, p201 | D16: Q=v*scaledS+(1-v)*scaledR; DQ=min(.25,1/(m-1)) | E16: v=.5; stability best S or R or best Q at both .25 and .75 | F16: MCDM_METHOD_COMPARISON; supplementary_analysis.py | G16: Follow inspected source; prior uncapped convention archived separately
A17: E10 | B17: P95 | C17: Hyndman-Fan R27 type7 | D17: h=1+(n-1)p; linear interpolation between order statistics | E17: p=.95 within each complete primary run; equal mean across seeds | F17: np.quantile(method=linear); P95 diagnostic column | G17: Not pooled quantile; pilot original lower order statistic unchanged
A18: E11 | B18: Prediction error screen | C18: Absolute-error arithmetic; decision-loss distinction R11 | D18: MAE=mean abs(pred-actual); WAPE=sum abs error/sum actual | E18: Trip-weighted screen; bias=sum error/sum actual; thresholds declared here | F18: analysis/forecast_summary.csv; VALIDATION | G18: Research tolerances not established acceptance standards
... A21: E14 | B21: TOPSIS / PROMETHEE comparison only | C21: R12,R13 / R14 | D21: Vector distances to ideals / pairwise preference flows | E21: No numeric implementation in this release | F21: LITERATURE_METHODS; report | G21: Avoid extra unexplained methods and unjustified thresholds

Sheet NETWORK
A2: Engineering candidate: compact cross-connected urban mesh
A4: 12 signalized junctions; 47 external links; 29 legal simple primary paths. One topology, no real-city inference.
A7: Candidate | B7: Core junctions | C7: Directed core links | D7: Simple graph paths | E7: Min core length (m) | F7: Max core length (m) | G7: Evidence status
A8: 2x4 | B8: 8 | C8: 20 | D8: 8 | E8: 1200 | F8: 2400 | G8: Analytical graph only; not SUMO-engineered
A9: 3x3 | B9: 9 | C9: 24 | D9: 9 | E9: 800 | F9: 2000 | G9: Analytical graph only; not SUMO-engineered
A10: 3x4 | B10: 12 | C10: 34 | D10: 29 | E10: 1200 | F10: 3200 | G10: SUMO engineering tested
A13: Primary OD | B13: O -> C0 ... C3 -> D
A14: Background | B14: Four fixed NS/SN streams at columns 1 and 2
A15: Signal programs | B15: 60 s; EW/NS 26/26 or 36/16; two 3 s yellow + 1 s all-red
A16: Capacity specification | B16: Lane counts are inputs, not calibrated saturation capacities.
A19: External link | B19: From | C19: To | D19: Lanes | E19: Speed (km/h) | F19: Requested length (m)
A20: C0_C1 | B20: C0 | C20: C1 | D20: 1 | E20: 50 | F20: 400
A21: C0_L0 | B21: C0 | C21: L0 | D21: 1 | E21: 40 | F21: 300
A22: C0_U0 | B22: C0 | C22: U0 | D22: 1 | E22: 40 | F22: 300
A23: C1_C0 | B23: C1 | C23: C0 | D23: 1 | E23: 50 | F23: 400
A24: C1_CR | B24: C1 | C24: CR | D24: 1 | E24: 50 | F24: 150
A25: C1_L1 | B25: C1 | C25: L1 | D25: 1 | E25: 40 | F25: 300
A26: C1_U1 | B26: C1 | C26: U1 | D26: 1 | E26: 40 | F26: 300
A27: C2_C1 | B27: C2 | C27: C1 | D27: 1 | E27: 50 | F27: 400
A28: C2_C3 | B28: C2 | C28: C3 | D28: 1 | E28: 50 | F28: 400
A29: C2_L2 | B29: C2 | C29: L2 | D29: 1 | E29: 40 | F29: 300
A30: C2_U2 | B30: C2 | C30: U2 | D30: 1 | E30: 40 | F30: 300
A31: C3_C2 | B31: C3 | C31: C2 | D31: 1 | E31: 50 | F31: 400
... A66: source | B66: O | C66: C0 | D66: 3 | E66: 50 | F66: 1500
A70: Route | B70: Primary? | C70: Length incl. connectors (m) | D70: External edge sequence
A71: NS1 | B71: NO | C71: 1849.6 | D71: N1_U1 U1_C1 C1_L1 L1_S1
A72: NS2 | B72: NO | C72: 1849.6 | D72: N2_U2 U2_C2 C2_L2 L2_S2
A73: P01 | B73: YES | C73: 3208.82 | D73: source C0_C1 C1_CR CR_C2 C2_C3 sink
A74: P02 | B74: YES | C74: 3833.87 | D74: source C0_C1 C1_CR CR_C2 C2_L2 L2_L3 L3_C3 sink
A75: P03 | B75: YES | C75: 3819.34 | D75: source C0_C1 C1_CR CR_C2 C2_U2 U2_U3 U3_C3 sink
A76: P04 | B76: YES | C76: 3831.78 | D76: source C0_C1 C1_L1 L1_LR LR_L2 L2_C2 C2_C3 sink
A77: P05 | B77: YES | C77: 4447.87 | D77: source C0_C1 C1_L1 L1_LR LR_L2 L2_C2 C2_U2 U2_U3 U3_C3 sink
A78: P06 | B78: YES | C78: 3833.87 | D78: source C0_C1 C1_L1 L1_LR LR_L2 L2_L3 L3_C3 sink
A79: P07 | B79: YES | C79: 3826.48 | D79: source C0_C1 C1_U1 U1_UR UR_U2 U2_C2 C2_C3 sink
A80: P08 | B80: YES | C80: 4457.1 | D80: source C0_C1 C1_U1 U1_UR UR_U2 U2_C2 C2_L2 L2_L3 L3_C3 sink
A81: P09 | B81: YES | C81: 3819.34 | D81: source C0_C1 C1_U1 U1_UR UR_U2 U2_U3 U3_C3 sink
A82: P10 | B82: YES | C82: 3834.13 | D82: source C0_L0 L0_L1 L1_C1 C1_CR CR_C2 C2_C3 sink
... A103: SN2 | B103: NO | C103: 1849.6 | D103: S2_L2 L2_C2 C2_U2 U2_N2

Sheet SCENARIO_DESIGN
A2: Development evidence and unreleased main design
A4: D = completed development; M = preallocated candidate main contexts, outcomes NOT GENERATED.
A7: Context | B7: Primary (veh/h) | C7: Background / stream (veh/h) | D7: Restriction location | E7: Speed ratio | F7: Signal | G7: Allocation | H7: Repetitions | I7: Outcome status | J7: Knowledge at selection
A8: D001 | B8: 720 | C8: 200 | D8: None | E8: 1 | F8: Balanced | G8: DEVELOPMENT | H8: 3 | I8: COMPLETED | J8: Scheduled/stipulated inputs
A9: D002 | B9: 720 | C9: 200 | D9: None | E9: 1 | F9: Arterial | G9: DEVELOPMENT | H9: 3 | I9: COMPLETED | J9: Scheduled/stipulated inputs
A10: D003 | B10: 720 | C10: 200 | D10: U | E10: 0.35 | F10: Balanced | G10: DEVELOPMENT | H10: 3 | I10: COMPLETED | J10: Scheduled/stipulated inputs
A11: D004 | B11: 720 | C11: 200 | D11: U | E11: 0.35 | F11: Arterial | G11: DEVELOPMENT | H11: 3 | I11: COMPLETED | J11: Scheduled/stipulated inputs
A12: D005 | B12: 720 | C12: 200 | D12: C | E12: 0.35 | F12: Balanced | G12: DEVELOPMENT | H12: 3 | I12: COMPLETED | J12: Scheduled/stipulated inputs
A13: D006 | B13: 720 | C13: 200 | D13: C | E13: 0.35 | F13: Arterial | G13: DEVELOPMENT | H13: 3 | I13: COMPLETED | J13: Scheduled/stipulated inputs
A14: D007 | B14: 720 | C14: 200 | D14: L | E14: 0.35 | F14: Balanced | G14: DEVELOPMENT | H14: 3 | I14: COMPLETED | J14: Scheduled/stipulated inputs
A15: D008 | B15: 720 | C15: 200 | D15: L | E15: 0.35 | F15: Arterial | G15: DEVELOPMENT | H15: 3 | I15: COMPLETED | J15: Scheduled/stipulated inputs
A16: D009 | B16: 1200 | C16: 200 | D16: None | E16: 1 | F16: Balanced | G16: DEVELOPMENT | H16: 3 | I16: COMPLETED | J16: Scheduled/stipulated inputs
A17: D010 | B17: 1200 | C17: 200 | D17: None | E17: 1 | F17: Arterial | G17: DEVELOPMENT | H17: 3 | I17: COMPLETED | J17: Scheduled/stipulated inputs
A18: D011 | B18: 1200 | C18: 200 | D18: U | E18: 0.35 | F18: Balanced | G18: DEVELOPMENT | H18: 3 | I18: COMPLETED | J18: Scheduled/stipulated inputs
A19: D012 | B19: 1200 | C19: 200 | D19: U | E19: 0.35 | F19: Arterial | G19: DEVELOPMENT | H19: 3 | I19: COMPLETED | J19: Scheduled/stipulated inputs
... A171: M140 | B171: 1680 | C171: 280 | D171: L | E171: 0.65 | F171: Arterial | G171: VALIDATION | H171: 5 | I171: TO BE GENERATED — BLOCKED | J171: Scheduled/stipulated inputs

Sheet RAW_PERFORMANCE
A2: 432 completed development runs
A4: Imported audited SUMO run summaries; primary cohort only in primary criteria. Not a held-out test.
A7: Key | B7: Context | C7: Setting | D7: Seed | E7: Primary n | F7: Mean journey (s) | G7: CO2 (g/veh) | H7: Distance (m) | I7: P95 journey (s) | J7: Insertion (s) | K7: BG journey (s) | L7: BG CO2 (g/veh) | M7: Network cohort CO2 (g) | N7: Stopped vehicle-time (veh-s) | O7: Default link fraction | P7: CO2 WAPE | Q7: CO2 signed bias | R7: Mean primary (veh/h) | S7: Background / stream | T7: Restriction | U7: Signal | V7: Source status | W7: Native mass error
A8: D001__SP__8101 | B8: D001 | C8: SP | D8: 8101 | E8: 375 | F8: 336.71733 | G8: 906.09468 | H8: 3203.72 | I8: 356 | J8: 0.098666667 | K8: 236.98677 | L8: 578.68636 | M8: 558528.95 | N8: 78535 | O8: 0 | P8: 0.046665366 | Q8: 0.015033588 | R8: 720 | S8: 200 | T8: None | U8: Balanced | V8: NEW DEVELOPMENT RESULT | W8: 0.0014515402
A9: D001__SP__8102 | B9: D001 | C9: SP | D9: 8102 | E9: 392 | F9: 337.48724 | G9: 910.74976 | H9: 3203.72 | I9: 357 | J9: 0.125 | K9: 238.77778 | L9: 583.98384 | M9: 583015.65 | N9: 78516 | O9: 0 | P9: 0.042920982 | Q9: 0.0041563173 | R9: 720 | S9: 200 | T9: None | U9: Balanced | V9: NEW DEVELOPMENT RESULT | W9: 0.0014535984
A10: D001__SP__8103 | B10: D001 | C10: SP | D10: 8103 | E10: 361 | F10: 336.70914 | G10: 906.86264 | H10: 3203.72 | I10: 356 | J10: 0.14127424 | K10: 237.02757 | L10: 579.23196 | M10: 558490.97 | N10: 75179 | O10: 0 | P10: 0.043290611 | Q10: 0.0053161341 | R10: 720 | S10: 200 | T10: None | U10: Balanced | V10: NEW DEVELOPMENT RESULT | W10: 0.001470761
A11: D001__DTT__8101 | B11: D001 | C11: DTT | D11: 8101 | E11: 375 | F11: 368.41333 | G11: 979.3579 | H11: 3635.1293 | I11: 426 | J11: 0.098666667 | K11: 236.98677 | L11: 578.68636 | M11: 586002.66 | N11: 73009 | O11: 0.75971059 | P11: 0.18294275 | Q11: 0.15713598 | R11: 720 | S11: 200 | T11: None | U11: Balanced | V11: NEW DEVELOPMENT RESULT | W11: 0.001376046
A12: D001__DTT__8102 | B12: D001 | C12: DTT | D12: 8102 | E12: 392 | F12: 373.07143 | G12: 990.25633 | H12: 3629.6059 | I12: 441.45 | J12: 0.125 | K12: 238.77778 | L12: 583.98384 | M12: 614182.23 | N12: 73747 | O12: 0.78395062 | P12: 0.17703479 | Q12: 0.13648927 | R12: 720 | S12: 200 | T12: None | U12: Balanced | V12: NEW DEVELOPMENT RESULT | W12: 0.0013839282
A13: D001__DTT__8103 | B13: D001 | C13: DTT | D13: 8103 | E13: 361 | F13: 360.93352 | G13: 958.80462 | H13: 3634.4145 | I13: 412 | J13: 0.14127424 | K13: 237.02757 | L13: 579.23196 | M13: 577242.02 | N13: 67872 | O13: 0.76121763 | P13: 0.17015345 | Q13: 0.14789195 | R13: 720 | S13: 200 | T13: None | U13: Balanced | V13: NEW DEVELOPMENT RESULT | W13: 0.0014196907
A14: D001__ECO__8101 | B14: D001 | C14: ECO | D14: 8101 | E14: 375 | F14: 336.71733 | G14: 906.09468 | H14: 3203.72 | I14: 356 | J14: 0.098666667 | K14: 236.98677 | L14: 578.68636 | M14: 558528.95 | N14: 78535 | O14: 0 | P14: 0.046665366 | Q14: 0.015033588 | R14: 720 | S14: 200 | T14: None | U14: Balanced | V14: NEW DEVELOPMENT RESULT | W14: 0.0014515402
A15: D001__ECO__8102 | B15: D001 | C15: ECO | D15: 8102 | E15: 392 | F15: 337.48724 | G15: 910.74976 | H15: 3203.72 | I15: 357 | J15: 0.125 | K15: 238.77778 | L15: 583.98384 | M15: 583015.65 | N15: 78516 | O15: 0 | P15: 0.042920982 | Q15: 0.0041563173 | R15: 720 | S15: 200 | T15: None | U15: Balanced | V15: NEW DEVELOPMENT RESULT | W15: 0.0014535984
A16: D001__ECO__8103 | B16: D001 | C16: ECO | D16: 8103 | E16: 361 | F16: 336.70914 | G16: 906.86264 | H16: 3203.72 | I16: 356 | J16: 0.14127424 | K16: 237.02757 | L16: 579.23196 | M16: 558490.97 | N16: 75179 | O16: 0 | P16: 0.043290611 | Q16: 0.0053161341 | R16: 720 | S16: 200 | T16: None | U16: Balanced | V16: NEW DEVELOPMENT RESULT | W16: 0.001470761
A17: D001__TECO05__8101 | B17: D001 | C17: TECO05 | D17: 8101 | E17: 375 | F17: 360.816 | G17: 971.24918 | H17: 3594.5123 | I17: 410.3 | J17: 0.098666667 | K17: 237.01323 | L17: 578.73581 | M17: 582980.58 | N17: 73371 | O17: 0.63325518 | P17: 0.17551735 | Q17: 0.12773761 | R17: 720 | S17: 200 | T17: None | U17: Balanced | V17: NEW DEVELOPMENT RESULT | W17: 0.0013588955
A18: D001__TECO05__8102 | B18: D001 | C18: TECO05 | D18: 8102 | E18: 392 | F18: 362.82143 | G18: 976.51474 | H18: 3585.0584 | I18: 425.45 | J18: 0.125 | K18: 238.77778 | L18: 583.98384 | M18: 608795.52 | N18: 73510 | O18: 0.67128157 | P18: 0.15799372 | Q18: 0.10012674 | R18: 720 | S18: 200 | T18: None | U18: Balanced | V18: NEW DEVELOPMENT RESULT | W18: 0.0013743567
A19: D001__TECO05__8103 | B19: D001 | C19: TECO05 | D19: 8103 | E19: 361 | F19: 358.09972 | G19: 965.17577 | H19: 3590.8241 | I19: 400 | J19: 0.14127424 | K19: 237.04261 | L19: 579.26789 | M19: 579556.34 | N19: 69669 | O19: 0.6590124 | P19: 0.14749955 | Q19: 0.10384628 | R19: 720 | S19: 200 | T19: None | U19: Balanced | V19: NEW DEVELOPMENT RESULT | W19: 0.0013881113
... A439: D024__TECO15__8103 | B439: D024 | C439: TECO15 | D439: 8103 | E439: 862 | F439: 663.67749 | G439: 1489.7032 | H439: 3203.72 | I439: 953.95 | J439: 133.43387 | K439: 247.02757 | L439: 607.67642 | M439: 1526587.1 | N439: 248772 | O439: 0 | P439: 0.12076377 | Q439: -0.0014328132 | R439: 1680 | S439: 200 | T439: L | U439: Arterial | V439: NEW DEVELOPMENT RESULT | W439: 0.00097854461

Sheet CRITERIA_SELECTION
A2: Two primary criteria; additional measures remain diagnostics
A4: Primary time + CO2; distance and P95 are available for explicitly labeled sensitivity.
A7: Criterion | B7: Role | C7: Unit / population | D7: Direction | E7: Calculation | F7: Source | G7: Meaning | H7: Redundancy / limitation | I7: Decision
A8: Mean journey time | B8: ESTABLISHED; PRIMARY | C8: s/primary vehicle | D8: Cost | E8: arrival minus scheduled request = duration + departDelay | F8: R19 SUMO Tripinfo; our full-cohort definition | G8: Captures service including delayed insertion | H8: Partly correlated with CO2, but a distinct mobility impact | I8: KEEP
A9: Mean tailpipe CO2 | B9: ESTABLISHED; PRIMARY | C9: g/primary vehicle | D9: Cost | E9: CO2_abs mg / 1000; completed primary cohort mean | F9: R20-R21; R03,R06,R40 environmental routing | G9: Direct modeled environmental outcome | H9: Excludes pre-insertion idling, lifecycle and non-CO2 pollutants | I9: KEEP
A10: Fuel | B10: ESTABLISHED environmental alternative | C10: SUMO model fuel units | D10: Cost | E10: Native fuel_abs, unit mode recorded | F10: R05; R20 | G10: Energy relevance | H10: CO2/fuel ratio ~3.135; trip correlation >0.999999997 in every run | I10: REMOVE from MCDM
A11: Distance | B11: ESTABLISHED route objective; possible decision criterion | C11: m/primary vehicle | D11: Cost | E11: Tripinfo routeLength | F11: R01,R05; R19 | G11: Could represent distance-related operating burden if explicitly valued | H11: Not automatically double counting SP; but no separate stakeholder value stated; 0/24 winner changes | I11: DIAGNOSTIC
A12: P95 journey time | B12: ADDITIONAL tail service criterion | C12: s/primary vehicle | D12: Cost | E12: Type7 per-run percentile; average of run P95s across seeds | F12: R17; R27; our episode-tail adaptation | G12: Reflects poorly served trips | H12: Not day-to-day same-trip reliability; correlated with mean; only 1/24 equal-three-weight winner changes | I12: SENSITIVITY
A13: Delay / time loss | B13: ADDITIONAL operational indicator | C13: s/vehicle | D13: Cost | E13: Native timeLoss / waitingTime; definitions differ | F13: R19 | G13: Explains mechanisms | H13: Adds another time-related component; do not silently equate waiting, timeLoss and departDelay | I13: DIAGNOSTIC
A14: Stops / queues | B14: ADDITIONAL operational indicator | C14: count; vehicle-s | D14: Cost | E14: Stops require threshold convention; edge waitingTime aggregated | F14: R22 | G14: Locates bottlenecks and spillback | H14: Not an independent welfare criterion; queue proxy is stopped vehicle-time, not max physical length | I14: DIAGNOSTIC
A15: Safety / exposure / noise / money | B15: Additional possible impacts | C15: Unspecified | D15: Unspecified | E15: No validated model supplied | F15: Not used | G15: Potential future studies | H15: Cannot be inferred credibly from present outputs | I15: REMOVE

Sheet DECISION_MATRIX
A2: 1. Observed policy outcomes for the selected context
A4: Only observed development outcomes enter physical ranking. Future ML predictions will be separate.
A5: Development context | B5: =WEIGHTS!B5 | D5: Preference profile | E5: =WEIGHTS!B6
A7: Policy | B7: Time (s) — COST | C7: CO2 (g) — COST | D7: Distance (m) — COST | E7: P95 (s) — COST | F7: Evidence status | G7: Source lookup
A8: SP | B8: =INDEX(REDESIGN_RESULTS!$D$8:$D$151,MATCH(WEIGHTS!$B$5&"__"&A8,REDESIGN_RESULTS!$A$8:$A$151,0)) | C8: =INDEX(REDESIGN_RESULTS!$E$8:$E$151,MATCH(WEIGHTS!$B$5&"__"&A8,REDESIGN_RESULTS!$A$8:$A$151,0)) | D8: =INDEX(REDESIGN_RESULTS!$F$8:$F$151,MATCH(WEIGHTS!$B$5&"__"&A8,REDESIGN_RESULTS!$A$8:$A$151,0)) | E8: =INDEX(REDESIGN_RESULTS!$G$8:$G$151,MATCH(WEIGHTS!$B$5&"__"&A8,REDESIGN_RESULTS!$A$8:$A$151,0)) | F8: COMPLETED DEVELOPMENT | G8: =WEIGHTS!B5&"__"&A8
A9: DTT | B9: =INDEX(REDESIGN_RESULTS!$D$8:$D$151,MATCH(WEIGHTS!$B$5&"__"&A9,REDESIGN_RESULTS!$A$8:$A$151,0)) | C9: =INDEX(REDESIGN_RESULTS!$E$8:$E$151,MATCH(WEIGHTS!$B$5&"__"&A9,REDESIGN_RESULTS!$A$8:$A$151,0)) | D9: =INDEX(REDESIGN_RESULTS!$F$8:$F$151,MATCH(WEIGHTS!$B$5&"__"&A9,REDESIGN_RESULTS!$A$8:$A$151,0)) | E9: =INDEX(REDESIGN_RESULTS!$G$8:$G$151,MATCH(WEIGHTS!$B$5&"__"&A9,REDESIGN_RESULTS!$A$8:$A$151,0)) | F9: COMPLETED DEVELOPMENT | G9: =WEIGHTS!B5&"__"&A9
A10: ECO | B10: =INDEX(REDESIGN_RESULTS!$D$8:$D$151,MATCH(WEIGHTS!$B$5&"__"&A10,REDESIGN_RESULTS!$A$8:$A$151,0)) | C10: =INDEX(REDESIGN_RESULTS!$E$8:$E$151,MATCH(WEIGHTS!$B$5&"__"&A10,REDESIGN_RESULTS!$A$8:$A$151,0)) | D10: =INDEX(REDESIGN_RESULTS!$F$8:$F$151,MATCH(WEIGHTS!$B$5&"__"&A10,REDESIGN_RESULTS!$A$8:$A$151,0)) | E10: =INDEX(REDESIGN_RESULTS!$G$8:$G$151,MATCH(WEIGHTS!$B$5&"__"&A10,REDESIGN_RESULTS!$A$8:$A$151,0)) | F10: COMPLETED DEVELOPMENT | G10: =WEIGHTS!B5&"__"&A10
A11: TECO10 | B11: =INDEX(REDESIGN_RESULTS!$D$8:$D$151,MATCH(WEIGHTS!$B$5&"__"&A11,REDESIGN_RESULTS!$A$8:$A$151,0)) | C11: =INDEX(REDESIGN_RESULTS!$E$8:$E$151,MATCH(WEIGHTS!$B$5&"__"&A11,REDESIGN_RESULTS!$A$8:$A$151,0)) | D11: =INDEX(REDESIGN_RESULTS!$F$8:$F$151,MATCH(WEIGHTS!$B$5&"__"&A11,REDESIGN_RESULTS!$A$8:$A$151,0)) | E11: =INDEX(REDESIGN_RESULTS!$G$8:$G$151,MATCH(WEIGHTS!$B$5&"__"&A11,REDESIGN_RESULTS!$A$8:$A$151,0)) | F11: COMPLETED DEVELOPMENT | G11: =WEIGHTS!B5&"__"&A11
A14: Population | B14: Primary requests 600–2400 s, followed until arrival.
A16: MCDM direction | B16: All criteria are costs. Only positive active weights contribute.

Sheet NORMALIZATION
A2: 2. Divide each criterion by its reference
A4: Fixed references retain common loss units across contexts. This is our additive-value scaling adaptation.
A5: Development context | B5: =WEIGHTS!B5 | D5: Preference profile | E5: =WEIGHTS!B6
A7: Policy | B7: Raw T | C7: T reference | D7: Normalized T | E7: Raw CO2 | F7: CO2 reference | G7: Normalized CO2 | H7: Raw distance | I7: Distance ref | J7: Normalized distance | K7: Raw P95 | L7: P95 reference | M7: Normalized P95 | N7: What it means
A8: =DECISION_MATRIX!A8 | B8: =DECISION_MATRIX!B8 | C8: =WEIGHTS!B22 | D8: =B8/C8 | E8: =DECISION_MATRIX!C8 | F8: =WEIGHTS!C22 | G8: =E8/F8 | H8: =DECISION_MATRIX!D8 | I8: =WEIGHTS!D22 | J8: =H8/I8 | K8: =DECISION_MATRIX!E8 | L8: =WEIGHTS!E22 | M8: =K8/L8 | N8: A value of 1 equals the common development reference; >1 is a larger cost.
A9: =DECISION_MATRIX!A9 | B9: =DECISION_MATRIX!B9 | C9: =WEIGHTS!B22 | D9: =B9/C9 | E9: =DECISION_MATRIX!C9 | F9: =WEIGHTS!C22 | G9: =E9/F9 | H9: =DECISION_MATRIX!D9 | I9: =WEIGHTS!D22 | J9: =H9/I9 | K9: =DECISION_MATRIX!E9 | L9: =WEIGHTS!E22 | M9: =K9/L9 | N9: A value of 1 equals the common development reference; >1 is a larger cost.
A10: =DECISION_MATRIX!A10 | B10: =DECISION_MATRIX!B10 | C10: =WEIGHTS!B22 | D10: =B10/C10 | E10: =DECISION_MATRIX!C10 | F10: =WEIGHTS!C22 | G10: =E10/F10 | H10: =DECISION_MATRIX!D10 | I10: =WEIGHTS!D22 | J10: =H10/I10 | K10: =DECISION_MATRIX!E10 | L10: =WEIGHTS!E22 | M10: =K10/L10 | N10: A value of 1 equals the common development reference; >1 is a larger cost.
A11: =DECISION_MATRIX!A11 | B11: =DECISION_MATRIX!B11 | C11: =WEIGHTS!B22 | D11: =B11/C11 | E11: =DECISION_MATRIX!C11 | F11: =WEIGHTS!C22 | G11: =E11/F11 | H11: =DECISION_MATRIX!D11 | I11: =WEIGHTS!D22 | J11: =H11/I11 | K11: =DECISION_MATRIX!E11 | L11: =WEIGHTS!E22 | M11: =K11/L11 | N11: A value of 1 equals the common development reference; >1 is a larger cost.
A15: Example formula | B15: =B8/C8
A17: Original source | B17: Additive value R15/R16; fixed ratio value function is our disclosed adaptation.

Sheet WEIGHTS
A2: The control panel: context, profile and references
A4: Amber cells are editable analytical assumptions; profiles are NOT elicited stakeholder preferences.
A5: Active context | B5: D011
A6: Active profile | B6: Balanced
A9: Declared profile | B9: Time | C9: CO2 | D9: Distance | E9: P95 | F9: Weight sum
A10: Balanced | B10: 0.5 | C10: 0.5 | D10: 0 | E10: 0 | F10: =SUM(B10:E10)
A11: Time-heavy | B11: 0.75 | C11: 0.25 | D11: 0 | E11: 0 | F11: =SUM(B11:E11)
A12: Environment-heavy | B12: 0.25 | C12: 0.75 | D12: 0 | E12: 0 | F12: =SUM(B12:E12)
A13: Distance-set | B13: 0.33333333 | C13: 0.33333333 | D13: 0.33333333 | E13: 0 | F13: =SUM(B13:E13)
A14: Tail-set | B14: 0.33333333 | C14: 0.33333333 | D14: 0 | E14: 0.33333333 | F14: =SUM(B14:E14)
A15: Tail-heavy | B15: 0.2 | C15: 0.2 | D15: 0 | E15: 0.6 | F15: =SUM(B15:E15)
A18: Active values | B18: Time | C18: CO2 | D18: Distance | E18: P95 | F18: Check
A19: Active weights | B19: =INDEX(B10:B15,MATCH($B$6,$A$10:$A$15,0)) | C19: =INDEX(C10:C15,MATCH($B$6,$A$10:$A$15,0)) | D19: =INDEX(D10:D15,MATCH($B$6,$A$10:$A$15,0)) | E19: =INDEX(E10:E15,MATCH($B$6,$A$10:$A$15,0)) | F19: =IF(AND(ABS(SUM(B19:E19)-1)<0.000000001,MIN(B19:E19)>=0),"OK","INVALID")
A22: Development references | B22: =SUMIF(REDESIGN_RESULTS!$H$8:$H$151,1,REDESIGN_RESULTS!$D$8:$D$151)/COUNTIF(REDESIGN_RESULTS!$H$8:$H$151,1) | C22: =SUMIF(REDESIGN_RESULTS!$H$8:$H$151,1,REDESIGN_RESULTS!$E$8:$E$151)/COUNTIF(REDESIGN_RESULTS!$H$8:$H$151,1) | D22: =SUMIF(REDESIGN_RESULTS!$H$8:$H$151,1,REDESIGN_RESULTS!$F$8:$F$151)/COUNTIF(REDESIGN_RESULTS!$H$8:$H$151,1) | E22: =SUMIF(REDESIGN_RESULTS!$H$8:$H$151,1,REDESIGN_RESULTS!$G$8:$G$151)/COUNTIF(REDESIGN_RESULTS!$H$8:$H$151,1)
A24: Reference meaning | B24: Equal mean over 24 x 4 development policy-context means; NOT final training scaling.
A26: Tie tolerance | B26: 1e-10
A27: Near-best tolerance | B27: 0.02 | C27: Illustrative loss units; inspect .01/.02/.05; not an elicited meaningful threshold.
A29: Primary recommendation | B29: Time + CO2. Distance/P95 profiles are development sensitivity only.
A31: VIKOR convention | B31: Kosijer eq11: min(0.25, 1/(m-1)); v=0.5; compare compromise sets.
A33: Scale caveat | B33: Cost increment per physical unit = weight/reference; weights alone do not state trade-offs.

Sheet MCDM_CALCULATION
A2: 3. Weight, add, rank, choose and calculate regret
A4: Smaller additive cost is preferred. All calculations remain visible and traceable.
A5: Development context | B5: =WEIGHTS!B5 | D5: Preference profile | E5: =WEIGHTS!B6
A7: Policy | B7: Norm time | C7: Norm CO2 | D7: Norm distance | E7: Norm P95 | F7: w time | G7: w CO2 | H7: w distance | I7: w P95 | J7: Contribution T | K7: Contribution CO2 | L7: Contribution distance | M7: Contribution P95 | N7: Final cost
A8: =DECISION_MATRIX!A8 | B8: =NORMALIZATION!D8 | C8: =NORMALIZATION!G8 | D8: =NORMALIZATION!J8 | E8: =NORMALIZATION!M8 | F8: =WEIGHTS!B19 | G8: =WEIGHTS!C19 | H8: =WEIGHTS!D19 | I8: =WEIGHTS!E19 | J8: =B8*F8 | K8: =C8*G8 | L8: =D8*H8 | M8: =E8*I8 | N8: =IF(WEIGHTS!F19="OK",SUM(J8:M8),"INVALID WEIGHTS")
A9: =DECISION_MATRIX!A9 | B9: =NORMALIZATION!D9 | C9: =NORMALIZATION!G9 | D9: =NORMALIZATION!J9 | E9: =NORMALIZATION!M9 | F9: =WEIGHTS!B19 | G9: =WEIGHTS!C19 | H9: =WEIGHTS!D19 | I9: =WEIGHTS!E19 | J9: =B9*F9 | K9: =C9*G9 | L9: =D9*H9 | M9: =E9*I9 | N9: =IF(WEIGHTS!F19="OK",SUM(J9:M9),"INVALID WEIGHTS")
A10: =DECISION_MATRIX!A10 | B10: =NORMALIZATION!D10 | C10: =NORMALIZATION!G10 | D10: =NORMALIZATION!J10 | E10: =NORMALIZATION!M10 | F10: =WEIGHTS!B19 | G10: =WEIGHTS!C19 | H10: =WEIGHTS!D19 | I10: =WEIGHTS!E19 | J10: =B10*F10 | K10: =C10*G10 | L10: =D10*H10 | M10: =E10*I10 | N10: =IF(WEIGHTS!F19="OK",SUM(J10:M10),"INVALID WEIGHTS")
A11: =DECISION_MATRIX!A11 | B11: =NORMALIZATION!D11 | C11: =NORMALIZATION!G11 | D11: =NORMALIZATION!J11 | E11: =NORMALIZATION!M11 | F11: =WEIGHTS!B19 | G11: =WEIGHTS!C19 | H11: =WEIGHTS!D19 | I11: =WEIGHTS!E19 | J11: =B11*F11 | K11: =C11*G11 | L11: =D11*H11 | M11: =E11*I11 | N11: =IF(WEIGHTS!F19="OK",SUM(J11:M11),"INVALID WEIGHTS")
A15: Policy | B15: Final cost | C15: Numerical rank | D15: Regret | E15: Near-best?
A16: =A8 | B16: =N8 | C16: =COUNTIF($B$16:$B$19,"<"&(B16-WEIGHTS!$B$26))+1 | D16: =B16-MIN($B$16:$B$19) | E16: =IF(D16<=WEIGHTS!$B$27,"YES","NO")
A17: =A9 | B17: =N9 | C17: =COUNTIF($B$16:$B$19,"<"&(B17-WEIGHTS!$B$26))+1 | D17: =B17-MIN($B$16:$B$19) | E17: =IF(D17<=WEIGHTS!$B$27,"YES","NO")
A18: =A10 | B18: =N10 | C18: =COUNTIF($B$16:$B$19,"<"&(B18-WEIGHTS!$B$26))+1 | D18: =B18-MIN($B$16:$B$19) | E18: =IF(D18<=WEIGHTS!$B$27,"YES","NO")
A19: =A11 | B19: =N11 | C19: =COUNTIF($B$16:$B$19,"<"&(B19-WEIGHTS!$B$26))+1 | D19: =B19-MIN($B$16:$B$19) | E19: =IF(D19<=WEIGHTS!$B$27,"YES","NO")
A22: Selected policy | B22: =INDEX(A16:A19,MATCH(MIN(C16:C19),C16:C19,0))
A24: Score formula | B24: =SUM(J8:M8)
A26: Regret formula | B26: =B16-MIN($B$16:$B$19)
A28: Tie rule | B28: First declared policy among numerical rank 1; near-best is separately defined.

Sheet MCDM_METHOD_COMPARISON
A2: VIKOR sensitivity: follow the actual cited variant
A4: Kosijer et al. 2012, §3.3, eqs7–11. This is within-context compromise ranking, not common-scale scenario regret.
A5: Development context | B5: =WEIGHTS!B5 | D5: Preference profile | E5: =WEIGHTS!B6
A7: Policy | B7: Weighted loss T | C7: Weighted loss CO2 | D7: Weighted loss distance | E7: Weighted loss P95 | F7: S sum | G7: R maximum | H7: Scaled S | I7: Scaled R | J7: Q v=.5 | K7: Q v=.25 | L7: Q v=.75 | M7: Q rank
A8: =DECISION_MATRIX!A8 | B8: =IF(MAX(DECISION_MATRIX!$B$8:$B$11)=MIN(DECISION_MATRIX!$B$8:$B$11),0,(DECISION_MATRIX!B8-MIN(DECISION_MATRIX!$B$8:$B$11))/(MAX(DECISION_MATRIX!$B$8:$B$11)-MIN(DECISION_MATRIX!$B$8:$B$11))*WEIGHTS!B19) | C8: =IF(MAX(DECISION_MATRIX!$C$8:$C$11)=MIN(DECISION_MATRIX!$C$8:$C$11),0,(DECISION_MATRIX!C8-MIN(DECISION_MATRIX!$C$8:$C$11))/(MAX(DECISION_MATRIX!$C$8:$C$11)-MIN(DECISION_MATRIX!$C$8:$C$11))*WEIGHTS!C19) | D8: =IF(MAX(DECISION_MATRIX!$D$8:$D$11)=MIN(DECISION_MATRIX!$D$8:$D$11),0,(DECISION_MATRIX!D8-MIN(DECISION_MATRIX!$D$8:$D$11))/(MAX(DECISION_MATRIX!$D$8:$D$11)-MIN(DECISION_MATRIX!$D$8:$D$11))*WEIGHTS!D19) | E8: =IF(MAX(DECISION_MATRIX!$E$8:$E$11)=MIN(DECISION_MATRIX!$E$8:$E$11),0,(DECISION_MATRIX!E8-MIN(DECISION_MATRIX!$E$8:$E$11))/(MAX(DECISION_MATRIX!$E$8:$E$11)-MIN(DECISION_MATRIX!$E$8:$E$11))*WEIGHTS!E19) | F8: =SUM(B8:E8) | G8: =MAX(B8:E8) | H8: =IF(MAX($F$8:$F$11)=MIN($F$8:$F$11),0,(F8-MIN($F$8:$F$11))/(MAX($F$8:$F$11)-MIN($F$8:$F$11))) | I8: =IF(MAX($G$8:$G$11)=MIN($G$8:$G$11),0,(G8-MIN($G$8:$G$11))/(MAX($G$8:$G$11)-MIN($G$8:$G$11))) | J8: =0.5*H8+0.5*I8 | K8: =0.25*H8+0.75*I8 | L8: =0.75*H8+0.25*I8 | M8: =COUNTIF($J$8:$J$11,"<"&J8)+1
A9: =DECISION_MATRIX!A9 | B9: =IF(MAX(DECISION_MATRIX!$B$8:$B$11)=MIN(DECISION_MATRIX!$B$8:$B$11),0,(DECISION_MATRIX!B9-MIN(DECISION_MATRIX!$B$8:$B$11))/(MAX(DECISION_MATRIX!$B$8:$B$11)-MIN(DECISION_MATRIX!$B$8:$B$11))*WEIGHTS!B19) | C9: =IF(MAX(DECISION_MATRIX!$C$8:$C$11)=MIN(DECISION_MATRIX!$C$8:$C$11),0,(DECISION_MATRIX!C9-MIN(DECISION_MATRIX!$C$8:$C$11))/(MAX(DECISION_MATRIX!$C$8:$C$11)-MIN(DECISION_MATRIX!$C$8:$C$11))*WEIGHTS!C19) | D9: =IF(MAX(DECISION_MATRIX!$D$8:$D$11)=MIN(DECISION_MATRIX!$D$8:$D$11),0,(DECISION_MATRIX!D9-MIN(DECISION_MATRIX!$D$8:$D$11))/(MAX(DECISION_MATRIX!$D$8:$D$11)-MIN(DECISION_MATRIX!$D$8:$D$11))*WEIGHTS!D19) | E9: =IF(MAX(DECISION_MATRIX!$E$8:$E$11)=MIN(DECISION_MATRIX!$E$8:$E$11),0,(DECISION_MATRIX!E9-MIN(DECISION_MATRIX!$E$8:$E$11))/(MAX(DECISION_MATRIX!$E$8:$E$11)-MIN(DECISION_MATRIX!$E$8:$E$11))*WEIGHTS!E19) | F9: =SUM(B9:E9) | G9: =MAX(B9:E9) | H9: =IF(MAX($F$8:$F$11)=MIN($F$8:$F$11),0,(F9-MIN($F$8:$F$11))/(MAX($F$8:$F$11)-MIN($F$8:$F$11))) | I9: =IF(MAX($G$8:$G$11)=MIN($G$8:$G$11),0,(G9-MIN($G$8:$G$11))/(MAX($G$8:$G$11)-MIN($G$8:$G$11))) | J9: =0.5*H9+0.5*I9 | K9: =0.25*H9+0.75*I9 | L9: =0.75*H9+0.25*I9 | M9: =COUNTIF($J$8:$J$11,"<"&J9)+1
A10: =DECISION_MATRIX!A10 | B10: =IF(MAX(DECISION_MATRIX!$B$8:$B$11)=MIN(DECISION_MATRIX!$B$8:$B$11),0,(DECISION_MATRIX!B10-MIN(DECISION_MATRIX!$B$8:$B$11))/(MAX(DECISION_MATRIX!$B$8:$B$11)-MIN(DECISION_MATRIX!$B$8:$B$11))*WEIGHTS!B19) | C10: =IF(MAX(DECISION_MATRIX!$C$8:$C$11)=MIN(DECISION_MATRIX!$C$8:$C$11),0,(DECISION_MATRIX!C10-MIN(DECISION_MATRIX!$C$8:$C$11))/(MAX(DECISION_MATRIX!$C$8:$C$11)-MIN(DECISION_MATRIX!$C$8:$C$11))*WEIGHTS!C19) | D10: =IF(MAX(DECISION_MATRIX!$D$8:$D$11)=MIN(DECISION_MATRIX!$D$8:$D$11),0,(DECISION_MATRIX!D10-MIN(DECISION_MATRIX!$D$8:$D$11))/(MAX(DECISION_MATRIX!$D$8:$D$11)-MIN(DECISION_MATRIX!$D$8:$D$11))*WEIGHTS!D19) | E10: =IF(MAX(DECISION_MATRIX!$E$8:$E$11)=MIN(DECISION_MATRIX!$E$8:$E$11),0,(DECISION_MATRIX!E10-MIN(DECISION_MATRIX!$E$8:$E$11))/(MAX(DECISION_MATRIX!$E$8:$E$11)-MIN(DECISION_MATRIX!$E$8:$E$11))*WEIGHTS!E19) | F10: =SUM(B10:E10) | G10: =MAX(B10:E10) | H10: =IF(MAX($F$8:$F$11)=MIN($F$8:$F$11),0,(F10-MIN($F$8:$F$11))/(MAX($F$8:$F$11)-MIN($F$8:$F$11))) | I10: =IF(MAX($G$8:$G$11)=MIN($G$8:$G$11),0,(G10-MIN($G$8:$G$11))/(MAX($G$8:$G$11)-MIN($G$8:$G$11))) | J10: =0.5*H10+0.5*I10 | K10: =0.25*H10+0.75*I10 | L10: =0.75*H10+0.25*I10 | M10: =COUNTIF($J$8:$J$11,"<"&J10)+1
A11: =DECISION_MATRIX!A11 | B11: =IF(MAX(DECISION_MATRIX!$B$8:$B$11)=MIN(DECISION_MATRIX!$B$8:$B$11),0,(DECISION_MATRIX!B11-MIN(DECISION_MATRIX!$B$8:$B$11))/(MAX(DECISION_MATRIX!$B$8:$B$11)-MIN(DECISION_MATRIX!$B$8:$B$11))*WEIGHTS!B19) | C11: =IF(MAX(DECISION_MATRIX!$C$8:$C$11)=MIN(DECISION_MATRIX!$C$8:$C$11),0,(DECISION_MATRIX!C11-MIN(DECISION_MATRIX!$C$8:$C$11))/(MAX(DECISION_MATRIX!$C$8:$C$11)-MIN(DECISION_MATRIX!$C$8:$C$11))*WEIGHTS!C19) | D11: =IF(MAX(DECISION_MATRIX!$D$8:$D$11)=MIN(DECISION_MATRIX!$D$8:$D$11),0,(DECISION_MATRIX!D11-MIN(DECISION_MATRIX!$D$8:$D$11))/(MAX(DECISION_MATRIX!$D$8:$D$11)-MIN(DECISION_MATRIX!$D$8:$D$11))*WEIGHTS!D19) | E11: =IF(MAX(DECISION_MATRIX!$E$8:$E$11)=MIN(DECISION_MATRIX!$E$8:$E$11),0,(DECISION_MATRIX!E11-MIN(DECISION_MATRIX!$E$8:$E$11))/(MAX(DECISION_MATRIX!$E$8:$E$11)-MIN(DECISION_MATRIX!$E$8:$E$11))*WEIGHTS!E19) | F11: =SUM(B11:E11) | G11: =MAX(B11:E11) | H11: =IF(MAX($F$8:$F$11)=MIN($F$8:$F$11),0,(F11-MIN($F$8:$F$11))/(MAX($F$8:$F$11)-MIN($F$8:$F$11))) | I11: =IF(MAX($G$8:$G$11)=MIN($G$8:$G$11),0,(G11-MIN($G$8:$G$11))/(MAX($G$8:$G$11)-MIN($G$8:$G$11))) | J11: =0.5*H11+0.5*I11 | K11: =0.25*H11+0.75*I11 | L11: =0.75*H11+0.25*I11 | M11: =COUNTIF($J$8:$J$11,"<"&J11)+1
A14: Primary SAW choice | B14: =MCDM_CALCULATION!B22
A15: VIKOR first | B15: =INDEX(A8:A11,MATCH(MIN(J8:J11),J8:J11,0))
A16: First row index | B16: =MATCH(B15,A8:A11,0)
A17: DQ threshold | B17: =MIN(0.25,1/(COUNT(J8:J11)-1))
A18: Sufficient advantage? | B18: =SMALL(J8:J11,2)-MIN(J8:J11)>=B17-0.000000000001
A19: Sufficient stability? | B19: =OR(INDEX(F8:F11,B16)<=MIN(F8:F11)+0.000000000001,INDEX(G8:G11,B16)<=MIN(G8:G11)+0.000000000001,AND(INDEX(K8:K11,B16)<=MIN(K8:K11)+0.000000000001,INDEX(L8:L11,B16)<=MIN(L8:L11)+0.000000000001))
A22: Policy | B22: Q score | C22: Compromise member? | D22: Interpretation
A23: =A8 | B23: =J8 | C23: =IF(AND($B$18,$B$19),A23=$B$15,IF(NOT($B$18),B23-MIN($J$8:$J$11)<$B$17,B23<=SMALL($J$8:$J$11,2))) | D23: If acceptance fails, show the compromise set rather than a unique winner.
A24: =A9 | B24: =J9 | C24: =IF(AND($B$18,$B$19),A24=$B$15,IF(NOT($B$18),B24-MIN($J$8:$J$11)<$B$17,B24<=SMALL($J$8:$J$11,2))) | D24: If acceptance fails, show the compromise set rather than a unique winner.
A25: =A10 | B25: =J10 | C25: =IF(AND($B$18,$B$19),A25=$B$15,IF(NOT($B$18),B25-MIN($J$8:$J$11)<$B$17,B25<=SMALL($J$8:$J$11,2))) | D25: If acceptance fails, show the compromise set rather than a unique winner.
A26: =A11 | B26: =J11 | C26: =IF(AND($B$18,$B$19),A26=$B$15,IF(NOT($B$18),B26-MIN($J$8:$J$11)<$B$17,B26<=SMALL($J$8:$J$11,2))) | D26: If acceptance fails, show the compromise set rather than a unique winner.
A28: SAW in compromise set? | B28: =INDEX(C23:C26,MATCH(B14,A23:A26,0))
A30: Constant-column rule | B30: Zero loss for a constant criterion; zero range in S/R contributes zero. Explicit numerical convention.
A32: TOPSIS / PROMETHEE | B32: Literature comparison only; no unsupported numeric rankings.

Sheet SENSITIVITY
A2: Preferences, criterion sets and TECO allowance
A4: Sensitivity is calculated on development data. No profile is chosen to improve ML test performance.
A5: Development context | B5: =WEIGHTS!B5 | D5: Preference profile | E5: =WEIGHTS!B6
A7: Profile | B7: Time weight | C7: CO2 weight | D7: Distance weight | E7: P95 weight | F7: SP cost | G7: DTT cost | H7: ECO cost | I7: TECO10 cost | J7: Selected policy
A8: =WEIGHTS!A10 | B8: =WEIGHTS!B10 | C8: =WEIGHTS!C10 | D8: =WEIGHTS!D10 | E8: =WEIGHTS!E10 | F8: =SUMPRODUCT($B8:$E8,MCDM_CALCULATION!B8:E8) | G8: =SUMPRODUCT($B8:$E8,MCDM_CALCULATION!B9:E9) | H8: =SUMPRODUCT($B8:$E8,MCDM_CALCULATION!B10:E10) | I8: =SUMPRODUCT($B8:$E8,MCDM_CALCULATION!B11:E11) | J8: =INDEX($F$7:$I$7,1,MATCH(MIN(F8:I8),F8:I8,0))
A9: =WEIGHTS!A11 | B9: =WEIGHTS!B11 | C9: =WEIGHTS!C11 | D9: =WEIGHTS!D11 | E9: =WEIGHTS!E11 | F9: =SUMPRODUCT($B9:$E9,MCDM_CALCULATION!B8:E8) | G9: =SUMPRODUCT($B9:$E9,MCDM_CALCULATION!B9:E9) | H9: =SUMPRODUCT($B9:$E9,MCDM_CALCULATION!B10:E10) | I9: =SUMPRODUCT($B9:$E9,MCDM_CALCULATION!B11:E11) | J9: =INDEX($F$7:$I$7,1,MATCH(MIN(F9:I9),F9:I9,0))
A10: =WEIGHTS!A12 | B10: =WEIGHTS!B12 | C10: =WEIGHTS!C12 | D10: =WEIGHTS!D12 | E10: =WEIGHTS!E12 | F10: =SUMPRODUCT($B10:$E10,MCDM_CALCULATION!B8:E8) | G10: =SUMPRODUCT($B10:$E10,MCDM_CALCULATION!B9:E9) | H10: =SUMPRODUCT($B10:$E10,MCDM_CALCULATION!B10:E10) | I10: =SUMPRODUCT($B10:$E10,MCDM_CALCULATION!B11:E11) | J10: =INDEX($F$7:$I$7,1,MATCH(MIN(F10:I10),F10:I10,0))
A11: =WEIGHTS!A13 | B11: =WEIGHTS!B13 | C11: =WEIGHTS!C13 | D11: =WEIGHTS!D13 | E11: =WEIGHTS!E13 | F11: =SUMPRODUCT($B11:$E11,MCDM_CALCULATION!B8:E8) | G11: =SUMPRODUCT($B11:$E11,MCDM_CALCULATION!B9:E9) | H11: =SUMPRODUCT($B11:$E11,MCDM_CALCULATION!B10:E10) | I11: =SUMPRODUCT($B11:$E11,MCDM_CALCULATION!B11:E11) | J11: =INDEX($F$7:$I$7,1,MATCH(MIN(F11:I11),F11:I11,0))
A12: =WEIGHTS!A14 | B12: =WEIGHTS!B14 | C12: =WEIGHTS!C14 | D12: =WEIGHTS!D14 | E12: =WEIGHTS!E14 | F12: =SUMPRODUCT($B12:$E12,MCDM_CALCULATION!B8:E8) | G12: =SUMPRODUCT($B12:$E12,MCDM_CALCULATION!B9:E9) | H12: =SUMPRODUCT($B12:$E12,MCDM_CALCULATION!B10:E10) | I12: =SUMPRODUCT($B12:$E12,MCDM_CALCULATION!B11:E11) | J12: =INDEX($F$7:$I$7,1,MATCH(MIN(F12:I12),F12:I12,0))
A13: =WEIGHTS!A15 | B13: =WEIGHTS!B15 | C13: =WEIGHTS!C15 | D13: =WEIGHTS!D15 | E13: =WEIGHTS!E15 | F13: =SUMPRODUCT($B13:$E13,MCDM_CALCULATION!B8:E8) | G13: =SUMPRODUCT($B13:$E13,MCDM_CALCULATION!B9:E9) | H13: =SUMPRODUCT($B13:$E13,MCDM_CALCULATION!B10:E10) | I13: =SUMPRODUCT($B13:$E13,MCDM_CALCULATION!B11:E11) | J13: =INDEX($F$7:$I$7,1,MATCH(MIN(F13:I13),F13:I13,0))
A17: Time weight | B17: Environment weight | C17: SP | D17: DTT | E17: ECO | F17: TECO10 | G17: Selected policy
A18: 0 | B18: =1-A18 | C18: =A18*MCDM_CALCULATION!B8+B18*MCDM_CALCULATION!C8 | D18: =A18*MCDM_CALCULATION!B9+B18*MCDM_CALCULATION!C9 | E18: =A18*MCDM_CALCULATION!B10+B18*MCDM_CALCULATION!C10 | F18: =A18*MCDM_CALCULATION!B11+B18*MCDM_CALCULATION!C11 | G18: =INDEX($C$17:$F$17,1,MATCH(MIN(C18:F18),C18:F18,0))
A19: 0.05 | B19: =1-A19 | C19: =A19*MCDM_CALCULATION!B8+B19*MCDM_CALCULATION!C8 | D19: =A19*MCDM_CALCULATION!B9+B19*MCDM_CALCULATION!C9 | E19: =A19*MCDM_CALCULATION!B10+B19*MCDM_CALCULATION!C10 | F19: =A19*MCDM_CALCULATION!B11+B19*MCDM_CALCULATION!C11 | G19: =INDEX($C$17:$F$17,1,MATCH(MIN(C19:F19),C19:F19,0))
A20: 0.1 | B20: =1-A20 | C20: =A20*MCDM_CALCULATION!B8+B20*MCDM_CALCULATION!C8 | D20: =A20*MCDM_CALCULATION!B9+B20*MCDM_CALCULATION!C9 | E20: =A20*MCDM_CALCULATION!B10+B20*MCDM_CALCULATION!C10 | F20: =A20*MCDM_CALCULATION!B11+B20*MCDM_CALCULATION!C11 | G20: =INDEX($C$17:$F$17,1,MATCH(MIN(C20:F20),C20:F20,0))
A21: 0.15 | B21: =1-A21 | C21: =A21*MCDM_CALCULATION!B8+B21*MCDM_CALCULATION!C8 | D21: =A21*MCDM_CALCULATION!B9+B21*MCDM_CALCULATION!C9 | E21: =A21*MCDM_CALCULATION!B10+B21*MCDM_CALCULATION!C10 | F21: =A21*MCDM_CALCULATION!B11+B21*MCDM_CALCULATION!C11 | G21: =INDEX($C$17:$F$17,1,MATCH(MIN(C21:F21),C21:F21,0))
A22: 0.2 | B22: =1-A22 | C22: =A22*MCDM_CALCULATION!B8+B22*MCDM_CALCULATION!C8 | D22: =A22*MCDM_CALCULATION!B9+B22*MCDM_CALCULATION!C9 | E22: =A22*MCDM_CALCULATION!B10+B22*MCDM_CALCULATION!C10 | F22: =A22*MCDM_CALCULATION!B11+B22*MCDM_CALCULATION!C11 | G22: =INDEX($C$17:$F$17,1,MATCH(MIN(C22:F22),C22:F22,0))
A23: 0.25 | B23: =1-A23 | C23: =A23*MCDM_CALCULATION!B8+B23*MCDM_CALCULATION!C8 | D23: =A23*MCDM_CALCULATION!B9+B23*MCDM_CALCULATION!C9 | E23: =A23*MCDM_CALCULATION!B10+B23*MCDM_CALCULATION!C10 | F23: =A23*MCDM_CALCULATION!B11+B23*MCDM_CALCULATION!C11 | G23: =INDEX($C$17:$F$17,1,MATCH(MIN(C23:F23),C23:F23,0))
A24: 0.3 | B24: =1-A24 | C24: =A24*MCDM_CALCULATION!B8+B24*MCDM_CALCULATION!C8 | D24: =A24*MCDM_CALCULATION!B9+B24*MCDM_CALCULATION!C9 | E24: =A24*MCDM_CALCULATION!B10+B24*MCDM_CALCULATION!C10 | F24: =A24*MCDM_CALCULATION!B11+B24*MCDM_CALCULATION!C11 | G24: =INDEX($C$17:$F$17,1,MATCH(MIN(C24:F24),C24:F24,0))
A25: 0.35 | B25: =1-A25 | C25: =A25*MCDM_CALCULATION!B8+B25*MCDM_CALCULATION!C8 | D25: =A25*MCDM_CALCULATION!B9+B25*MCDM_CALCULATION!C9 | E25: =A25*MCDM_CALCULATION!B10+B25*MCDM_CALCULATION!C10 | F25: =A25*MCDM_CALCULATION!B11+B25*MCDM_CALCULATION!C11 | G25: =INDEX($C$17:$F$17,1,MATCH(MIN(C25:F25),C25:F25,0))
A26: 0.4 | B26: =1-A26 | C26: =A26*MCDM_CALCULATION!B8+B26*MCDM_CALCULATION!C8 | D26: =A26*MCDM_CALCULATION!B9+B26*MCDM_CALCULATION!C9 | E26: =A26*MCDM_CALCULATION!B10+B26*MCDM_CALCULATION!C10 | F26: =A26*MCDM_CALCULATION!B11+B26*MCDM_CALCULATION!C11 | G26: =INDEX($C$17:$F$17,1,MATCH(MIN(C26:F26),C26:F26,0))
A27: 0.45 | B27: =1-A27 | C27: =A27*MCDM_CALCULATION!B8+B27*MCDM_CALCULATION!C8 | D27: =A27*MCDM_CALCULATION!B9+B27*MCDM_CALCULATION!C9 | E27: =A27*MCDM_CALCULATION!B10+B27*MCDM_CALCULATION!C10 | F27: =A27*MCDM_CALCULATION!B11+B27*MCDM_CALCULATION!C11 | G27: =INDEX($C$17:$F$17,1,MATCH(MIN(C27:F27),C27:F27,0))
A28: 0.5 | B28: =1-A28 | C28: =A28*MCDM_CALCULATION!B8+B28*MCDM_CALCULATION!C8 | D28: =A28*MCDM_CALCULATION!B9+B28*MCDM_CALCULATION!C9 | E28: =A28*MCDM_CALCULATION!B10+B28*MCDM_CALCULATION!C10 | F28: =A28*MCDM_CALCULATION!B11+B28*MCDM_CALCULATION!C11 | G28: =INDEX($C$17:$F$17,1,MATCH(MIN(C28:F28),C28:F28,0))
A29: 0.55 | B29: =1-A29 | C29: =A29*MCDM_CALCULATION!B8+B29*MCDM_CALCULATION!C8 | D29: =A29*MCDM_CALCULATION!B9+B29*MCDM_CALCULATION!C9 | E29: =A29*MCDM_CALCULATION!B10+B29*MCDM_CALCULATION!C10 | F29: =A29*MCDM_CALCULATION!B11+B29*MCDM_CALCULATION!C11 | G29: =INDEX($C$17:$F$17,1,MATCH(MIN(C29:F29),C29:F29,0))
A30: 0.6 | B30: =1-A30 | C30: =A30*MCDM_CALCULATION!B8+B30*MCDM_CALCULATION!C8 | D30: =A30*MCDM_CALCULATION!B9+B30*MCDM_CALCULATION!C9 | E30: =A30*MCDM_CALCULATION!B10+B30*MCDM_CALCULATION!C10 | F30: =A30*MCDM_CALCULATION!B11+B30*MCDM_CALCULATION!C11 | G30: =INDEX($C$17:$F$17,1,MATCH(MIN(C30:F30),C30:F30,0))
A31: 0.65 | B31: =1-A31 | C31: =A31*MCDM_CALCULATION!B8+B31*MCDM_CALCULATION!C8 | D31: =A31*MCDM_CALCULATION!B9+B31*MCDM_CALCULATION!C9 | E31: =A31*MCDM_CALCULATION!B10+B31*MCDM_CALCULATION!C10 | F31: =A31*MCDM_CALCULATION!B11+B31*MCDM_CALCULATION!C11 | G31: =INDEX($C$17:$F$17,1,MATCH(MIN(C31:F31),C31:F31,0))
A32: 0.7 | B32: =1-A32 | C32: =A32*MCDM_CALCULATION!B8+B32*MCDM_CALCULATION!C8 | D32: =A32*MCDM_CALCULATION!B9+B32*MCDM_CALCULATION!C9 | E32: =A32*MCDM_CALCULATION!B10+B32*MCDM_CALCULATION!C10 | F32: =A32*MCDM_CALCULATION!B11+B32*MCDM_CALCULATION!C11 | G32: =INDEX($C$17:$F$17,1,MATCH(MIN(C32:F32),C32:F32,0))
A33: 0.75 | B33: =1-A33 | C33: =A33*MCDM_CALCULATION!B8+B33*MCDM_CALCULATION!C8 | D33: =A33*MCDM_CALCULATION!B9+B33*MCDM_CALCULATION!C9 | E33: =A33*MCDM_CALCULATION!B10+B33*MCDM_CALCULATION!C10 | F33: =A33*MCDM_CALCULATION!B11+B33*MCDM_CALCULATION!C11 | G33: =INDEX($C$17:$F$17,1,MATCH(MIN(C33:F33),C33:F33,0))
A34: 0.8 | B34: =1-A34 | C34: =A34*MCDM_CALCULATION!B8+B34*MCDM_CALCULATION!C8 | D34: =A34*MCDM_CALCULATION!B9+B34*MCDM_CALCULATION!C9 | E34: =A34*MCDM_CALCULATION!B10+B34*MCDM_CALCULATION!C10 | F34: =A34*MCDM_CALCULATION!B11+B34*MCDM_CALCULATION!C11 | G34: =INDEX($C$17:$F$17,1,MATCH(MIN(C34:F34),C34:F34,0))
A35: 0.85 | B35: =1-A35 | C35: =A35*MCDM_CALCULATION!B8+B35*MCDM_CALCULATION!C8 | D35: =A35*MCDM_CALCULATION!B9+B35*MCDM_CALCULATION!C9 | E35: =A35*MCDM_CALCULATION!B10+B35*MCDM_CALCULATION!C10 | F35: =A35*MCDM_CALCULATION!B11+B35*MCDM_CALCULATION!C11 | G35: =INDEX($C$17:$F$17,1,MATCH(MIN(C35:F35),C35:F35,0))
A36: 0.9 | B36: =1-A36 | C36: =A36*MCDM_CALCULATION!B8+B36*MCDM_CALCULATION!C8 | D36: =A36*MCDM_CALCULATION!B9+B36*MCDM_CALCULATION!C9 | E36: =A36*MCDM_CALCULATION!B10+B36*MCDM_CALCULATION!C10 | F36: =A36*MCDM_CALCULATION!B11+B36*MCDM_CALCULATION!C11 | G36: =INDEX($C$17:$F$17,1,MATCH(MIN(C36:F36),C36:F36,0))
A37: 0.95 | B37: =1-A37 | C37: =A37*MCDM_CALCULATION!B8+B37*MCDM_CALCULATION!C8 | D37: =A37*MCDM_CALCULATION!B9+B37*MCDM_CALCULATION!C9 | E37: =A37*MCDM_CALCULATION!B10+B37*MCDM_CALCULATION!C10 | F37: =A37*MCDM_CALCULATION!B11+B37*MCDM_CALCULATION!C11 | G37: =INDEX($C$17:$F$17,1,MATCH(MIN(C37:F37),C37:F37,0))
A38: 1 | B38: =1-A38 | C38: =A38*MCDM_CALCULATION!B8+B38*MCDM_CALCULATION!C8 | D38: =A38*MCDM_CALCULATION!B9+B38*MCDM_CALCULATION!C9 | E38: =A38*MCDM_CALCULATION!B10+B38*MCDM_CALCULATION!C10 | F38: =A38*MCDM_CALCULATION!B11+B38*MCDM_CALCULATION!C11 | G38: =INDEX($C$17:$F$17,1,MATCH(MIN(C38:F38),C38:F38,0))
A43: TECO setting | B43: Mean time (s) | C43: Mean CO2 (g) | D43: Mean P95 (s) | E43: CO2 WAPE, run mean | F43: Realized above predicted time bound
A44: TECO05 | B44: 475.66715 | C44: 1197.7508 | D44: 672.75694 | E44: 0.15482071 | F44: 0.54121055
A45: TECO10 | B45: 564.93316 | C45: 1268.2908 | D45: 800.89792 | E45: 0.12827788 | F45: 0.35551597
A46: TECO15 | B46: 590.31772 | C46: 1349.4213 | D46: 834.88472 | E46: 0.12131926 | F46: 0.26133454
A49: TECO interpretation | B49: These are observed development effects, not guaranteed realized detour bounds. No final alpha is frozen.
A52: Full-design diagnostic | B52: Balanced / time-heavy / environment-heavy winners are identical in all 24 contexts.
A54: Broad 0..1 sweep | B54: Only 1 of 24 contexts changes winner over the 0.05-spaced two-criterion weight sweep.
A56: Third criteria | B56: Distance-set changes 0/24 balanced choices; Tail-set changes 1/24.

Sheet ML_SELECTION
A2: New selector is NOT FITTED
A4: Main release is blocked by route-order validation; these cells are deliberately not invented predictions.
A7: Stage | B7: Context count | C7: Role | D7: Model status | E7: Evidence
A8: Pilot | B8: 30 | C8: 21 training / 9 test; frozen historical model | D8: ALREADY COMPLETED | E8: Always DTT; no positive adaptive gain
A9: Current development | B9: 24 | C9: Engineering / complementarity diagnostics | D9: NOT USED TO CLAIM TEST GAIN | E9: 432 runs + separate route probes
A10: Candidate main training | B10: 84 | C10: Fit scaled multi-output CART | D10: TO BE GENERATED | E10: No new main data
A11: Candidate validation | B11: 28 | C11: One prespecified model check / lock | D11: TO BE GENERATED | E11: Do not alter test from this result
A12: Candidate test | B12: 28 | C12: One held-out observed decision evaluation | D12: TO BE GENERATED | E12: No new predictions or losses
A16: Feature | B16: Available when? | C16: Encoding | D16: Leakage restriction
A17: Primary demand | B17: Scheduled before episode | C17: Numeric veh/h | D17: No future realized demand outcome
A18: Background per stream | B18: Scheduled before episode | C18: Numeric veh/h | D18: Same manifest across compared policies
A19: Restriction location | B19: Known planned restriction | C19: One-hot location | D19: Unannounced incidents require separate detection study
A20: Restriction speed ratio | B20: Known planned control | C20: Numeric 0.35/0.65 or1 | D20: No future realized queue
A21: Signal regime | B21: Controller plan known | C21: Binary regime | D21: No realized travel times/emissions
A24: Recommended task | B24: Predict all policy outcomes; apply the same frozen preferences to predictions; evaluate chosen policy on observed test outcomes.
A27: Recommended model | B27: CART depth3, min leaf8, training-only scaled outputs. Constant training-mean prediction baseline.
A30: Why regression? | B30: Reusable across declared weights; direct labels conflate preferences and physical prediction.
A33: Grouping | B33: All replications of a context together. 140 contexts remain 140 ML examples, not 2,800.
A36: Test meaning | B36: Held-out factor combinations in the same synthetic network/range; not city transfer or out-of-range extrapolation.

Sheet ROBUSTNESS
A2: Descriptive development headroom; no new ML result
A4: Fixed and oracle calculated on the same development matrix: descriptive opportunity, NOT held-out performance.
A7: Context | B7: SP cost | C7: DTT cost | D7: ECO cost | E7: TECO10 cost | F7: Oracle cost | G7: SP regret | H7: DTT regret | I7: ECO regret | J7: TECO10 regret | K7: Winner | L7: Fixed DTT headroom
A8: D001 | B8: =REDESIGN_RESULTS!D8/WEIGHTS!$B$22*WEIGHTS!$B$19+REDESIGN_RESULTS!E8/WEIGHTS!$C$22*WEIGHTS!$C$19+REDESIGN_RESULTS!F8/WEIGHTS!$D$22*WEIGHTS!$D$19+REDESIGN_RESULTS!G8/WEIGHTS!$E$22*WEIGHTS!$E$19 | C8: =REDESIGN_RESULTS!D9/WEIGHTS!$B$22*WEIGHTS!$B$19+REDESIGN_RESULTS!E9/WEIGHTS!$C$22*WEIGHTS!$C$19+REDESIGN_RESULTS!F9/WEIGHTS!$D$22*WEIGHTS!$D$19+REDESIGN_RESULTS!G9/WEIGHTS!$E$22*WEIGHTS!$E$19 | D8: =REDESIGN_RESULTS!D10/WEIGHTS!$B$22*WEIGHTS!$B$19+REDESIGN_RESULTS!E10/WEIGHTS!$C$22*WEIGHTS!$C$19+REDESIGN_RESULTS!F10/WEIGHTS!$D$22*WEIGHTS!$D$19+REDESIGN_RESULTS!G10/WEIGHTS!$E$22*WEIGHTS!$E$19 | E8: =REDESIGN_RESULTS!D12/WEIGHTS!$B$22*WEIGHTS!$B$19+REDESIGN_RESULTS!E12/WEIGHTS!$C$22*WEIGHTS!$C$19+REDESIGN_RESULTS!F12/WEIGHTS!$D$22*WEIGHTS!$D$19+REDESIGN_RESULTS!G12/WEIGHTS!$E$22*WEIGHTS!$E$19 | F8: =MIN(B8:E8) | G8: =B8-F8 | H8: =C8-F8 | I8: =D8-F8 | J8: =E8-F8 | K8: =INDEX($B$7:$E$7,1,MATCH(F8,B8:E8,0)) | L8: =H8
A9: D002 | B9: =REDESIGN_RESULTS!D14/WEIGHTS!$B$22*WEIGHTS!$B$19+REDESIGN_RESULTS!E14/WEIGHTS!$C$22*WEIGHTS!$C$19+REDESIGN_RESULTS!F14/WEIGHTS!$D$22*WEIGHTS!$D$19+REDESIGN_RESULTS!G14/WEIGHTS!$E$22*WEIGHTS!$E$19 | C9: =REDESIGN_RESULTS!D15/WEIGHTS!$B$22*WEIGHTS!$B$19+REDESIGN_RESULTS!E15/WEIGHTS!$C$22*WEIGHTS!$C$19+REDESIGN_RESULTS!F15/WEIGHTS!$D$22*WEIGHTS!$D$19+REDESIGN_RESULTS!G15/WEIGHTS!$E$22*WEIGHTS!$E$19 | D9: =REDESIGN_RESULTS!D16/WEIGHTS!$B$22*WEIGHTS!$B$19+REDESIGN_RESULTS!E16/WEIGHTS!$C$22*WEIGHTS!$C$19+REDESIGN_RESULTS!F16/WEIGHTS!$D$22*WEIGHTS!$D$19+REDESIGN_RESULTS!G16/WEIGHTS!$E$22*WEIGHTS!$E$19 | E9: =REDESIGN_RESULTS!D18/WEIGHTS!$B$22*WEIGHTS!$B$19+REDESIGN_RESULTS!E18/WEIGHTS!$C$22*WEIGHTS!$C$19+REDESIGN_RESULTS!F18/WEIGHTS!$D$22*WEIGHTS!$D$19+REDESIGN_RESULTS!G18/WEIGHTS!$E$22*WEIGHTS!$E$19 | F9: =MIN(B9:E9) | G9: =B9-F9 | H9: =C9-F9 | I9: =D9-F9 | J9: =E9-F9 | K9: =INDEX($B$7:$E$7,1,MATCH(F9,B9:E9,0)) | L9: =H9
A10: D003 | B10: =REDESIGN_RESULTS!D20/WEIGHTS!$B$22*WEIGHTS!$B$19+REDESIGN_RESULTS!E20/WEIGHTS!$C$22*WEIGHTS!$C$19+REDESIGN_RESULTS!F20/WEIGHTS!$D$22*WEIGHTS!$D$19+REDESIGN_RESULTS!G20/WEIGHTS!$E$22*WEIGHTS!$E$19 | C10: =REDESIGN_RESULTS!D21/WEIGHTS!$B$22*WEIGHTS!$B$19+REDESIGN_RESULTS!E21/WEIGHTS!$C$22*WEIGHTS!$C$19+REDESIGN_RESULTS!F21/WEIGHTS!$D$22*WEIGHTS!$D$19+REDESIGN_RESULTS!G21/WEIGHTS!$E$22*WEIGHTS!$E$19 | D10: =REDESIGN_RESULTS!D22/WEIGHTS!$B$22*WEIGHTS!$B$19+REDESIGN_RESULTS!E22/WEIGHTS!$C$22*WEIGHTS!$C$19+REDESIGN_RESULTS!F22/WEIGHTS!$D$22*WEIGHTS!$D$19+REDESIGN_RESULTS!G22/WEIGHTS!$E$22*WEIGHTS!$E$19 | E10: =REDESIGN_RESULTS!D24/WEIGHTS!$B$22*WEIGHTS!$B$19+REDESIGN_RESULTS!E24/WEIGHTS!$C$22*WEIGHTS!$C$19+REDESIGN_RESULTS!F24/WEIGHTS!$D$22*WEIGHTS!$D$19+REDESIGN_RESULTS!G24/WEIGHTS!$E$22*WEIGHTS!$E$19 | F10: =MIN(B10:E10) | G10: =B10-F10 | H10: =C10-F10 | I10: =D10-F10 | J10: =E10-F10 | K10: =INDEX($B$7:$E$7,1,MATCH(F10,B10:E10,0)) | L10: =H10
A11: D004 | B11: =REDESIGN_RESULTS!D26/WEIGHTS!$B$22*WEIGHTS!$B$19+REDESIGN_RESULTS!E26/WEIGHTS!$C$22*WEIGHTS!$C$19+REDESIGN_RESULTS!F26/WEIGHTS!$D$22*WEIGHTS!$D$19+REDESIGN_RESULTS!G26/WEIGHTS!$E$22*WEIGHTS!$E$19 | C11: =REDESIGN_RESULTS!D27/WEIGHTS!$B$22*WEIGHTS!$B$19+REDESIGN_RESULTS!E27/WEIGHTS!$C$22*WEIGHTS!$C$19+REDESIGN_RESULTS!F27/WEIGHTS!$D$22*WEIGHTS!$D$19+REDESIGN_RESULTS!G27/WEIGHTS!$E$22*WEIGHTS!$E$19 | D11: =REDESIGN_RESULTS!D28/WEIGHTS!$B$22*WEIGHTS!$B$19+REDESIGN_RESULTS!E28/WEIGHTS!$C$22*WEIGHTS!$C$19+REDESIGN_RESULTS!F28/WEIGHTS!$D$22*WEIGHTS!$D$19+REDESIGN_RESULTS!G28/WEIGHTS!$E$22*WEIGHTS!$E$19 | E11: =REDESIGN_RESULTS!D30/WEIGHTS!$B$22*WEIGHTS!$B$19+REDESIGN_RESULTS!E30/WEIGHTS!$C$22*WEIGHTS!$C$19+REDESIGN_RESULTS!F30/WEIGHTS!$D$22*WEIGHTS!$D$19+REDESIGN_RESULTS!G30/WEIGHTS!$E$22*WEIGHTS!$E$19 | F11: =MIN(B11:E11) | G11: =B11-F11 | H11: =C11-F11 | I11: =D11-F11 | J11: =E11-F11 | K11: =INDEX($B$7:$E$7,1,MATCH(F11,B11:E11,0)) | L11: =H11
A12: D005 | B12: =REDESIGN_RESULTS!D32/WEIGHTS!$B$22*WEIGHTS!$B$19+REDESIGN_RESULTS!E32/WEIGHTS!$C$22*WEIGHTS!$C$19+REDESIGN_RESULTS!F32/WEIGHTS!$D$22*WEIGHTS!$D$19+REDESIGN_RESULTS!G32/WEIGHTS!$E$22*WEIGHTS!$E$19 | C12: =REDESIGN_RESULTS!D33/WEIGHTS!$B$22*WEIGHTS!$B$19+REDESIGN_RESULTS!E33/WEIGHTS!$C$22*WEIGHTS!$C$19+REDESIGN_RESULTS!F33/WEIGHTS!$D$22*WEIGHTS!$D$19+REDESIGN_RESULTS!G33/WEIGHTS!$E$22*WEIGHTS!$E$19 | D12: =REDESIGN_RESULTS!D34/WEIGHTS!$B$22*WEIGHTS!$B$19+REDESIGN_RESULTS!E34/WEIGHTS!$C$22*WEIGHTS!$C$19+REDESIGN_RESULTS!F34/WEIGHTS!$D$22*WEIGHTS!$D$19+REDESIGN_RESULTS!G34/WEIGHTS!$E$22*WEIGHTS!$E$19 | E12: =REDESIGN_RESULTS!D36/WEIGHTS!$B$22*WEIGHTS!$B$19+REDESIGN_RESULTS!E36/WEIGHTS!$C$22*WEIGHTS!$C$19+REDESIGN_RESULTS!F36/WEIGHTS!$D$22*WEIGHTS!$D$19+REDESIGN_RESULTS!G36/WEIGHTS!$E$22*WEIGHTS!$E$19 | F12: =MIN(B12:E12) | G12: =B12-F12 | H12: =C12-F12 | I12: =D12-F12 | J12: =E12-F12 | K12: =INDEX($B$7:$E$7,1,MATCH(F12,B12:E12,0)) | L12: =H12
A13: D006 | B13: =REDESIGN_RESULTS!D38/WEIGHTS!$B$22*WEIGHTS!$B$19+REDESIGN_RESULTS!E38/WEIGHTS!$C$22*WEIGHTS!$C$19+REDESIGN_RESULTS!F38/WEIGHTS!$D$22*WEIGHTS!$D$19+REDESIGN_RESULTS!G38/WEIGHTS!$E$22*WEIGHTS!$E$19 | C13: =REDESIGN_RESULTS!D39/WEIGHTS!$B$22*WEIGHTS!$B$19+REDESIGN_RESULTS!E39/WEIGHTS!$C$22*WEIGHTS!$C$19+REDESIGN_RESULTS!F39/WEIGHTS!$D$22*WEIGHTS!$D$19+REDESIGN_RESULTS!G39/WEIGHTS!$E$22*WEIGHTS!$E$19 | D13: =REDESIGN_RESULTS!D40/WEIGHTS!$B$22*WEIGHTS!$B$19+REDESIGN_RESULTS!E40/WEIGHTS!$C$22*WEIGHTS!$C$19+REDESIGN_RESULTS!F40/WEIGHTS!$D$22*WEIGHTS!$D$19+REDESIGN_RESULTS!G40/WEIGHTS!$E$22*WEIGHTS!$E$19 | E13: =REDESIGN_RESULTS!D42/WEIGHTS!$B$22*WEIGHTS!$B$19+REDESIGN_RESULTS!E42/WEIGHTS!$C$22*WEIGHTS!$C$19+REDESIGN_RESULTS!F42/WEIGHTS!$D$22*WEIGHTS!$D$19+REDESIGN_RESULTS!G42/WEIGHTS!$E$22*WEIGHTS!$E$19 | F13: =MIN(B13:E13) | G13: =B13-F13 | H13: =C13-F13 | I13: =D13-F13 | J13: =E13-F13 | K13: =INDEX($B$7:$E$7,1,MATCH(F13,B13:E13,0)) | L13: =H13
A14: D007 | B14: =REDESIGN_RESULTS!D44/WEIGHTS!$B$22*WEIGHTS!$B$19+REDESIGN_RESULTS!E44/WEIGHTS!$C$22*WEIGHTS!$C$19+REDESIGN_RESULTS!F44/WEIGHTS!$D$22*WEIGHTS!$D$19+REDESIGN_RESULTS!G44/WEIGHTS!$E$22*WEIGHTS!$E$19 | C14: =REDESIGN_RESULTS!D45/WEIGHTS!$B$22*WEIGHTS!$B$19+REDESIGN_RESULTS!E45/WEIGHTS!$C$22*WEIGHTS!$C$19+REDESIGN_RESULTS!F45/WEIGHTS!$D$22*WEIGHTS!$D$19+REDESIGN_RESULTS!G45/WEIGHTS!$E$22*WEIGHTS!$E$19 | D14: =REDESIGN_RESULTS!D46/WEIGHTS!$B$22*WEIGHTS!$B$19+REDESIGN_RESULTS!E46/WEIGHTS!$C$22*WEIGHTS!$C$19+REDESIGN_RESULTS!F46/WEIGHTS!$D$22*WEIGHTS!$D$19+REDESIGN_RESULTS!G46/WEIGHTS!$E$22*WEIGHTS!$E$19 | E14: =REDESIGN_RESULTS!D48/WEIGHTS!$B$22*WEIGHTS!$B$19+REDESIGN_RESULTS!E48/WEIGHTS!$C$22*WEIGHTS!$C$19+REDESIGN_RESULTS!F48/WEIGHTS!$D$22*WEIGHTS!$D$19+REDESIGN_RESULTS!G48/WEIGHTS!$E$22*WEIGHTS!$E$19 | F14: =MIN(B14:E14) | G14: =B14-F14 | H14: =C14-F14 | I14: =D14-F14 | J14: =E14-F14 | K14: =INDEX($B$7:$E$7,1,MATCH(F14,B14:E14,0)) | L14: =H14
A15: D008 | B15: =REDESIGN_RESULTS!D50/WEIGHTS!$B$22*WEIGHTS!$B$19+REDESIGN_RESULTS!E50/WEIGHTS!$C$22*WEIGHTS!$C$19+REDESIGN_RESULTS!F50/WEIGHTS!$D$22*WEIGHTS!$D$19+REDESIGN_RESULTS!G50/WEIGHTS!$E$22*WEIGHTS!$E$19 | C15: =REDESIGN_RESULTS!D51/WEIGHTS!$B$22*WEIGHTS!$B$19+REDESIGN_RESULTS!E51/WEIGHTS!$C$22*WEIGHTS!$C$19+REDESIGN_RESULTS!F51/WEIGHTS!$D$22*WEIGHTS!$D$19+REDESIGN_RESULTS!G51/WEIGHTS!$E$22*WEIGHTS!$E$19 | D15: =REDESIGN_RESULTS!D52/WEIGHTS!$B$22*WEIGHTS!$B$19+REDESIGN_RESULTS!E52/WEIGHTS!$C$22*WEIGHTS!$C$19+REDESIGN_RESULTS!F52/WEIGHTS!$D$22*WEIGHTS!$D$19+REDESIGN_RESULTS!G52/WEIGHTS!$E$22*WEIGHTS!$E$19 | E15: =REDESIGN_RESULTS!D54/WEIGHTS!$B$22*WEIGHTS!$B$19+REDESIGN_RESULTS!E54/WEIGHTS!$C$22*WEIGHTS!$C$19+REDESIGN_RESULTS!F54/WEIGHTS!$D$22*WEIGHTS!$D$19+REDESIGN_RESULTS!G54/WEIGHTS!$E$22*WEIGHTS!$E$19 | F15: =MIN(B15:E15) | G15: =B15-F15 | H15: =C15-F15 | I15: =D15-F15 | J15: =E15-F15 | K15: =INDEX($B$7:$E$7,1,MATCH(F15,B15:E15,0)) | L15: =H15
A16: D009 | B16: =REDESIGN_RESULTS!D56/WEIGHTS!$B$22*WEIGHTS!$B$19+REDESIGN_RESULTS!E56/WEIGHTS!$C$22*WEIGHTS!$C$19+REDESIGN_RESULTS!F56/WEIGHTS!$D$22*WEIGHTS!$D$19+REDESIGN_RESULTS!G56/WEIGHTS!$E$22*WEIGHTS!$E$19 | C16: =REDESIGN_RESULTS!D57/WEIGHTS!$B$22*WEIGHTS!$B$19+REDESIGN_RESULTS!E57/WEIGHTS!$C$22*WEIGHTS!$C$19+REDESIGN_RESULTS!F57/WEIGHTS!$D$22*WEIGHTS!$D$19+REDESIGN_RESULTS!G57/WEIGHTS!$E$22*WEIGHTS!$E$19 | D16: =REDESIGN_RESULTS!D58/WEIGHTS!$B$22*WEIGHTS!$B$19+REDESIGN_RESULTS!E58/WEIGHTS!$C$22*WEIGHTS!$C$19+REDESIGN_RESULTS!F58/WEIGHTS!$D$22*WEIGHTS!$D$19+REDESIGN_RESULTS!G58/WEIGHTS!$E$22*WEIGHTS!$E$19 | E16: =REDESIGN_RESULTS!D60/WEIGHTS!$B$22*WEIGHTS!$B$19+REDESIGN_RESULTS!E60/WEIGHTS!$C$22*WEIGHTS!$C$19+REDESIGN_RESULTS!F60/WEIGHTS!$D$22*WEIGHTS!$D$19+REDESIGN_RESULTS!G60/WEIGHTS!$E$22*WEIGHTS!$E$19 | F16: =MIN(B16:E16) | G16: =B16-F16 | H16: =C16-F16 | I16: =D16-F16 | J16: =E16-F16 | K16: =INDEX($B$7:$E$7,1,MATCH(F16,B16:E16,0)) | L16: =H16
A17: D010 | B17: =REDESIGN_RESULTS!D62/WEIGHTS!$B$22*WEIGHTS!$B$19+REDESIGN_RESULTS!E62/WEIGHTS!$C$22*WEIGHTS!$C$19+REDESIGN_RESULTS!F62/WEIGHTS!$D$22*WEIGHTS!$D$19+REDESIGN_RESULTS!G62/WEIGHTS!$E$22*WEIGHTS!$E$19 | C17: =REDESIGN_RESULTS!D63/WEIGHTS!$B$22*WEIGHTS!$B$19+REDESIGN_RESULTS!E63/WEIGHTS!$C$22*WEIGHTS!$C$19+REDESIGN_RESULTS!F63/WEIGHTS!$D$22*WEIGHTS!$D$19+REDESIGN_RESULTS!G63/WEIGHTS!$E$22*WEIGHTS!$E$19 | D17: =REDESIGN_RESULTS!D64/WEIGHTS!$B$22*WEIGHTS!$B$19+REDESIGN_RESULTS!E64/WEIGHTS!$C$22*WEIGHTS!$C$19+REDESIGN_RESULTS!F64/WEIGHTS!$D$22*WEIGHTS!$D$19+REDESIGN_RESULTS!G64/WEIGHTS!$E$22*WEIGHTS!$E$19 | E17: =REDESIGN_RESULTS!D66/WEIGHTS!$B$22*WEIGHTS!$B$19+REDESIGN_RESULTS!E66/WEIGHTS!$C$22*WEIGHTS!$C$19+REDESIGN_RESULTS!F66/WEIGHTS!$D$22*WEIGHTS!$D$19+REDESIGN_RESULTS!G66/WEIGHTS!$E$22*WEIGHTS!$E$19 | F17: =MIN(B17:E17) | G17: =B17-F17 | H17: =C17-F17 | I17: =D17-F17 | J17: =E17-F17 | K17: =INDEX($B$7:$E$7,1,MATCH(F17,B17:E17,0)) | L17: =H17
A18: D011 | B18: =REDESIGN_RESULTS!D68/WEIGHTS!$B$22*WEIGHTS!$B$19+REDESIGN_RESULTS!E68/WEIGHTS!$C$22*WEIGHTS!$C$19+REDESIGN_RESULTS!F68/WEIGHTS!$D$22*WEIGHTS!$D$19+REDESIGN_RESULTS!G68/WEIGHTS!$E$22*WEIGHTS!$E$19 | C18: =REDESIGN_RESULTS!D69/WEIGHTS!$B$22*WEIGHTS!$B$19+REDESIGN_RESULTS!E69/WEIGHTS!$C$22*WEIGHTS!$C$19+REDESIGN_RESULTS!F69/WEIGHTS!$D$22*WEIGHTS!$D$19+REDESIGN_RESULTS!G69/WEIGHTS!$E$22*WEIGHTS!$E$19 | D18: =REDESIGN_RESULTS!D70/WEIGHTS!$B$22*WEIGHTS!$B$19+REDESIGN_RESULTS!E70/WEIGHTS!$C$22*WEIGHTS!$C$19+REDESIGN_RESULTS!F70/WEIGHTS!$D$22*WEIGHTS!$D$19+REDESIGN_RESULTS!G70/WEIGHTS!$E$22*WEIGHTS!$E$19 | E18: =REDESIGN_RESULTS!D72/WEIGHTS!$B$22*WEIGHTS!$B$19+REDESIGN_RESULTS!E72/WEIGHTS!$C$22*WEIGHTS!$C$19+REDESIGN_RESULTS!F72/WEIGHTS!$D$22*WEIGHTS!$D$19+REDESIGN_RESULTS!G72/WEIGHTS!$E$22*WEIGHTS!$E$19 | F18: =MIN(B18:E18) | G18: =B18-F18 | H18: =C18-F18 | I18: =D18-F18 | J18: =E18-F18 | K18: =INDEX($B$7:$E$7,1,MATCH(F18,B18:E18,0)) | L18: =H18
A19: D012 | B19: =REDESIGN_RESULTS!D74/WEIGHTS!$B$22*WEIGHTS!$B$19+REDESIGN_RESULTS!E74/WEIGHTS!$C$22*WEIGHTS!$C$19+REDESIGN_RESULTS!F74/WEIGHTS!$D$22*WEIGHTS!$D$19+REDESIGN_RESULTS!G74/WEIGHTS!$E$22*WEIGHTS!$E$19 | C19: =REDESIGN_RESULTS!D75/WEIGHTS!$B$22*WEIGHTS!$B$19+REDESIGN_RESULTS!E75/WEIGHTS!$C$22*WEIGHTS!$C$19+REDESIGN_RESULTS!F75/WEIGHTS!$D$22*WEIGHTS!$D$19+REDESIGN_RESULTS!G75/WEIGHTS!$E$22*WEIGHTS!$E$19 | D19: =REDESIGN_RESULTS!D76/WEIGHTS!$B$22*WEIGHTS!$B$19+REDESIGN_RESULTS!E76/WEIGHTS!$C$22*WEIGHTS!$C$19+REDESIGN_RESULTS!F76/WEIGHTS!$D$22*WEIGHTS!$D$19+REDESIGN_RESULTS!G76/WEIGHTS!$E$22*WEIGHTS!$E$19 | E19: =REDESIGN_RESULTS!D78/WEIGHTS!$B$22*WEIGHTS!$B$19+REDESIGN_RESULTS!E78/WEIGHTS!$C$22*WEIGHTS!$C$19+REDESIGN_RESULTS!F78/WEIGHTS!$D$22*WEIGHTS!$D$19+REDESIGN_RESULTS!G78/WEIGHTS!$E$22*WEIGHTS!$E$19 | F19: =MIN(B19:E19) | G19: =B19-F19 | H19: =C19-F19 | I19: =D19-F19 | J19: =E19-F19 | K19: =INDEX($B$7:$E$7,1,MATCH(F19,B19:E19,0)) | L19: =H19
A20: D013 | B20: =REDESIGN_RESULTS!D80/WEIGHTS!$B$22*WEIGHTS!$B$19+REDESIGN_RESULTS!E80/WEIGHTS!$C$22*WEIGHTS!$C$19+REDESIGN_RESULTS!F80/WEIGHTS!$D$22*WEIGHTS!$D$19+REDESIGN_RESULTS!G80/WEIGHTS!$E$22*WEIGHTS!$E$19 | C20: =REDESIGN_RESULTS!D81/WEIGHTS!$B$22*WEIGHTS!$B$19+REDESIGN_RESULTS!E81/WEIGHTS!$C$22*WEIGHTS!$C$19+REDESIGN_RESULTS!F81/WEIGHTS!$D$22*WEIGHTS!$D$19+REDESIGN_RESULTS!G81/WEIGHTS!$E$22*WEIGHTS!$E$19 | D20: =REDESIGN_RESULTS!D82/WEIGHTS!$B$22*WEIGHTS!$B$19+REDESIGN_RESULTS!E82/WEIGHTS!$C$22*WEIGHTS!$C$19+REDESIGN_RESULTS!F82/WEIGHTS!$D$22*WEIGHTS!$D$19+REDESIGN_RESULTS!G82/WEIGHTS!$E$22*WEIGHTS!$E$19 | E20: =REDESIGN_RESULTS!D84/WEIGHTS!$B$22*WEIGHTS!$B$19+REDESIGN_RESULTS!E84/WEIGHTS!$C$22*WEIGHTS!$C$19+REDESIGN_RESULTS!F84/WEIGHTS!$D$22*WEIGHTS!$D$19+REDESIGN_RESULTS!G84/WEIGHTS!$E$22*WEIGHTS!$E$19 | F20: =MIN(B20:E20) | G20: =B20-F20 | H20: =C20-F20 | I20: =D20-F20 | J20: =E20-F20 | K20: =INDEX($B$7:$E$7,1,MATCH(F20,B20:E20,0)) | L20: =H20
A21: D014 | B21: =REDESIGN_RESULTS!D86/WEIGHTS!$B$22*WEIGHTS!$B$19+REDESIGN_RESULTS!E86/WEIGHTS!$C$22*WEIGHTS!$C$19+REDESIGN_RESULTS!F86/WEIGHTS!$D$22*WEIGHTS!$D$19+REDESIGN_RESULTS!G86/WEIGHTS!$E$22*WEIGHTS!$E$19 | C21: =REDESIGN_RESULTS!D87/WEIGHTS!$B$22*WEIGHTS!$B$19+REDESIGN_RESULTS!E87/WEIGHTS!$C$22*WEIGHTS!$C$19+REDESIGN_RESULTS!F87/WEIGHTS!$D$22*WEIGHTS!$D$19+REDESIGN_RESULTS!G87/WEIGHTS!$E$22*WEIGHTS!$E$19 | D21: =REDESIGN_RESULTS!D88/WEIGHTS!$B$22*WEIGHTS!$B$19+REDESIGN_RESULTS!E88/WEIGHTS!$C$22*WEIGHTS!$C$19+REDESIGN_RESULTS!F88/WEIGHTS!$D$22*WEIGHTS!$D$19+REDESIGN_RESULTS!G88/WEIGHTS!$E$22*WEIGHTS!$E$19 | E21: =REDESIGN_RESULTS!D90/WEIGHTS!$B$22*WEIGHTS!$B$19+REDESIGN_RESULTS!E90/WEIGHTS!$C$22*WEIGHTS!$C$19+REDESIGN_RESULTS!F90/WEIGHTS!$D$22*WEIGHTS!$D$19+REDESIGN_RESULTS!G90/WEIGHTS!$E$22*WEIGHTS!$E$19 | F21: =MIN(B21:E21) | G21: =B21-F21 | H21: =C21-F21 | I21: =D21-F21 | J21: =E21-F21 | K21: =INDEX($B$7:$E$7,1,MATCH(F21,B21:E21,0)) | L21: =H21
A22: D015 | B22: =REDESIGN_RESULTS!D92/WEIGHTS!$B$22*WEIGHTS!$B$19+REDESIGN_RESULTS!E92/WEIGHTS!$C$22*WEIGHTS!$C$19+REDESIGN_RESULTS!F92/WEIGHTS!$D$22*WEIGHTS!$D$19+REDESIGN_RESULTS!G92/WEIGHTS!$E$22*WEIGHTS!$E$19 | C22: =REDESIGN_RESULTS!D93/WEIGHTS!$B$22*WEIGHTS!$B$19+REDESIGN_RESULTS!E93/WEIGHTS!$C$22*WEIGHTS!$C$19+REDESIGN_RESULTS!F93/WEIGHTS!$D$22*WEIGHTS!$D$19+REDESIGN_RESULTS!G93/WEIGHTS!$E$22*WEIGHTS!$E$19 | D22: =REDESIGN_RESULTS!D94/WEIGHTS!$B$22*WEIGHTS!$B$19+REDESIGN_RESULTS!E94/WEIGHTS!$C$22*WEIGHTS!$C$19+REDESIGN_RESULTS!F94/WEIGHTS!$D$22*WEIGHTS!$D$19+REDESIGN_RESULTS!G94/WEIGHTS!$E$22*WEIGHTS!$E$19 | E22: =REDESIGN_RESULTS!D96/WEIGHTS!$B$22*WEIGHTS!$B$19+REDESIGN_RESULTS!E96/WEIGHTS!$C$22*WEIGHTS!$C$19+REDESIGN_RESULTS!F96/WEIGHTS!$D$22*WEIGHTS!$D$19+REDESIGN_RESULTS!G96/WEIGHTS!$E$22*WEIGHTS!$E$19 | F22: =MIN(B22:E22) | G22: =B22-F22 | H22: =C22-F22 | I22: =D22-F22 | J22: =E22-F22 | K22: =INDEX($B$7:$E$7,1,MATCH(F22,B22:E22,0)) | L22: =H22
A23: D016 | B23: =REDESIGN_RESULTS!D98/WEIGHTS!$B$22*WEIGHTS!$B$19+REDESIGN_RESULTS!E98/WEIGHTS!$C$22*WEIGHTS!$C$19+REDESIGN_RESULTS!F98/WEIGHTS!$D$22*WEIGHTS!$D$19+REDESIGN_RESULTS!G98/WEIGHTS!$E$22*WEIGHTS!$E$19 | C23: =REDESIGN_RESULTS!D99/WEIGHTS!$B$22*WEIGHTS!$B$19+REDESIGN_RESULTS!E99/WEIGHTS!$C$22*WEIGHTS!$C$19+REDESIGN_RESULTS!F99/WEIGHTS!$D$22*WEIGHTS!$D$19+REDESIGN_RESULTS!G99/WEIGHTS!$E$22*WEIGHTS!$E$19 | D23: =REDESIGN_RESULTS!D100/WEIGHTS!$B$22*WEIGHTS!$B$19+REDESIGN_RESULTS!E100/WEIGHTS!$C$22*WEIGHTS!$C$19+REDESIGN_RESULTS!F100/WEIGHTS!$D$22*WEIGHTS!$D$19+REDESIGN_RESULTS!G100/WEIGHTS!$E$22*WEIGHTS!$E$19 | E23: =REDESIGN_RESULTS!D102/WEIGHTS!$B$22*WEIGHTS!$B$19+REDESIGN_RESULTS!E102/WEIGHTS!$C$22*WEIGHTS!$C$19+REDESIGN_RESULTS!F102/WEIGHTS!$D$22*WEIGHTS!$D$19+REDESIGN_RESULTS!G102/WEIGHTS!$E$22*WEIGHTS!$E$19 | F23: =MIN(B23:E23) | G23: =B23-F23 | H23: =C23-F23 | I23: =D23-F23 | J23: =E23-F23 | K23: =INDEX($B$7:$E$7,1,MATCH(F23,B23:E23,0)) | L23: =H23
A24: D017 | B24: =REDESIGN_RESULTS!D104/WEIGHTS!$B$22*WEIGHTS!$B$19+REDESIGN_RESULTS!E104/WEIGHTS!$C$22*WEIGHTS!$C$19+REDESIGN_RESULTS!F104/WEIGHTS!$D$22*WEIGHTS!$D$19+REDESIGN_RESULTS!G104/WEIGHTS!$E$22*WEIGHTS!$E$19 | C24: =REDESIGN_RESULTS!D105/WEIGHTS!$B$22*WEIGHTS!$B$19+REDESIGN_RESULTS!E105/WEIGHTS!$C$22*WEIGHTS!$C$19+REDESIGN_RESULTS!F105/WEIGHTS!$D$22*WEIGHTS!$D$19+REDESIGN_RESULTS!G105/WEIGHTS!$E$22*WEIGHTS!$E$19 | D24: =REDESIGN_RESULTS!D106/WEIGHTS!$B$22*WEIGHTS!$B$19+REDESIGN_RESULTS!E106/WEIGHTS!$C$22*WEIGHTS!$C$19+REDESIGN_RESULTS!F106/WEIGHTS!$D$22*WEIGHTS!$D$19+REDESIGN_RESULTS!G106/WEIGHTS!$E$22*WEIGHTS!$E$19 | E24: =REDESIGN_RESULTS!D108/WEIGHTS!$B$22*WEIGHTS!$B$19+REDESIGN_RESULTS!E108/WEIGHTS!$C$22*WEIGHTS!$C$19+REDESIGN_RESULTS!F108/WEIGHTS!$D$22*WEIGHTS!$D$19+REDESIGN_RESULTS!G108/WEIGHTS!$E$22*WEIGHTS!$E$19 | F24: =MIN(B24:E24) | G24: =B24-F24 | H24: =C24-F24 | I24: =D24-F24 | J24: =E24-F24 | K24: =INDEX($B$7:$E$7,1,MATCH(F24,B24:E24,0)) | L24: =H24
A25: D018 | B25: =REDESIGN_RESULTS!D110/WEIGHTS!$B$22*WEIGHTS!$B$19+REDESIGN_RESULTS!E110/WEIGHTS!$C$22*WEIGHTS!$C$19+REDESIGN_RESULTS!F110/WEIGHTS!$D$22*WEIGHTS!$D$19+REDESIGN_RESULTS!G110/WEIGHTS!$E$22*WEIGHTS!$E$19 | C25: =REDESIGN_RESULTS!D111/WEIGHTS!$B$22*WEIGHTS!$B$19+REDESIGN_RESULTS!E111/WEIGHTS!$C$22*WEIGHTS!$C$19+REDESIGN_RESULTS!F111/WEIGHTS!$D$22*WEIGHTS!$D$19+REDESIGN_RESULTS!G111/WEIGHTS!$E$22*WEIGHTS!$E$19 | D25: =REDESIGN_RESULTS!D112/WEIGHTS!$B$22*WEIGHTS!$B$19+REDESIGN_RESULTS!E112/WEIGHTS!$C$22*WEIGHTS!$C$19+REDESIGN_RESULTS!F112/WEIGHTS!$D$22*WEIGHTS!$D$19+REDESIGN_RESULTS!G112/WEIGHTS!$E$22*WEIGHTS!$E$19 | E25: =REDESIGN_RESULTS!D114/WEIGHTS!$B$22*WEIGHTS!$B$19+REDESIGN_RESULTS!E114/WEIGHTS!$C$22*WEIGHTS!$C$19+REDESIGN_RESULTS!F114/WEIGHTS!$D$22*WEIGHTS!$D$19+REDESIGN_RESULTS!G114/WEIGHTS!$E$22*WEIGHTS!$E$19 | F25: =MIN(B25:E25) | G25: =B25-F25 | H25: =C25-F25 | I25: =D25-F25 | J25: =E25-F25 | K25: =INDEX($B$7:$E$7,1,MATCH(F25,B25:E25,0)) | L25: =H25
A26: D019 | B26: =REDESIGN_RESULTS!D116/WEIGHTS!$B$22*WEIGHTS!$B$19+REDESIGN_RESULTS!E116/WEIGHTS!$C$22*WEIGHTS!$C$19+REDESIGN_RESULTS!F116/WEIGHTS!$D$22*WEIGHTS!$D$19+REDESIGN_RESULTS!G116/WEIGHTS!$E$22*WEIGHTS!$E$19 | C26: =REDESIGN_RESULTS!D117/WEIGHTS!$B$22*WEIGHTS!$B$19+REDESIGN_RESULTS!E117/WEIGHTS!$C$22*WEIGHTS!$C$19+REDESIGN_RESULTS!F117/WEIGHTS!$D$22*WEIGHTS!$D$19+REDESIGN_RESULTS!G117/WEIGHTS!$E$22*WEIGHTS!$E$19 | D26: =REDESIGN_RESULTS!D118/WEIGHTS!$B$22*WEIGHTS!$B$19+REDESIGN_RESULTS!E118/WEIGHTS!$C$22*WEIGHTS!$C$19+REDESIGN_RESULTS!F118/WEIGHTS!$D$22*WEIGHTS!$D$19+REDESIGN_RESULTS!G118/WEIGHTS!$E$22*WEIGHTS!$E$19 | E26: =REDESIGN_RESULTS!D120/WEIGHTS!$B$22*WEIGHTS!$B$19+REDESIGN_RESULTS!E120/WEIGHTS!$C$22*WEIGHTS!$C$19+REDESIGN_RESULTS!F120/WEIGHTS!$D$22*WEIGHTS!$D$19+REDESIGN_RESULTS!G120/WEIGHTS!$E$22*WEIGHTS!$E$19 | F26: =MIN(B26:E26) | G26: =B26-F26 | H26: =C26-F26 | I26: =D26-F26 | J26: =E26-F26 | K26: =INDEX($B$7:$E$7,1,MATCH(F26,B26:E26,0)) | L26: =H26
A27: D020 | B27: =REDESIGN_RESULTS!D122/WEIGHTS!$B$22*WEIGHTS!$B$19+REDESIGN_RESULTS!E122/WEIGHTS!$C$22*WEIGHTS!$C$19+REDESIGN_RESULTS!F122/WEIGHTS!$D$22*WEIGHTS!$D$19+REDESIGN_RESULTS!G122/WEIGHTS!$E$22*WEIGHTS!$E$19 | C27: =REDESIGN_RESULTS!D123/WEIGHTS!$B$22*WEIGHTS!$B$19+REDESIGN_RESULTS!E123/WEIGHTS!$C$22*WEIGHTS!$C$19+REDESIGN_RESULTS!F123/WEIGHTS!$D$22*WEIGHTS!$D$19+REDESIGN_RESULTS!G123/WEIGHTS!$E$22*WEIGHTS!$E$19 | D27: =REDESIGN_RESULTS!D124/WEIGHTS!$B$22*WEIGHTS!$B$19+REDESIGN_RESULTS!E124/WEIGHTS!$C$22*WEIGHTS!$C$19+REDESIGN_RESULTS!F124/WEIGHTS!$D$22*WEIGHTS!$D$19+REDESIGN_RESULTS!G124/WEIGHTS!$E$22*WEIGHTS!$E$19 | E27: =REDESIGN_RESULTS!D126/WEIGHTS!$B$22*WEIGHTS!$B$19+REDESIGN_RESULTS!E126/WEIGHTS!$C$22*WEIGHTS!$C$19+REDESIGN_RESULTS!F126/WEIGHTS!$D$22*WEIGHTS!$D$19+REDESIGN_RESULTS!G126/WEIGHTS!$E$22*WEIGHTS!$E$19 | F27: =MIN(B27:E27) | G27: =B27-F27 | H27: =C27-F27 | I27: =D27-F27 | J27: =E27-F27 | K27: =INDEX($B$7:$E$7,1,MATCH(F27,B27:E27,0)) | L27: =H27
A28: D021 | B28: =REDESIGN_RESULTS!D128/WEIGHTS!$B$22*WEIGHTS!$B$19+REDESIGN_RESULTS!E128/WEIGHTS!$C$22*WEIGHTS!$C$19+REDESIGN_RESULTS!F128/WEIGHTS!$D$22*WEIGHTS!$D$19+REDESIGN_RESULTS!G128/WEIGHTS!$E$22*WEIGHTS!$E$19 | C28: =REDESIGN_RESULTS!D129/WEIGHTS!$B$22*WEIGHTS!$B$19+REDESIGN_RESULTS!E129/WEIGHTS!$C$22*WEIGHTS!$C$19+REDESIGN_RESULTS!F129/WEIGHTS!$D$22*WEIGHTS!$D$19+REDESIGN_RESULTS!G129/WEIGHTS!$E$22*WEIGHTS!$E$19 | D28: =REDESIGN_RESULTS!D130/WEIGHTS!$B$22*WEIGHTS!$B$19+REDESIGN_RESULTS!E130/WEIGHTS!$C$22*WEIGHTS!$C$19+REDESIGN_RESULTS!F130/WEIGHTS!$D$22*WEIGHTS!$D$19+REDESIGN_RESULTS!G130/WEIGHTS!$E$22*WEIGHTS!$E$19 | E28: =REDESIGN_RESULTS!D132/WEIGHTS!$B$22*WEIGHTS!$B$19+REDESIGN_RESULTS!E132/WEIGHTS!$C$22*WEIGHTS!$C$19+REDESIGN_RESULTS!F132/WEIGHTS!$D$22*WEIGHTS!$D$19+REDESIGN_RESULTS!G132/WEIGHTS!$E$22*WEIGHTS!$E$19 | F28: =MIN(B28:E28) | G28: =B28-F28 | H28: =C28-F28 | I28: =D28-F28 | J28: =E28-F28 | K28: =INDEX($B$7:$E$7,1,MATCH(F28,B28:E28,0)) | L28: =H28
A29: D022 | B29: =REDESIGN_RESULTS!D134/WEIGHTS!$B$22*WEIGHTS!$B$19+REDESIGN_RESULTS!E134/WEIGHTS!$C$22*WEIGHTS!$C$19+REDESIGN_RESULTS!F134/WEIGHTS!$D$22*WEIGHTS!$D$19+REDESIGN_RESULTS!G134/WEIGHTS!$E$22*WEIGHTS!$E$19 | C29: =REDESIGN_RESULTS!D135/WEIGHTS!$B$22*WEIGHTS!$B$19+REDESIGN_RESULTS!E135/WEIGHTS!$C$22*WEIGHTS!$C$19+REDESIGN_RESULTS!F135/WEIGHTS!$D$22*WEIGHTS!$D$19+REDESIGN_RESULTS!G135/WEIGHTS!$E$22*WEIGHTS!$E$19 | D29: =REDESIGN_RESULTS!D136/WEIGHTS!$B$22*WEIGHTS!$B$19+REDESIGN_RESULTS!E136/WEIGHTS!$C$22*WEIGHTS!$C$19+REDESIGN_RESULTS!F136/WEIGHTS!$D$22*WEIGHTS!$D$19+REDESIGN_RESULTS!G136/WEIGHTS!$E$22*WEIGHTS!$E$19 | E29: =REDESIGN_RESULTS!D138/WEIGHTS!$B$22*WEIGHTS!$B$19+REDESIGN_RESULTS!E138/WEIGHTS!$C$22*WEIGHTS!$C$19+REDESIGN_RESULTS!F138/WEIGHTS!$D$22*WEIGHTS!$D$19+REDESIGN_RESULTS!G138/WEIGHTS!$E$22*WEIGHTS!$E$19 | F29: =MIN(B29:E29) | G29: =B29-F29 | H29: =C29-F29 | I29: =D29-F29 | J29: =E29-F29 | K29: =INDEX($B$7:$E$7,1,MATCH(F29,B29:E29,0)) | L29: =H29
A30: D023 | B30: =REDESIGN_RESULTS!D140/WEIGHTS!$B$22*WEIGHTS!$B$19+REDESIGN_RESULTS!E140/WEIGHTS!$C$22*WEIGHTS!$C$19+REDESIGN_RESULTS!F140/WEIGHTS!$D$22*WEIGHTS!$D$19+REDESIGN_RESULTS!G140/WEIGHTS!$E$22*WEIGHTS!$E$19 | C30: =REDESIGN_RESULTS!D141/WEIGHTS!$B$22*WEIGHTS!$B$19+REDESIGN_RESULTS!E141/WEIGHTS!$C$22*WEIGHTS!$C$19+REDESIGN_RESULTS!F141/WEIGHTS!$D$22*WEIGHTS!$D$19+REDESIGN_RESULTS!G141/WEIGHTS!$E$22*WEIGHTS!$E$19 | D30: =REDESIGN_RESULTS!D142/WEIGHTS!$B$22*WEIGHTS!$B$19+REDESIGN_RESULTS!E142/WEIGHTS!$C$22*WEIGHTS!$C$19+REDESIGN_RESULTS!F142/WEIGHTS!$D$22*WEIGHTS!$D$19+REDESIGN_RESULTS!G142/WEIGHTS!$E$22*WEIGHTS!$E$19 | E30: =REDESIGN_RESULTS!D144/WEIGHTS!$B$22*WEIGHTS!$B$19+REDESIGN_RESULTS!E144/WEIGHTS!$C$22*WEIGHTS!$C$19+REDESIGN_RESULTS!F144/WEIGHTS!$D$22*WEIGHTS!$D$19+REDESIGN_RESULTS!G144/WEIGHTS!$E$22*WEIGHTS!$E$19 | F30: =MIN(B30:E30) | G30: =B30-F30 | H30: =C30-F30 | I30: =D30-F30 | J30: =E30-F30 | K30: =INDEX($B$7:$E$7,1,MATCH(F30,B30:E30,0)) | L30: =H30
A31: D024 | B31: =REDESIGN_RESULTS!D146/WEIGHTS!$B$22*WEIGHTS!$B$19+REDESIGN_RESULTS!E146/WEIGHTS!$C$22*WEIGHTS!$C$19+REDESIGN_RESULTS!F146/WEIGHTS!$D$22*WEIGHTS!$D$19+REDESIGN_RESULTS!G146/WEIGHTS!$E$22*WEIGHTS!$E$19 | C31: =REDESIGN_RESULTS!D147/WEIGHTS!$B$22*WEIGHTS!$B$19+REDESIGN_RESULTS!E147/WEIGHTS!$C$22*WEIGHTS!$C$19+REDESIGN_RESULTS!F147/WEIGHTS!$D$22*WEIGHTS!$D$19+REDESIGN_RESULTS!G147/WEIGHTS!$E$22*WEIGHTS!$E$19 | D31: =REDESIGN_RESULTS!D148/WEIGHTS!$B$22*WEIGHTS!$B$19+REDESIGN_RESULTS!E148/WEIGHTS!$C$22*WEIGHTS!$C$19+REDESIGN_RESULTS!F148/WEIGHTS!$D$22*WEIGHTS!$D$19+REDESIGN_RESULTS!G148/WEIGHTS!$E$22*WEIGHTS!$E$19 | E31: =REDESIGN_RESULTS!D150/WEIGHTS!$B$22*WEIGHTS!$B$19+REDESIGN_RESULTS!E150/WEIGHTS!$C$22*WEIGHTS!$C$19+REDESIGN_RESULTS!F150/WEIGHTS!$D$22*WEIGHTS!$D$19+REDESIGN_RESULTS!G150/WEIGHTS!$E$22*WEIGHTS!$E$19 | F31: =MIN(B31:E31) | G31: =B31-F31 | H31: =C31-F31 | I31: =D31-F31 | J31: =E31-F31 | K31: =INDEX($B$7:$E$7,1,MATCH(F31,B31:E31,0)) | L31: =H31
A35: Policy | B35: Mean cost | C35: Mean regret | D35: Maximum regret | E35: Near-best fraction | F35: Wins
A36: SP | B36: =AVERAGE(B8:B31) | C36: =AVERAGE(G8:G31) | D36: =MAX(G8:G31) | E36: =COUNTIF(G8:G31,"<="&WEIGHTS!$B$27)/24 | F36: =COUNTIF(K8:K31,A36&" cost")
A37: DTT | B37: =AVERAGE(C8:C31) | C37: =AVERAGE(H8:H31) | D37: =MAX(H8:H31) | E37: =COUNTIF(H8:H31,"<="&WEIGHTS!$B$27)/24 | F37: =COUNTIF(K8:K31,A37&" cost")
A38: ECO | B38: =AVERAGE(D8:D31) | C38: =AVERAGE(I8:I31) | D38: =MAX(I8:I31) | E38: =COUNTIF(I8:I31,"<="&WEIGHTS!$B$27)/24 | F38: =COUNTIF(K8:K31,A38&" cost")
A39: TECO10 | B39: =AVERAGE(E8:E31) | C39: =AVERAGE(J8:J31) | D39: =MAX(J8:J31) | E39: =COUNTIF(J8:J31,"<="&WEIGHTS!$B$27)/24 | F39: =COUNTIF(K8:K31,A39&" cost")
A42: Best mean fixed | B42: =INDEX(A36:A39,MATCH(MIN(B36:B39),B36:B39,0))
A43: Minimax fixed | B43: =INDEX(A36:A39,MATCH(MIN(D36:D39),D36:D39,0))
A44: Empirical oracle | B44: =AVERAGE(F8:F31)
A45: Learned selector | B45: NOT FITTED — SCIENTIFIC GATE
A47: Mean available headroom | B47: =MIN(B36:B39)-B44
A49: Inference limitation | B49: No claim that a deployable selector can attain the oracle. Development oracle is optimistic and noisy.

Sheet WORKED_EXAMPLE
A2: HYPOTHETICAL TEACHING VALUES — not SUMO evidence
A4: This isolated example demonstrates preference conflict. It never feeds physical results or ML.
A7: Alternative | B7: Time (s) | C7: CO2 (g) | D7: Time / 10 | E7: CO2 / 100
A8: A | B8: 10 | C8: 120 | D8: =B8/10 | E8: =C8/100
A9: B | B9: 12 | C9: 80 | D9: =B9/10 | E9: =C9/100
A10: C | B10: 15 | C10: 60 | D10: =B10/10 | E10: =C10/100
A14: Profile | B14: Time weight | C14: CO2 weight | D14: A cost | E14: B cost | F14: C cost | G14: Winner | H14: Regret if choose A
A15: Balanced | B15: 0.5 | C15: 0.5 | D15: =$B15*D8+$C15*E8 | E15: =$B15*D9+$C15*E9 | F15: =$B15*D10+$C15*E10 | G15: =INDEX($A$8:$A$10,MATCH(MIN(D15:F15),D15:F15,0)) | H15: =D15-MIN(D15:F15)
A16: Time-heavy | B16: 0.75 | C16: 0.25 | D16: =$B16*D8+$C16*E8 | E16: =$B16*D9+$C16*E9 | F16: =$B16*D10+$C16*E10 | G16: =INDEX($A$8:$A$10,MATCH(MIN(D16:F16),D16:F16,0)) | H16: =D16-MIN(D16:F16)
A17: Environment-heavy | B17: 0.25 | C17: 0.75 | D17: =$B17*D8+$C17*E8 | E17: =$B17*D9+$C17*E9 | F17: =$B17*D10+$C17*E10 | G17: =INDEX($A$8:$A$10,MATCH(MIN(D17:F17),D17:F17,0)) | H17: =D17-MIN(D17:F17)
A20: Balanced calculation | B20: A=0.5×1+0.5×1.2=1.1; B=1.0; C=1.05. Select B. A regret=0.10.
A22: TECO example | B22: Fastest estimated time=100 s; alpha=0.10 gives limit=110 s. Eco routes above 110 s are excluded.
A24: Native emission example | B24: 60000 mg / 120 vehicle-s × 30 s = 15000 mg = 15 g per estimated traversal.
A26: Probe loss example | B26: Predicted-best route realizes 120 g; observed best realizes 100 g: relative loss=20/100=20%.
A28: Source distinction | B28: Arithmetic illustrations of E02/E03/E05/E06/E12. Input numbers are deliberately hypothetical.

Sheet PILOT_RESULTS
A2: Frozen original pilot — separate from all development work
A4: 270 original runs. Mixed primary/background estimand; original time/CO2 criteria and calibration preserved.
A7: Context | B7: Policy | C7: Seed | D7: Original mean journey (s) | E7: Original CO2 (g) | F7: Split | G7: Cohort n | H7: Evidence status
A8: P001 | B8: SP | C8: 1 | D8: 174.02135 | E8: 441.64145 | F8: train | G8: 281 | H8: COMPLETED PILOT
A9: P001 | B9: SP | C9: 2 | D9: 163.62258 | E9: 417.68812 | F9: train | G9: 310 | H9: COMPLETED PILOT
A10: P001 | B10: SP | C10: 3 | D10: 163.78912 | E10: 414.36402 | F10: train | G10: 294 | H10: COMPLETED PILOT
A11: P001 | B11: DTT | C11: 1 | D11: 173.2669 | E11: 437.21773 | F11: train | G11: 281 | H11: COMPLETED PILOT
A12: P001 | B12: DTT | C12: 2 | D12: 161.42258 | E12: 408.86846 | F12: train | G12: 310 | H12: COMPLETED PILOT
A13: P001 | B13: DTT | C13: 3 | D13: 164.02721 | E13: 413.24629 | F13: train | G13: 294 | H13: COMPLETED PILOT
A14: P001 | B14: TDR | C14: 1 | D14: 174.02135 | E14: 441.64145 | F14: train | G14: 281 | H14: COMPLETED PILOT
A15: P001 | B15: TDR | C15: 2 | D15: 163.63548 | E15: 417.75657 | F15: train | G15: 310 | H15: COMPLETED PILOT
A16: P001 | B16: TDR | C16: 3 | D16: 163.73469 | E16: 414.14547 | F16: train | G16: 294 | H16: COMPLETED PILOT
A17: P002 | B17: SP | C17: 1 | D17: 173.60854 | E17: 442.79546 | F17: train | G17: 281 | H17: COMPLETED PILOT
A18: P002 | B18: SP | C18: 2 | D18: 163.30645 | E18: 418.68459 | F18: train | G18: 310 | H18: COMPLETED PILOT
A19: P002 | B19: SP | C19: 3 | D19: 163.33333 | E19: 415.438 | F19: train | G19: 294 | H19: COMPLETED PILOT
... A277: P030 | B277: TDR | C277: 3 | D277: 244.10536 | E277: 633.77382 | F277: train | G277: 560 | H277: COMPLETED PILOT
A281: Context | B281: Policy | C281: Mean time (s) | D281: Mean CO2 (g) | E281: Original additive cost | F281: Context oracle | G281: Regret
A282: P001 | B282: SP | C282: =AVERAGE(D8:D10) | D282: =AVERAGE(E8:E10) | E282: =0.5*C282/$B$376+0.5*D282/$B$377 | F282: =MIN(E282:E284) | G282: =E282-F282
A283: P001 | B283: DTT | C283: =AVERAGE(D11:D13) | D283: =AVERAGE(E11:E13) | E283: =0.5*C283/$B$376+0.5*D283/$B$377 | F283: =MIN(E282:E284) | G283: =E283-F283
A284: P001 | B284: TDR | C284: =AVERAGE(D14:D16) | D284: =AVERAGE(E14:E16) | E284: =0.5*C284/$B$376+0.5*D284/$B$377 | F284: =MIN(E282:E284) | G284: =E284-F284
A285: P002 | B285: SP | C285: =AVERAGE(D17:D19) | D285: =AVERAGE(E17:E19) | E285: =0.5*C285/$B$376+0.5*D285/$B$377 | F285: =MIN(E285:E287) | G285: =E285-F285
A286: P002 | B286: DTT | C286: =AVERAGE(D20:D22) | D286: =AVERAGE(E20:E22) | E286: =0.5*C286/$B$376+0.5*D286/$B$377 | F286: =MIN(E285:E287) | G286: =E286-F286
A287: P002 | B287: TDR | C287: =AVERAGE(D23:D25) | D287: =AVERAGE(E23:E25) | E287: =0.5*C287/$B$376+0.5*D287/$B$377 | F287: =MIN(E285:E287) | G287: =E287-F287
A288: P003 | B288: SP | C288: =AVERAGE(D26:D28) | D288: =AVERAGE(E26:E28) | E288: =0.5*C288/$B$376+0.5*D288/$B$377 | F288: =MIN(E288:E290) | G288: =E288-F288
A289: P003 | B289: DTT | C289: =AVERAGE(D29:D31) | D289: =AVERAGE(E29:E31) | E289: =0.5*C289/$B$376+0.5*D289/$B$377 | F289: =MIN(E288:E290) | G289: =E289-F289
A290: P003 | B290: TDR | C290: =AVERAGE(D32:D34) | D290: =AVERAGE(E32:E34) | E290: =0.5*C290/$B$376+0.5*D290/$B$377 | F290: =MIN(E288:E290) | G290: =E290-F290
A291: P004 | B291: SP | C291: =AVERAGE(D35:D37) | D291: =AVERAGE(E35:E37) | E291: =0.5*C291/$B$376+0.5*D291/$B$377 | F291: =MIN(E291:E293) | G291: =E291-F291
A292: P004 | B292: DTT | C292: =AVERAGE(D38:D40) | D292: =AVERAGE(E38:E40) | E292: =0.5*C292/$B$376+0.5*D292/$B$377 | F292: =MIN(E291:E293) | G292: =E292-F292
A293: P004 | B293: TDR | C293: =AVERAGE(D41:D43) | D293: =AVERAGE(E41:E43) | E293: =0.5*C293/$B$376+0.5*D293/$B$377 | F293: =MIN(E291:E293) | G293: =E293-F293
A294: P005 | B294: SP | C294: =AVERAGE(D44:D46) | D294: =AVERAGE(E44:E46) | E294: =0.5*C294/$B$376+0.5*D294/$B$377 | F294: =MIN(E294:E296) | G294: =E294-F294
A295: P005 | B295: DTT | C295: =AVERAGE(D47:D49) | D295: =AVERAGE(E47:E49) | E295: =0.5*C295/$B$376+0.5*D295/$B$377 | F295: =MIN(E294:E296) | G295: =E295-F295
A296: P005 | B296: TDR | C296: =AVERAGE(D50:D52) | D296: =AVERAGE(E50:E52) | E296: =0.5*C296/$B$376+0.5*D296/$B$377 | F296: =MIN(E294:E296) | G296: =E296-F296
A297: P006 | B297: SP | C297: =AVERAGE(D53:D55) | D297: =AVERAGE(E53:E55) | E297: =0.5*C297/$B$376+0.5*D297/$B$377 | F297: =MIN(E297:E299) | G297: =E297-F297
A298: P006 | B298: DTT | C298: =AVERAGE(D56:D58) | D298: =AVERAGE(E56:E58) | E298: =0.5*C298/$B$376+0.5*D298/$B$377 | F298: =MIN(E297:E299) | G298: =E298-F298
A299: P006 | B299: TDR | C299: =AVERAGE(D59:D61) | D299: =AVERAGE(E59:E61) | E299: =0.5*C299/$B$376+0.5*D299/$B$377 | F299: =MIN(E297:E299) | G299: =E299-F299
A300: P007 | B300: SP | C300: =AVERAGE(D62:D64) | D300: =AVERAGE(E62:E64) | E300: =0.5*C300/$B$376+0.5*D300/$B$377 | F300: =MIN(E300:E302) | G300: =E300-F300
A301: P007 | B301: DTT | C301: =AVERAGE(D65:D67) | D301: =AVERAGE(E65:E67) | E301: =0.5*C301/$B$376+0.5*D301/$B$377 | F301: =MIN(E300:E302) | G301: =E301-F301
A302: P007 | B302: TDR | C302: =AVERAGE(D68:D70) | D302: =AVERAGE(E68:E70) | E302: =0.5*C302/$B$376+0.5*D302/$B$377 | F302: =MIN(E300:E302) | G302: =E302-F302
A303: P008 | B303: SP | C303: =AVERAGE(D71:D73) | D303: =AVERAGE(E71:E73) | E303: =0.5*C303/$B$376+0.5*D303/$B$377 | F303: =MIN(E303:E305) | G303: =E303-F303
A304: P008 | B304: DTT | C304: =AVERAGE(D74:D76) | D304: =AVERAGE(E74:E76) | E304: =0.5*C304/$B$376+0.5*D304/$B$377 | F304: =MIN(E303:E305) | G304: =E304-F304
A305: P008 | B305: TDR | C305: =AVERAGE(D77:D79) | D305: =AVERAGE(E77:E79) | E305: =0.5*C305/$B$376+0.5*D305/$B$377 | F305: =MIN(E303:E305) | G305: =E305-F305
A306: P009 | B306: SP | C306: =AVERAGE(D80:D82) | D306: =AVERAGE(E80:E82) | E306: =0.5*C306/$B$376+0.5*D306/$B$377 | F306: =MIN(E306:E308) | G306: =E306-F306
A307: P009 | B307: DTT | C307: =AVERAGE(D83:D85) | D307: =AVERAGE(E83:E85) | E307: =0.5*C307/$B$376+0.5*D307/$B$377 | F307: =MIN(E306:E308) | G307: =E307-F307
A308: P009 | B308: TDR | C308: =AVERAGE(D86:D88) | D308: =AVERAGE(E86:E88) | E308: =0.5*C308/$B$376+0.5*D308/$B$377 | F308: =MIN(E306:E308) | G308: =E308-F308
A309: P010 | B309: SP | C309: =AVERAGE(D89:D91) | D309: =AVERAGE(E89:E91) | E309: =0.5*C309/$B$376+0.5*D309/$B$377 | F309: =MIN(E309:E311) | G309: =E309-F309
A310: P010 | B310: DTT | C310: =AVERAGE(D92:D94) | D310: =AVERAGE(E92:E94) | E310: =0.5*C310/$B$376+0.5*D310/$B$377 | F310: =MIN(E309:E311) | G310: =E310-F310
A311: P010 | B311: TDR | C311: =AVERAGE(D95:D97) | D311: =AVERAGE(E95:E97) | E311: =0.5*C311/$B$376+0.5*D311/$B$377 | F311: =MIN(E309:E311) | G311: =E311-F311
A312: P011 | B312: SP | C312: =AVERAGE(D98:D100) | D312: =AVERAGE(E98:E100) | E312: =0.5*C312/$B$376+0.5*D312/$B$377 | F312: =MIN(E312:E314) | G312: =E312-F312
A313: P011 | B313: DTT | C313: =AVERAGE(D101:D103) | D313: =AVERAGE(E101:E103) | E313: =0.5*C313/$B$376+0.5*D313/$B$377 | F313: =MIN(E312:E314) | G313: =E313-F313
A314: P011 | B314: TDR | C314: =AVERAGE(D104:D106) | D314: =AVERAGE(E104:E106) | E314: =0.5*C314/$B$376+0.5*D314/$B$377 | F314: =MIN(E312:E314) | G314: =E314-F314
A315: P012 | B315: SP | C315: =AVERAGE(D107:D109) | D315: =AVERAGE(E107:E109) | E315: =0.5*C315/$B$376+0.5*D315/$B$377 | F315: =MIN(E315:E317) | G315: =E315-F315
A316: P012 | B316: DTT | C316: =AVERAGE(D110:D112) | D316: =AVERAGE(E110:E112) | E316: =0.5*C316/$B$376+0.5*D316/$B$377 | F316: =MIN(E315:E317) | G316: =E316-F316
A317: P012 | B317: TDR | C317: =AVERAGE(D113:D115) | D317: =AVERAGE(E113:E115) | E317: =0.5*C317/$B$376+0.5*D317/$B$377 | F317: =MIN(E315:E317) | G317: =E317-F317
A318: P013 | B318: SP | C318: =AVERAGE(D116:D118) | D318: =AVERAGE(E116:E118) | E318: =0.5*C318/$B$376+0.5*D318/$B$377 | F318: =MIN(E318:E320) | G318: =E318-F318
A319: P013 | B319: DTT | C319: =AVERAGE(D119:D121) | D319: =AVERAGE(E119:E121) | E319: =0.5*C319/$B$376+0.5*D319/$B$377 | F319: =MIN(E318:E320) | G319: =E319-F319
A320: P013 | B320: TDR | C320: =AVERAGE(D122:D124) | D320: =AVERAGE(E122:E124) | E320: =0.5*C320/$B$376+0.5*D320/$B$377 | F320: =MIN(E318:E320) | G320: =E320-F320
A321: P014 | B321: SP | C321: =AVERAGE(D125:D127) | D321: =AVERAGE(E125:E127) | E321: =0.5*C321/$B$376+0.5*D321/$B$377 | F321: =MIN(E321:E323) | G321: =E321-F321
A322: P014 | B322: DTT | C322: =AVERAGE(D128:D130) | D322: =AVERAGE(E128:E130) | E322: =0.5*C322/$B$376+0.5*D322/$B$377 | F322: =MIN(E321:E323) | G322: =E322-F322
A323: P014 | B323: TDR | C323: =AVERAGE(D131:D133) | D323: =AVERAGE(E131:E133) | E323: =0.5*C323/$B$376+0.5*D323/$B$377 | F323: =MIN(E321:E323) | G323: =E323-F323
A324: P015 | B324: SP | C324: =AVERAGE(D134:D136) | D324: =AVERAGE(E134:E136) | E324: =0.5*C324/$B$376+0.5*D324/$B$377 | F324: =MIN(E324:E326) | G324: =E324-F324
A325: P015 | B325: DTT | C325: =AVERAGE(D137:D139) | D325: =AVERAGE(E137:E139) | E325: =0.5*C325/$B$376+0.5*D325/$B$377 | F325: =MIN(E324:E326) | G325: =E325-F325
A326: P015 | B326: TDR | C326: =AVERAGE(D140:D142) | D326: =AVERAGE(E140:E142) | E326: =0.5*C326/$B$376+0.5*D326/$B$377 | F326: =MIN(E324:E326) | G326: =E326-F326
A327: P016 | B327: SP | C327: =AVERAGE(D143:D145) | D327: =AVERAGE(E143:E145) | E327: =0.5*C327/$B$376+0.5*D327/$B$377 | F327: =MIN(E327:E329) | G327: =E327-F327
A328: P016 | B328: DTT | C328: =AVERAGE(D146:D148) | D328: =AVERAGE(E146:E148) | E328: =0.5*C328/$B$376+0.5*D328/$B$377 | F328: =MIN(E327:E329) | G328: =E328-F328
A329: P016 | B329: TDR | C329: =AVERAGE(D149:D151) | D329: =AVERAGE(E149:E151) | E329: =0.5*C329/$B$376+0.5*D329/$B$377 | F329: =MIN(E327:E329) | G329: =E329-F329
A330: P017 | B330: SP | C330: =AVERAGE(D152:D154) | D330: =AVERAGE(E152:E154) | E330: =0.5*C330/$B$376+0.5*D330/$B$377 | F330: =MIN(E330:E332) | G330: =E330-F330
A331: P017 | B331: DTT | C331: =AVERAGE(D155:D157) | D331: =AVERAGE(E155:E157) | E331: =0.5*C331/$B$376+0.5*D331/$B$377 | F331: =MIN(E330:E332) | G331: =E331-F331
A332: P017 | B332: TDR | C332: =AVERAGE(D158:D160) | D332: =AVERAGE(E158:E160) | E332: =0.5*C332/$B$376+0.5*D332/$B$377 | F332: =MIN(E330:E332) | G332: =E332-F332
A333: P018 | B333: SP | C333: =AVERAGE(D161:D163) | D333: =AVERAGE(E161:E163) | E333: =0.5*C333/$B$376+0.5*D333/$B$377 | F333: =MIN(E333:E335) | G333: =E333-F333
A334: P018 | B334: DTT | C334: =AVERAGE(D164:D166) | D334: =AVERAGE(E164:E166) | E334: =0.5*C334/$B$376+0.5*D334/$B$377 | F334: =MIN(E333:E335) | G334: =E334-F334
A335: P018 | B335: TDR | C335: =AVERAGE(D167:D169) | D335: =AVERAGE(E167:E169) | E335: =0.5*C335/$B$376+0.5*D335/$B$377 | F335: =MIN(E333:E335) | G335: =E335-F335
A336: P019 | B336: SP | C336: =AVERAGE(D170:D172) | D336: =AVERAGE(E170:E172) | E336: =0.5*C336/$B$376+0.5*D336/$B$377 | F336: =MIN(E336:E338) | G336: =E336-F336
A337: P019 | B337: DTT | C337: =AVERAGE(D173:D175) | D337: =AVERAGE(E173:E175) | E337: =0.5*C337/$B$376+0.5*D337/$B$377 | F337: =MIN(E336:E338) | G337: =E337-F337
A338: P019 | B338: TDR | C338: =AVERAGE(D176:D178) | D338: =AVERAGE(E176:E178) | E338: =0.5*C338/$B$376+0.5*D338/$B$377 | F338: =MIN(E336:E338) | G338: =E338-F338
A339: P020 | B339: SP | C339: =AVERAGE(D179:D181) | D339: =AVERAGE(E179:E181) | E339: =0.5*C339/$B$376+0.5*D339/$B$377 | F339: =MIN(E339:E341) | G339: =E339-F339
A340: P020 | B340: DTT | C340: =AVERAGE(D182:D184) | D340: =AVERAGE(E182:E184) | E340: =0.5*C340/$B$376+0.5*D340/$B$377 | F340: =MIN(E339:E341) | G340: =E340-F340
A341: P020 | B341: TDR | C341: =AVERAGE(D185:D187) | D341: =AVERAGE(E185:E187) | E341: =0.5*C341/$B$376+0.5*D341/$B$377 | F341: =MIN(E339:E341) | G341: =E341-F341
A342: P021 | B342: SP | C342: =AVERAGE(D188:D190) | D342: =AVERAGE(E188:E190) | E342: =0.5*C342/$B$376+0.5*D342/$B$377 | F342: =MIN(E342:E344) | G342: =E342-F342
A343: P021 | B343: DTT | C343: =AVERAGE(D191:D193) | D343: =AVERAGE(E191:E193) | E343: =0.5*C343/$B$376+0.5*D343/$B$377 | F343: =MIN(E342:E344) | G343: =E343-F343
A344: P021 | B344: TDR | C344: =AVERAGE(D194:D196) | D344: =AVERAGE(E194:E196) | E344: =0.5*C344/$B$376+0.5*D344/$B$377 | F344: =MIN(E342:E344) | G344: =E344-F344
A345: P022 | B345: SP | C345: =AVERAGE(D197:D199) | D345: =AVERAGE(E197:E199) | E345: =0.5*C345/$B$376+0.5*D345/$B$377 | F345: =MIN(E345:E347) | G345: =E345-F345
A346: P022 | B346: DTT | C346: =AVERAGE(D200:D202) | D346: =AVERAGE(E200:E202) | E346: =0.5*C346/$B$376+0.5*D346/$B$377 | F346: =MIN(E345:E347) | G346: =E346-F346
A347: P022 | B347: TDR | C347: =AVERAGE(D203:D205) | D347: =AVERAGE(E203:E205) | E347: =0.5*C347/$B$376+0.5*D347/$B$377 | F347: =MIN(E345:E347) | G347: =E347-F347
A348: P023 | B348: SP | C348: =AVERAGE(D206:D208) | D348: =AVERAGE(E206:E208) | E348: =0.5*C348/$B$376+0.5*D348/$B$377 | F348: =MIN(E348:E350) | G348: =E348-F348
A349: P023 | B349: DTT | C349: =AVERAGE(D209:D211) | D349: =AVERAGE(E209:E211) | E349: =0.5*C349/$B$376+0.5*D349/$B$377 | F349: =MIN(E348:E350) | G349: =E349-F349
A350: P023 | B350: TDR | C350: =AVERAGE(D212:D214) | D350: =AVERAGE(E212:E214) | E350: =0.5*C350/$B$376+0.5*D350/$B$377 | F350: =MIN(E348:E350) | G350: =E350-F350
A351: P024 | B351: SP | C351: =AVERAGE(D215:D217) | D351: =AVERAGE(E215:E217) | E351: =0.5*C351/$B$376+0.5*D351/$B$377 | F351: =MIN(E351:E353) | G351: =E351-F351
A352: P024 | B352: DTT | C352: =AVERAGE(D218:D220) | D352: =AVERAGE(E218:E220) | E352: =0.5*C352/$B$376+0.5*D352/$B$377 | F352: =MIN(E351:E353) | G352: =E352-F352
A353: P024 | B353: TDR | C353: =AVERAGE(D221:D223) | D353: =AVERAGE(E221:E223) | E353: =0.5*C353/$B$376+0.5*D353/$B$377 | F353: =MIN(E351:E353) | G353: =E353-F353
A354: P025 | B354: SP | C354: =AVERAGE(D224:D226) | D354: =AVERAGE(E224:E226) | E354: =0.5*C354/$B$376+0.5*D354/$B$377 | F354: =MIN(E354:E356) | G354: =E354-F354
A355: P025 | B355: DTT | C355: =AVERAGE(D227:D229) | D355: =AVERAGE(E227:E229) | E355: =0.5*C355/$B$376+0.5*D355/$B$377 | F355: =MIN(E354:E356) | G355: =E355-F355
A356: P025 | B356: TDR | C356: =AVERAGE(D230:D232) | D356: =AVERAGE(E230:E232) | E356: =0.5*C356/$B$376+0.5*D356/$B$377 | F356: =MIN(E354:E356) | G356: =E356-F356
A357: P026 | B357: SP | C357: =AVERAGE(D233:D235) | D357: =AVERAGE(E233:E235) | E357: =0.5*C357/$B$376+0.5*D357/$B$377 | F357: =MIN(E357:E359) | G357: =E357-F357
A358: P026 | B358: DTT | C358: =AVERAGE(D236:D238) | D358: =AVERAGE(E236:E238) | E358: =0.5*C358/$B$376+0.5*D358/$B$377 | F358: =MIN(E357:E359) | G358: =E358-F358
A359: P026 | B359: TDR | C359: =AVERAGE(D239:D241) | D359: =AVERAGE(E239:E241) | E359: =0.5*C359/$B$376+0.5*D359/$B$377 | F359: =MIN(E357:E359) | G359: =E359-F359
A360: P027 | B360: SP | C360: =AVERAGE(D242:D244) | D360: =AVERAGE(E242:E244) | E360: =0.5*C360/$B$376+0.5*D360/$B$377 | F360: =MIN(E360:E362) | G360: =E360-F360
A361: P027 | B361: DTT | C361: =AVERAGE(D245:D247) | D361: =AVERAGE(E245:E247) | E361: =0.5*C361/$B$376+0.5*D361/$B$377 | F361: =MIN(E360:E362) | G361: =E361-F361
A362: P027 | B362: TDR | C362: =AVERAGE(D248:D250) | D362: =AVERAGE(E248:E250) | E362: =0.5*C362/$B$376+0.5*D362/$B$377 | F362: =MIN(E360:E362) | G362: =E362-F362
A363: P028 | B363: SP | C363: =AVERAGE(D251:D253) | D363: =AVERAGE(E251:E253) | E363: =0.5*C363/$B$376+0.5*D363/$B$377 | F363: =MIN(E363:E365) | G363: =E363-F363
A364: P028 | B364: DTT | C364: =AVERAGE(D254:D256) | D364: =AVERAGE(E254:E256) | E364: =0.5*C364/$B$376+0.5*D364/$B$377 | F364: =MIN(E363:E365) | G364: =E364-F364
...

Sheet REDESIGN_RESULTS
A2: Equal-repetition means; future main results absent
A4: 144 development context-setting means calculated from 432 runs. 24 contexts, not 432 independent ML instances.
A7: Lookup key | B7: Context | C7: Setting | D7: Mean journey (s) | E7: CO2 (g/veh) | F7: Distance (m) | G7: P95 journey (s) | H7: Core portfolio? | I7: Replications | J7: BG journey (s) | K7: BG CO2 (g/veh) | L7: Network CO2 (g) | M7: Insertion (s) | N7: Mean forecast WAPE | O7: Status
A8: D001__SP | B8: D001 | C8: SP | D8: =AVERAGE(RAW_PERFORMANCE!F8,RAW_PERFORMANCE!F9,RAW_PERFORMANCE!F10) | E8: =AVERAGE(RAW_PERFORMANCE!G8,RAW_PERFORMANCE!G9,RAW_PERFORMANCE!G10) | F8: =AVERAGE(RAW_PERFORMANCE!H8,RAW_PERFORMANCE!H9,RAW_PERFORMANCE!H10) | G8: =AVERAGE(RAW_PERFORMANCE!I8,RAW_PERFORMANCE!I9,RAW_PERFORMANCE!I10) | H8: 1 | I8: =COUNT(RAW_PERFORMANCE!F8,RAW_PERFORMANCE!F9,RAW_PERFORMANCE!F10) | J8: =AVERAGE(RAW_PERFORMANCE!K8,RAW_PERFORMANCE!K9,RAW_PERFORMANCE!K10) | K8: =AVERAGE(RAW_PERFORMANCE!L8,RAW_PERFORMANCE!L9,RAW_PERFORMANCE!L10) | L8: =AVERAGE(RAW_PERFORMANCE!M8,RAW_PERFORMANCE!M9,RAW_PERFORMANCE!M10) | M8: =AVERAGE(RAW_PERFORMANCE!J8,RAW_PERFORMANCE!J9,RAW_PERFORMANCE!J10) | N8: =AVERAGE(RAW_PERFORMANCE!P8,RAW_PERFORMANCE!P9,RAW_PERFORMANCE!P10) | O8: COMPLETED DEVELOPMENT
A9: D001__DTT | B9: D001 | C9: DTT | D9: =AVERAGE(RAW_PERFORMANCE!F11,RAW_PERFORMANCE!F12,RAW_PERFORMANCE!F13) | E9: =AVERAGE(RAW_PERFORMANCE!G11,RAW_PERFORMANCE!G12,RAW_PERFORMANCE!G13) | F9: =AVERAGE(RAW_PERFORMANCE!H11,RAW_PERFORMANCE!H12,RAW_PERFORMANCE!H13) | G9: =AVERAGE(RAW_PERFORMANCE!I11,RAW_PERFORMANCE!I12,RAW_PERFORMANCE!I13) | H9: 1 | I9: =COUNT(RAW_PERFORMANCE!F11,RAW_PERFORMANCE!F12,RAW_PERFORMANCE!F13) | J9: =AVERAGE(RAW_PERFORMANCE!K11,RAW_PERFORMANCE!K12,RAW_PERFORMANCE!K13) | K9: =AVERAGE(RAW_PERFORMANCE!L11,RAW_PERFORMANCE!L12,RAW_PERFORMANCE!L13) | L9: =AVERAGE(RAW_PERFORMANCE!M11,RAW_PERFORMANCE!M12,RAW_PERFORMANCE!M13) | M9: =AVERAGE(RAW_PERFORMANCE!J11,RAW_PERFORMANCE!J12,RAW_PERFORMANCE!J13) | N9: =AVERAGE(RAW_PERFORMANCE!P11,RAW_PERFORMANCE!P12,RAW_PERFORMANCE!P13) | O9: COMPLETED DEVELOPMENT
A10: D001__ECO | B10: D001 | C10: ECO | D10: =AVERAGE(RAW_PERFORMANCE!F14,RAW_PERFORMANCE!F15,RAW_PERFORMANCE!F16) | E10: =AVERAGE(RAW_PERFORMANCE!G14,RAW_PERFORMANCE!G15,RAW_PERFORMANCE!G16) | F10: =AVERAGE(RAW_PERFORMANCE!H14,RAW_PERFORMANCE!H15,RAW_PERFORMANCE!H16) | G10: =AVERAGE(RAW_PERFORMANCE!I14,RAW_PERFORMANCE!I15,RAW_PERFORMANCE!I16) | H10: 1 | I10: =COUNT(RAW_PERFORMANCE!F14,RAW_PERFORMANCE!F15,RAW_PERFORMANCE!F16) | J10: =AVERAGE(RAW_PERFORMANCE!K14,RAW_PERFORMANCE!K15,RAW_PERFORMANCE!K16) | K10: =AVERAGE(RAW_PERFORMANCE!L14,RAW_PERFORMANCE!L15,RAW_PERFORMANCE!L16) | L10: =AVERAGE(RAW_PERFORMANCE!M14,RAW_PERFORMANCE!M15,RAW_PERFORMANCE!M16) | M10: =AVERAGE(RAW_PERFORMANCE!J14,RAW_PERFORMANCE!J15,RAW_PERFORMANCE!J16) | N10: =AVERAGE(RAW_PERFORMANCE!P14,RAW_PERFORMANCE!P15,RAW_PERFORMANCE!P16) | O10: COMPLETED DEVELOPMENT
A11: D001__TECO05 | B11: D001 | C11: TECO05 | D11: =AVERAGE(RAW_PERFORMANCE!F17,RAW_PERFORMANCE!F18,RAW_PERFORMANCE!F19) | E11: =AVERAGE(RAW_PERFORMANCE!G17,RAW_PERFORMANCE!G18,RAW_PERFORMANCE!G19) | F11: =AVERAGE(RAW_PERFORMANCE!H17,RAW_PERFORMANCE!H18,RAW_PERFORMANCE!H19) | G11: =AVERAGE(RAW_PERFORMANCE!I17,RAW_PERFORMANCE!I18,RAW_PERFORMANCE!I19) | H11: 0 | I11: =COUNT(RAW_PERFORMANCE!F17,RAW_PERFORMANCE!F18,RAW_PERFORMANCE!F19) | J11: =AVERAGE(RAW_PERFORMANCE!K17,RAW_PERFORMANCE!K18,RAW_PERFORMANCE!K19) | K11: =AVERAGE(RAW_PERFORMANCE!L17,RAW_PERFORMANCE!L18,RAW_PERFORMANCE!L19) | L11: =AVERAGE(RAW_PERFORMANCE!M17,RAW_PERFORMANCE!M18,RAW_PERFORMANCE!M19) | M11: =AVERAGE(RAW_PERFORMANCE!J17,RAW_PERFORMANCE!J18,RAW_PERFORMANCE!J19) | N11: =AVERAGE(RAW_PERFORMANCE!P17,RAW_PERFORMANCE!P18,RAW_PERFORMANCE!P19) | O11: COMPLETED DEVELOPMENT
A12: D001__TECO10 | B12: D001 | C12: TECO10 | D12: =AVERAGE(RAW_PERFORMANCE!F20,RAW_PERFORMANCE!F21,RAW_PERFORMANCE!F22) | E12: =AVERAGE(RAW_PERFORMANCE!G20,RAW_PERFORMANCE!G21,RAW_PERFORMANCE!G22) | F12: =AVERAGE(RAW_PERFORMANCE!H20,RAW_PERFORMANCE!H21,RAW_PERFORMANCE!H22) | G12: =AVERAGE(RAW_PERFORMANCE!I20,RAW_PERFORMANCE!I21,RAW_PERFORMANCE!I22) | H12: 1 | I12: =COUNT(RAW_PERFORMANCE!F20,RAW_PERFORMANCE!F21,RAW_PERFORMANCE!F22) | J12: =AVERAGE(RAW_PERFORMANCE!K20,RAW_PERFORMANCE!K21,RAW_PERFORMANCE!K22) | K12: =AVERAGE(RAW_PERFORMANCE!L20,RAW_PERFORMANCE!L21,RAW_PERFORMANCE!L22) | L12: =AVERAGE(RAW_PERFORMANCE!M20,RAW_PERFORMANCE!M21,RAW_PERFORMANCE!M22) | M12: =AVERAGE(RAW_PERFORMANCE!J20,RAW_PERFORMANCE!J21,RAW_PERFORMANCE!J22) | N12: =AVERAGE(RAW_PERFORMANCE!P20,RAW_PERFORMANCE!P21,RAW_PERFORMANCE!P22) | O12: COMPLETED DEVELOPMENT
A13: D001__TECO15 | B13: D001 | C13: TECO15 | D13: =AVERAGE(RAW_PERFORMANCE!F23,RAW_PERFORMANCE!F24,RAW_PERFORMANCE!F25) | E13: =AVERAGE(RAW_PERFORMANCE!G23,RAW_PERFORMANCE!G24,RAW_PERFORMANCE!G25) | F13: =AVERAGE(RAW_PERFORMANCE!H23,RAW_PERFORMANCE!H24,RAW_PERFORMANCE!H25) | G13: =AVERAGE(RAW_PERFORMANCE!I23,RAW_PERFORMANCE!I24,RAW_PERFORMANCE!I25) | H13: 0 | I13: =COUNT(RAW_PERFORMANCE!F23,RAW_PERFORMANCE!F24,RAW_PERFORMANCE!F25) | J13: =AVERAGE(RAW_PERFORMANCE!K23,RAW_PERFORMANCE!K24,RAW_PERFORMANCE!K25) | K13: =AVERAGE(RAW_PERFORMANCE!L23,RAW_PERFORMANCE!L24,RAW_PERFORMANCE!L25) | L13: =AVERAGE(RAW_PERFORMANCE!M23,RAW_PERFORMANCE!M24,RAW_PERFORMANCE!M25) | M13: =AVERAGE(RAW_PERFORMANCE!J23,RAW_PERFORMANCE!J24,RAW_PERFORMANCE!J25) | N13: =AVERAGE(RAW_PERFORMANCE!P23,RAW_PERFORMANCE!P24,RAW_PERFORMANCE!P25) | O13: COMPLETED DEVELOPMENT
A14: D002__SP | B14: D002 | C14: SP | D14: =AVERAGE(RAW_PERFORMANCE!F26,RAW_PERFORMANCE!F27,RAW_PERFORMANCE!F28) | E14: =AVERAGE(RAW_PERFORMANCE!G26,RAW_PERFORMANCE!G27,RAW_PERFORMANCE!G28) | F14: =AVERAGE(RAW_PERFORMANCE!H26,RAW_PERFORMANCE!H27,RAW_PERFORMANCE!H28) | G14: =AVERAGE(RAW_PERFORMANCE!I26,RAW_PERFORMANCE!I27,RAW_PERFORMANCE!I28) | H14: 1 | I14: =COUNT(RAW_PERFORMANCE!F26,RAW_PERFORMANCE!F27,RAW_PERFORMANCE!F28) | J14: =AVERAGE(RAW_PERFORMANCE!K26,RAW_PERFORMANCE!K27,RAW_PERFORMANCE!K28) | K14: =AVERAGE(RAW_PERFORMANCE!L26,RAW_PERFORMANCE!L27,RAW_PERFORMANCE!L28) | L14: =AVERAGE(RAW_PERFORMANCE!M26,RAW_PERFORMANCE!M27,RAW_PERFORMANCE!M28) | M14: =AVERAGE(RAW_PERFORMANCE!J26,RAW_PERFORMANCE!J27,RAW_PERFORMANCE!J28) | N14: =AVERAGE(RAW_PERFORMANCE!P26,RAW_PERFORMANCE!P27,RAW_PERFORMANCE!P28) | O14: COMPLETED DEVELOPMENT
A15: D002__DTT | B15: D002 | C15: DTT | D15: =AVERAGE(RAW_PERFORMANCE!F29,RAW_PERFORMANCE!F30,RAW_PERFORMANCE!F31) | E15: =AVERAGE(RAW_PERFORMANCE!G29,RAW_PERFORMANCE!G30,RAW_PERFORMANCE!G31) | F15: =AVERAGE(RAW_PERFORMANCE!H29,RAW_PERFORMANCE!H30,RAW_PERFORMANCE!H31) | G15: =AVERAGE(RAW_PERFORMANCE!I29,RAW_PERFORMANCE!I30,RAW_PERFORMANCE!I31) | H15: 1 | I15: =COUNT(RAW_PERFORMANCE!F29,RAW_PERFORMANCE!F30,RAW_PERFORMANCE!F31) | J15: =AVERAGE(RAW_PERFORMANCE!K29,RAW_PERFORMANCE!K30,RAW_PERFORMANCE!K31) | K15: =AVERAGE(RAW_PERFORMANCE!L29,RAW_PERFORMANCE!L30,RAW_PERFORMANCE!L31) | L15: =AVERAGE(RAW_PERFORMANCE!M29,RAW_PERFORMANCE!M30,RAW_PERFORMANCE!M31) | M15: =AVERAGE(RAW_PERFORMANCE!J29,RAW_PERFORMANCE!J30,RAW_PERFORMANCE!J31) | N15: =AVERAGE(RAW_PERFORMANCE!P29,RAW_PERFORMANCE!P30,RAW_PERFORMANCE!P31) | O15: COMPLETED DEVELOPMENT
A16: D002__ECO | B16: D002 | C16: ECO | D16: =AVERAGE(RAW_PERFORMANCE!F32,RAW_PERFORMANCE!F33,RAW_PERFORMANCE!F34) | E16: =AVERAGE(RAW_PERFORMANCE!G32,RAW_PERFORMANCE!G33,RAW_PERFORMANCE!G34) | F16: =AVERAGE(RAW_PERFORMANCE!H32,RAW_PERFORMANCE!H33,RAW_PERFORMANCE!H34) | G16: =AVERAGE(RAW_PERFORMANCE!I32,RAW_PERFORMANCE!I33,RAW_PERFORMANCE!I34) | H16: 1 | I16: =COUNT(RAW_PERFORMANCE!F32,RAW_PERFORMANCE!F33,RAW_PERFORMANCE!F34) | J16: =AVERAGE(RAW_PERFORMANCE!K32,RAW_PERFORMANCE!K33,RAW_PERFORMANCE!K34) | K16: =AVERAGE(RAW_PERFORMANCE!L32,RAW_PERFORMANCE!L33,RAW_PERFORMANCE!L34) | L16: =AVERAGE(RAW_PERFORMANCE!M32,RAW_PERFORMANCE!M33,RAW_PERFORMANCE!M34) | M16: =AVERAGE(RAW_PERFORMANCE!J32,RAW_PERFORMANCE!J33,RAW_PERFORMANCE!J34) | N16: =AVERAGE(RAW_PERFORMANCE!P32,RAW_PERFORMANCE!P33,RAW_PERFORMANCE!P34) | O16: COMPLETED DEVELOPMENT
A17: D002__TECO05 | B17: D002 | C17: TECO05 | D17: =AVERAGE(RAW_PERFORMANCE!F35,RAW_PERFORMANCE!F36,RAW_PERFORMANCE!F37) | E17: =AVERAGE(RAW_PERFORMANCE!G35,RAW_PERFORMANCE!G36,RAW_PERFORMANCE!G37) | F17: =AVERAGE(RAW_PERFORMANCE!H35,RAW_PERFORMANCE!H36,RAW_PERFORMANCE!H37) | G17: =AVERAGE(RAW_PERFORMANCE!I35,RAW_PERFORMANCE!I36,RAW_PERFORMANCE!I37) | H17: 0 | I17: =COUNT(RAW_PERFORMANCE!F35,RAW_PERFORMANCE!F36,RAW_PERFORMANCE!F37) | J17: =AVERAGE(RAW_PERFORMANCE!K35,RAW_PERFORMANCE!K36,RAW_PERFORMANCE!K37) | K17: =AVERAGE(RAW_PERFORMANCE!L35,RAW_PERFORMANCE!L36,RAW_PERFORMANCE!L37) | L17: =AVERAGE(RAW_PERFORMANCE!M35,RAW_PERFORMANCE!M36,RAW_PERFORMANCE!M37) | M17: =AVERAGE(RAW_PERFORMANCE!J35,RAW_PERFORMANCE!J36,RAW_PERFORMANCE!J37) | N17: =AVERAGE(RAW_PERFORMANCE!P35,RAW_PERFORMANCE!P36,RAW_PERFORMANCE!P37) | O17: COMPLETED DEVELOPMENT
A18: D002__TECO10 | B18: D002 | C18: TECO10 | D18: =AVERAGE(RAW_PERFORMANCE!F38,RAW_PERFORMANCE!F39,RAW_PERFORMANCE!F40) | E18: =AVERAGE(RAW_PERFORMANCE!G38,RAW_PERFORMANCE!G39,RAW_PERFORMANCE!G40) | F18: =AVERAGE(RAW_PERFORMANCE!H38,RAW_PERFORMANCE!H39,RAW_PERFORMANCE!H40) | G18: =AVERAGE(RAW_PERFORMANCE!I38,RAW_PERFORMANCE!I39,RAW_PERFORMANCE!I40) | H18: 1 | I18: =COUNT(RAW_PERFORMANCE!F38,RAW_PERFORMANCE!F39,RAW_PERFORMANCE!F40) | J18: =AVERAGE(RAW_PERFORMANCE!K38,RAW_PERFORMANCE!K39,RAW_PERFORMANCE!K40) | K18: =AVERAGE(RAW_PERFORMANCE!L38,RAW_PERFORMANCE!L39,RAW_PERFORMANCE!L40) | L18: =AVERAGE(RAW_PERFORMANCE!M38,RAW_PERFORMANCE!M39,RAW_PERFORMANCE!M40) | M18: =AVERAGE(RAW_PERFORMANCE!J38,RAW_PERFORMANCE!J39,RAW_PERFORMANCE!J40) | N18: =AVERAGE(RAW_PERFORMANCE!P38,RAW_PERFORMANCE!P39,RAW_PERFORMANCE!P40) | O18: COMPLETED DEVELOPMENT
A19: D002__TECO15 | B19: D002 | C19: TECO15 | D19: =AVERAGE(RAW_PERFORMANCE!F41,RAW_PERFORMANCE!F42,RAW_PERFORMANCE!F43) | E19: =AVERAGE(RAW_PERFORMANCE!G41,RAW_PERFORMANCE!G42,RAW_PERFORMANCE!G43) | F19: =AVERAGE(RAW_PERFORMANCE!H41,RAW_PERFORMANCE!H42,RAW_PERFORMANCE!H43) | G19: =AVERAGE(RAW_PERFORMANCE!I41,RAW_PERFORMANCE!I42,RAW_PERFORMANCE!I43) | H19: 0 | I19: =COUNT(RAW_PERFORMANCE!F41,RAW_PERFORMANCE!F42,RAW_PERFORMANCE!F43) | J19: =AVERAGE(RAW_PERFORMANCE!K41,RAW_PERFORMANCE!K42,RAW_PERFORMANCE!K43) | K19: =AVERAGE(RAW_PERFORMANCE!L41,RAW_PERFORMANCE!L42,RAW_PERFORMANCE!L43) | L19: =AVERAGE(RAW_PERFORMANCE!M41,RAW_PERFORMANCE!M42,RAW_PERFORMANCE!M43) | M19: =AVERAGE(RAW_PERFORMANCE!J41,RAW_PERFORMANCE!J42,RAW_PERFORMANCE!J43) | N19: =AVERAGE(RAW_PERFORMANCE!P41,RAW_PERFORMANCE!P42,RAW_PERFORMANCE!P43) | O19: COMPLETED DEVELOPMENT
A20: D003__SP | B20: D003 | C20: SP | D20: =AVERAGE(RAW_PERFORMANCE!F44,RAW_PERFORMANCE!F45,RAW_PERFORMANCE!F46) | E20: =AVERAGE(RAW_PERFORMANCE!G44,RAW_PERFORMANCE!G45,RAW_PERFORMANCE!G46) | F20: =AVERAGE(RAW_PERFORMANCE!H44,RAW_PERFORMANCE!H45,RAW_PERFORMANCE!H46) | G20: =AVERAGE(RAW_PERFORMANCE!I44,RAW_PERFORMANCE!I45,RAW_PERFORMANCE!I46) | H20: 1 | I20: =COUNT(RAW_PERFORMANCE!F44,RAW_PERFORMANCE!F45,RAW_PERFORMANCE!F46) | J20: =AVERAGE(RAW_PERFORMANCE!K44,RAW_PERFORMANCE!K45,RAW_PERFORMANCE!K46) | K20: =AVERAGE(RAW_PERFORMANCE!L44,RAW_PERFORMANCE!L45,RAW_PERFORMANCE!L46) | L20: =AVERAGE(RAW_PERFORMANCE!M44,RAW_PERFORMANCE!M45,RAW_PERFORMANCE!M46) | M20: =AVERAGE(RAW_PERFORMANCE!J44,RAW_PERFORMANCE!J45,RAW_PERFORMANCE!J46) | N20: =AVERAGE(RAW_PERFORMANCE!P44,RAW_PERFORMANCE!P45,RAW_PERFORMANCE!P46) | O20: COMPLETED DEVELOPMENT
A21: D003__DTT | B21: D003 | C21: DTT | D21: =AVERAGE(RAW_PERFORMANCE!F47,RAW_PERFORMANCE!F48,RAW_PERFORMANCE!F49) | E21: =AVERAGE(RAW_PERFORMANCE!G47,RAW_PERFORMANCE!G48,RAW_PERFORMANCE!G49) | F21: =AVERAGE(RAW_PERFORMANCE!H47,RAW_PERFORMANCE!H48,RAW_PERFORMANCE!H49) | G21: =AVERAGE(RAW_PERFORMANCE!I47,RAW_PERFORMANCE!I48,RAW_PERFORMANCE!I49) | H21: 1 | I21: =COUNT(RAW_PERFORMANCE!F47,RAW_PERFORMANCE!F48,RAW_PERFORMANCE!F49) | J21: =AVERAGE(RAW_PERFORMANCE!K47,RAW_PERFORMANCE!K48,RAW_PERFORMANCE!K49) | K21: =AVERAGE(RAW_PERFORMANCE!L47,RAW_PERFORMANCE!L48,RAW_PERFORMANCE!L49) | L21: =AVERAGE(RAW_PERFORMANCE!M47,RAW_PERFORMANCE!M48,RAW_PERFORMANCE!M49) | M21: =AVERAGE(RAW_PERFORMANCE!J47,RAW_PERFORMANCE!J48,RAW_PERFORMANCE!J49) | N21: =AVERAGE(RAW_PERFORMANCE!P47,RAW_PERFORMANCE!P48,RAW_PERFORMANCE!P49) | O21: COMPLETED DEVELOPMENT
A22: D003__ECO | B22: D003 | C22: ECO | D22: =AVERAGE(RAW_PERFORMANCE!F50,RAW_PERFORMANCE!F51,RAW_PERFORMANCE!F52) | E22: =AVERAGE(RAW_PERFORMANCE!G50,RAW_PERFORMANCE!G51,RAW_PERFORMANCE!G52) | F22: =AVERAGE(RAW_PERFORMANCE!H50,RAW_PERFORMANCE!H51,RAW_PERFORMANCE!H52) | G22: =AVERAGE(RAW_PERFORMANCE!I50,RAW_PERFORMANCE!I51,RAW_PERFORMANCE!I52) | H22: 1 | I22: =COUNT(RAW_PERFORMANCE!F50,RAW_PERFORMANCE!F51,RAW_PERFORMANCE!F52) | J22: =AVERAGE(RAW_PERFORMANCE!K50,RAW_PERFORMANCE!K51,RAW_PERFORMANCE!K52) | K22: =AVERAGE(RAW_PERFORMANCE!L50,RAW_PERFORMANCE!L51,RAW_PERFORMANCE!L52) | L22: =AVERAGE(RAW_PERFORMANCE!M50,RAW_PERFORMANCE!M51,RAW_PERFORMANCE!M52) | M22: =AVERAGE(RAW_PERFORMANCE!J50,RAW_PERFORMANCE!J51,RAW_PERFORMANCE!J52) | N22: =AVERAGE(RAW_PERFORMANCE!P50,RAW_PERFORMANCE!P51,RAW_PERFORMANCE!P52) | O22: COMPLETED DEVELOPMENT
A23: D003__TECO05 | B23: D003 | C23: TECO05 | D23: =AVERAGE(RAW_PERFORMANCE!F53,RAW_PERFORMANCE!F54,RAW_PERFORMANCE!F55) | E23: =AVERAGE(RAW_PERFORMANCE!G53,RAW_PERFORMANCE!G54,RAW_PERFORMANCE!G55) | F23: =AVERAGE(RAW_PERFORMANCE!H53,RAW_PERFORMANCE!H54,RAW_PERFORMANCE!H55) | G23: =AVERAGE(RAW_PERFORMANCE!I53,RAW_PERFORMANCE!I54,RAW_PERFORMANCE!I55) | H23: 0 | I23: =COUNT(RAW_PERFORMANCE!F53,RAW_PERFORMANCE!F54,RAW_PERFORMANCE!F55) | J23: =AVERAGE(RAW_PERFORMANCE!K53,RAW_PERFORMANCE!K54,RAW_PERFORMANCE!K55) | K23: =AVERAGE(RAW_PERFORMANCE!L53,RAW_PERFORMANCE!L54,RAW_PERFORMANCE!L55) | L23: =AVERAGE(RAW_PERFORMANCE!M53,RAW_PERFORMANCE!M54,RAW_PERFORMANCE!M55) | M23: =AVERAGE(RAW_PERFORMANCE!J53,RAW_PERFORMANCE!J54,RAW_PERFORMANCE!J55) | N23: =AVERAGE(RAW_PERFORMANCE!P53,RAW_PERFORMANCE!P54,RAW_PERFORMANCE!P55) | O23: COMPLETED DEVELOPMENT
A24: D003__TECO10 | B24: D003 | C24: TECO10 | D24: =AVERAGE(RAW_PERFORMANCE!F56,RAW_PERFORMANCE!F57,RAW_PERFORMANCE!F58) | E24: =AVERAGE(RAW_PERFORMANCE!G56,RAW_PERFORMANCE!G57,RAW_PERFORMANCE!G58) | F24: =AVERAGE(RAW_PERFORMANCE!H56,RAW_PERFORMANCE!H57,RAW_PERFORMANCE!H58) | G24: =AVERAGE(RAW_PERFORMANCE!I56,RAW_PERFORMANCE!I57,RAW_PERFORMANCE!I58) | H24: 1 | I24: =COUNT(RAW_PERFORMANCE!F56,RAW_PERFORMANCE!F57,RAW_PERFORMANCE!F58) | J24: =AVERAGE(RAW_PERFORMANCE!K56,RAW_PERFORMANCE!K57,RAW_PERFORMANCE!K58) | K24: =AVERAGE(RAW_PERFORMANCE!L56,RAW_PERFORMANCE!L57,RAW_PERFORMANCE!L58) | L24: =AVERAGE(RAW_PERFORMANCE!M56,RAW_PERFORMANCE!M57,RAW_PERFORMANCE!M58) | M24: =AVERAGE(RAW_PERFORMANCE!J56,RAW_PERFORMANCE!J57,RAW_PERFORMANCE!J58) | N24: =AVERAGE(RAW_PERFORMANCE!P56,RAW_PERFORMANCE!P57,RAW_PERFORMANCE!P58) | O24: COMPLETED DEVELOPMENT
A25: D003__TECO15 | B25: D003 | C25: TECO15 | D25: =AVERAGE(RAW_PERFORMANCE!F59,RAW_PERFORMANCE!F60,RAW_PERFORMANCE!F61) | E25: =AVERAGE(RAW_PERFORMANCE!G59,RAW_PERFORMANCE!G60,RAW_PERFORMANCE!G61) | F25: =AVERAGE(RAW_PERFORMANCE!H59,RAW_PERFORMANCE!H60,RAW_PERFORMANCE!H61) | G25: =AVERAGE(RAW_PERFORMANCE!I59,RAW_PERFORMANCE!I60,RAW_PERFORMANCE!I61) | H25: 0 | I25: =COUNT(RAW_PERFORMANCE!F59,RAW_PERFORMANCE!F60,RAW_PERFORMANCE!F61) | J25: =AVERAGE(RAW_PERFORMANCE!K59,RAW_PERFORMANCE!K60,RAW_PERFORMANCE!K61) | K25: =AVERAGE(RAW_PERFORMANCE!L59,RAW_PERFORMANCE!L60,RAW_PERFORMANCE!L61) | L25: =AVERAGE(RAW_PERFORMANCE!M59,RAW_PERFORMANCE!M60,RAW_PERFORMANCE!M61) | M25: =AVERAGE(RAW_PERFORMANCE!J59,RAW_PERFORMANCE!J60,RAW_PERFORMANCE!J61) | N25: =AVERAGE(RAW_PERFORMANCE!P59,RAW_PERFORMANCE!P60,RAW_PERFORMANCE!P61) | O25: COMPLETED DEVELOPMENT
A26: D004__SP | B26: D004 | C26: SP | D26: =AVERAGE(RAW_PERFORMANCE!F62,RAW_PERFORMANCE!F63,RAW_PERFORMANCE!F64) | E26: =AVERAGE(RAW_PERFORMANCE!G62,RAW_PERFORMANCE!G63,RAW_PERFORMANCE!G64) | F26: =AVERAGE(RAW_PERFORMANCE!H62,RAW_PERFORMANCE!H63,RAW_PERFORMANCE!H64) | G26: =AVERAGE(RAW_PERFORMANCE!I62,RAW_PERFORMANCE!I63,RAW_PERFORMANCE!I64) | H26: 1 | I26: =COUNT(RAW_PERFORMANCE!F62,RAW_PERFORMANCE!F63,RAW_PERFORMANCE!F64) | J26: =AVERAGE(RAW_PERFORMANCE!K62,RAW_PERFORMANCE!K63,RAW_PERFORMANCE!K64) | K26: =AVERAGE(RAW_PERFORMANCE!L62,RAW_PERFORMANCE!L63,RAW_PERFORMANCE!L64) | L26: =AVERAGE(RAW_PERFORMANCE!M62,RAW_PERFORMANCE!M63,RAW_PERFORMANCE!M64) | M26: =AVERAGE(RAW_PERFORMANCE!J62,RAW_PERFORMANCE!J63,RAW_PERFORMANCE!J64) | N26: =AVERAGE(RAW_PERFORMANCE!P62,RAW_PERFORMANCE!P63,RAW_PERFORMANCE!P64) | O26: COMPLETED DEVELOPMENT
A27: D004__DTT | B27: D004 | C27: DTT | D27: =AVERAGE(RAW_PERFORMANCE!F65,RAW_PERFORMANCE!F66,RAW_PERFORMANCE!F67) | E27: =AVERAGE(RAW_PERFORMANCE!G65,RAW_PERFORMANCE!G66,RAW_PERFORMANCE!G67) | F27: =AVERAGE(RAW_PERFORMANCE!H65,RAW_PERFORMANCE!H66,RAW_PERFORMANCE!H67) | G27: =AVERAGE(RAW_PERFORMANCE!I65,RAW_PERFORMANCE!I66,RAW_PERFORMANCE!I67) | H27: 1 | I27: =COUNT(RAW_PERFORMANCE!F65,RAW_PERFORMANCE!F66,RAW_PERFORMANCE!F67) | J27: =AVERAGE(RAW_PERFORMANCE!K65,RAW_PERFORMANCE!K66,RAW_PERFORMANCE!K67) | K27: =AVERAGE(RAW_PERFORMANCE!L65,RAW_PERFORMANCE!L66,RAW_PERFORMANCE!L67) | L27: =AVERAGE(RAW_PERFORMANCE!M65,RAW_PERFORMANCE!M66,RAW_PERFORMANCE!M67) | M27: =AVERAGE(RAW_PERFORMANCE!J65,RAW_PERFORMANCE!J66,RAW_PERFORMANCE!J67) | N27: =AVERAGE(RAW_PERFORMANCE!P65,RAW_PERFORMANCE!P66,RAW_PERFORMANCE!P67) | O27: COMPLETED DEVELOPMENT
A28: D004__ECO | B28: D004 | C28: ECO | D28: =AVERAGE(RAW_PERFORMANCE!F68,RAW_PERFORMANCE!F69,RAW_PERFORMANCE!F70) | E28: =AVERAGE(RAW_PERFORMANCE!G68,RAW_PERFORMANCE!G69,RAW_PERFORMANCE!G70) | F28: =AVERAGE(RAW_PERFORMANCE!H68,RAW_PERFORMANCE!H69,RAW_PERFORMANCE!H70) | G28: =AVERAGE(RAW_PERFORMANCE!I68,RAW_PERFORMANCE!I69,RAW_PERFORMANCE!I70) | H28: 1 | I28: =COUNT(RAW_PERFORMANCE!F68,RAW_PERFORMANCE!F69,RAW_PERFORMANCE!F70) | J28: =AVERAGE(RAW_PERFORMANCE!K68,RAW_PERFORMANCE!K69,RAW_PERFORMANCE!K70) | K28: =AVERAGE(RAW_PERFORMANCE!L68,RAW_PERFORMANCE!L69,RAW_PERFORMANCE!L70) | L28: =AVERAGE(RAW_PERFORMANCE!M68,RAW_PERFORMANCE!M69,RAW_PERFORMANCE!M70) | M28: =AVERAGE(RAW_PERFORMANCE!J68,RAW_PERFORMANCE!J69,RAW_PERFORMANCE!J70) | N28: =AVERAGE(RAW_PERFORMANCE!P68,RAW_PERFORMANCE!P69,RAW_PERFORMANCE!P70) | O28: COMPLETED DEVELOPMENT
A29: D004__TECO05 | B29: D004 | C29: TECO05 | D29: =AVERAGE(RAW_PERFORMANCE!F71,RAW_PERFORMANCE!F72,RAW_PERFORMANCE!F73) | E29: =AVERAGE(RAW_PERFORMANCE!G71,RAW_PERFORMANCE!G72,RAW_PERFORMANCE!G73) | F29: =AVERAGE(RAW_PERFORMANCE!H71,RAW_PERFORMANCE!H72,RAW_PERFORMANCE!H73) | G29: =AVERAGE(RAW_PERFORMANCE!I71,RAW_PERFORMANCE!I72,RAW_PERFORMANCE!I73) | H29: 0 | I29: =COUNT(RAW_PERFORMANCE!F71,RAW_PERFORMANCE!F72,RAW_PERFORMANCE!F73) | J29: =AVERAGE(RAW_PERFORMANCE!K71,RAW_PERFORMANCE!K72,RAW_PERFORMANCE!K73) | K29: =AVERAGE(RAW_PERFORMANCE!L71,RAW_PERFORMANCE!L72,RAW_PERFORMANCE!L73) | L29: =AVERAGE(RAW_PERFORMANCE!M71,RAW_PERFORMANCE!M72,RAW_PERFORMANCE!M73) | M29: =AVERAGE(RAW_PERFORMANCE!J71,RAW_PERFORMANCE!J72,RAW_PERFORMANCE!J73) | N29: =AVERAGE(RAW_PERFORMANCE!P71,RAW_PERFORMANCE!P72,RAW_PERFORMANCE!P73) | O29: COMPLETED DEVELOPMENT
A30: D004__TECO10 | B30: D004 | C30: TECO10 | D30: =AVERAGE(RAW_PERFORMANCE!F74,RAW_PERFORMANCE!F75,RAW_PERFORMANCE!F76) | E30: =AVERAGE(RAW_PERFORMANCE!G74,RAW_PERFORMANCE!G75,RAW_PERFORMANCE!G76) | F30: =AVERAGE(RAW_PERFORMANCE!H74,RAW_PERFORMANCE!H75,RAW_PERFORMANCE!H76) | G30: =AVERAGE(RAW_PERFORMANCE!I74,RAW_PERFORMANCE!I75,RAW_PERFORMANCE!I76) | H30: 1 | I30: =COUNT(RAW_PERFORMANCE!F74,RAW_PERFORMANCE!F75,RAW_PERFORMANCE!F76) | J30: =AVERAGE(RAW_PERFORMANCE!K74,RAW_PERFORMANCE!K75,RAW_PERFORMANCE!K76) | K30: =AVERAGE(RAW_PERFORMANCE!L74,RAW_PERFORMANCE!L75,RAW_PERFORMANCE!L76) | L30: =AVERAGE(RAW_PERFORMANCE!M74,RAW_PERFORMANCE!M75,RAW_PERFORMANCE!M76) | M30: =AVERAGE(RAW_PERFORMANCE!J74,RAW_PERFORMANCE!J75,RAW_PERFORMANCE!J76) | N30: =AVERAGE(RAW_PERFORMANCE!P74,RAW_PERFORMANCE!P75,RAW_PERFORMANCE!P76) | O30: COMPLETED DEVELOPMENT
A31: D004__TECO15 | B31: D004 | C31: TECO15 | D31: =AVERAGE(RAW_PERFORMANCE!F77,RAW_PERFORMANCE!F78,RAW_PERFORMANCE!F79) | E31: =AVERAGE(RAW_PERFORMANCE!G77,RAW_PERFORMANCE!G78,RAW_PERFORMANCE!G79) | F31: =AVERAGE(RAW_PERFORMANCE!H77,RAW_PERFORMANCE!H78,RAW_PERFORMANCE!H79) | G31: =AVERAGE(RAW_PERFORMANCE!I77,RAW_PERFORMANCE!I78,RAW_PERFORMANCE!I79) | H31: 0 | I31: =COUNT(RAW_PERFORMANCE!F77,RAW_PERFORMANCE!F78,RAW_PERFORMANCE!F79) | J31: =AVERAGE(RAW_PERFORMANCE!K77,RAW_PERFORMANCE!K78,RAW_PERFORMANCE!K79) | K31: =AVERAGE(RAW_PERFORMANCE!L77,RAW_PERFORMANCE!L78,RAW_PERFORMANCE!L79) | L31: =AVERAGE(RAW_PERFORMANCE!M77,RAW_PERFORMANCE!M78,RAW_PERFORMANCE!M79) | M31: =AVERAGE(RAW_PERFORMANCE!J77,RAW_PERFORMANCE!J78,RAW_PERFORMANCE!J79) | N31: =AVERAGE(RAW_PERFORMANCE!P77,RAW_PERFORMANCE!P78,RAW_PERFORMANCE!P79) | O31: COMPLETED DEVELOPMENT
A32: D005__SP | B32: D005 | C32: SP | D32: =AVERAGE(RAW_PERFORMANCE!F80,RAW_PERFORMANCE!F81,RAW_PERFORMANCE!F82) | E32: =AVERAGE(RAW_PERFORMANCE!G80,RAW_PERFORMANCE!G81,RAW_PERFORMANCE!G82) | F32: =AVERAGE(RAW_PERFORMANCE!H80,RAW_PERFORMANCE!H81,RAW_PERFORMANCE!H82) | G32: =AVERAGE(RAW_PERFORMANCE!I80,RAW_PERFORMANCE!I81,RAW_PERFORMANCE!I82) | H32: 1 | I32: =COUNT(RAW_PERFORMANCE!F80,RAW_PERFORMANCE!F81,RAW_PERFORMANCE!F82) | J32: =AVERAGE(RAW_PERFORMANCE!K80,RAW_PERFORMANCE!K81,RAW_PERFORMANCE!K82) | K32: =AVERAGE(RAW_PERFORMANCE!L80,RAW_PERFORMANCE!L81,RAW_PERFORMANCE!L82) | L32: =AVERAGE(RAW_PERFORMANCE!M80,RAW_PERFORMANCE!M81,RAW_PERFORMANCE!M82) | M32: =AVERAGE(RAW_PERFORMANCE!J80,RAW_PERFORMANCE!J81,RAW_PERFORMANCE!J82) | N32: =AVERAGE(RAW_PERFORMANCE!P80,RAW_PERFORMANCE!P81,RAW_PERFORMANCE!P82) | O32: COMPLETED DEVELOPMENT
A33: D005__DTT | B33: D005 | C33: DTT | D33: =AVERAGE(RAW_PERFORMANCE!F83,RAW_PERFORMANCE!F84,RAW_PERFORMANCE!F85) | E33: =AVERAGE(RAW_PERFORMANCE!G83,RAW_PERFORMANCE!G84,RAW_PERFORMANCE!G85) | F33: =AVERAGE(RAW_PERFORMANCE!H83,RAW_PERFORMANCE!H84,RAW_PERFORMANCE!H85) | G33: =AVERAGE(RAW_PERFORMANCE!I83,RAW_PERFORMANCE!I84,RAW_PERFORMANCE!I85) | H33: 1 | I33: =COUNT(RAW_PERFORMANCE!F83,RAW_PERFORMANCE!F84,RAW_PERFORMANCE!F85) | J33: =AVERAGE(RAW_PERFORMANCE!K83,RAW_PERFORMANCE!K84,RAW_PERFORMANCE!K85) | K33: =AVERAGE(RAW_PERFORMANCE!L83,RAW_PERFORMANCE!L84,RAW_PERFORMANCE!L85) | L33: =AVERAGE(RAW_PERFORMANCE!M83,RAW_PERFORMANCE!M84,RAW_PERFORMANCE!M85) | M33: =AVERAGE(RAW_PERFORMANCE!J83,RAW_PERFORMANCE!J84,RAW_PERFORMANCE!J85) | N33: =AVERAGE(RAW_PERFORMANCE!P83,RAW_PERFORMANCE!P84,RAW_PERFORMANCE!P85) | O33: COMPLETED DEVELOPMENT
A34: D005__ECO | B34: D005 | C34: ECO | D34: =AVERAGE(RAW_PERFORMANCE!F86,RAW_PERFORMANCE!F87,RAW_PERFORMANCE!F88) | E34: =AVERAGE(RAW_PERFORMANCE!G86,RAW_PERFORMANCE!G87,RAW_PERFORMANCE!G88) | F34: =AVERAGE(RAW_PERFORMANCE!H86,RAW_PERFORMANCE!H87,RAW_PERFORMANCE!H88) | G34: =AVERAGE(RAW_PERFORMANCE!I86,RAW_PERFORMANCE!I87,RAW_PERFORMANCE!I88) | H34: 1 | I34: =COUNT(RAW_PERFORMANCE!F86,RAW_PERFORMANCE!F87,RAW_PERFORMANCE!F88) | J34: =AVERAGE(RAW_PERFORMANCE!K86,RAW_PERFORMANCE!K87,RAW_PERFORMANCE!K88) | K34: =AVERAGE(RAW_PERFORMANCE!L86,RAW_PERFORMANCE!L87,RAW_PERFORMANCE!L88) | L34: =AVERAGE(RAW_PERFORMANCE!M86,RAW_PERFORMANCE!M87,RAW_PERFORMANCE!M88) | M34: =AVERAGE(RAW_PERFORMANCE!J86,RAW_PERFORMANCE!J87,RAW_PERFORMANCE!J88) | N34: =AVERAGE(RAW_PERFORMANCE!P86,RAW_PERFORMANCE!P87,RAW_PERFORMANCE!P88) | O34: COMPLETED DEVELOPMENT
A35: D005__TECO05 | B35: D005 | C35: TECO05 | D35: =AVERAGE(RAW_PERFORMANCE!F89,RAW_PERFORMANCE!F90,RAW_PERFORMANCE!F91) | E35: =AVERAGE(RAW_PERFORMANCE!G89,RAW_PERFORMANCE!G90,RAW_PERFORMANCE!G91) | F35: =AVERAGE(RAW_PERFORMANCE!H89,RAW_PERFORMANCE!H90,RAW_PERFORMANCE!H91) | G35: =AVERAGE(RAW_PERFORMANCE!I89,RAW_PERFORMANCE!I90,RAW_PERFORMANCE!I91) | H35: 0 | I35: =COUNT(RAW_PERFORMANCE!F89,RAW_PERFORMANCE!F90,RAW_PERFORMANCE!F91) | J35: =AVERAGE(RAW_PERFORMANCE!K89,RAW_PERFORMANCE!K90,RAW_PERFORMANCE!K91) | K35: =AVERAGE(RAW_PERFORMANCE!L89,RAW_PERFORMANCE!L90,RAW_PERFORMANCE!L91) | L35: =AVERAGE(RAW_PERFORMANCE!M89,RAW_PERFORMANCE!M90,RAW_PERFORMANCE!M91) | M35: =AVERAGE(RAW_PERFORMANCE!J89,RAW_PERFORMANCE!J90,RAW_PERFORMANCE!J91) | N35: =AVERAGE(RAW_PERFORMANCE!P89,RAW_PERFORMANCE!P90,RAW_PERFORMANCE!P91) | O35: COMPLETED DEVELOPMENT
A36: D005__TECO10 | B36: D005 | C36: TECO10 | D36: =AVERAGE(RAW_PERFORMANCE!F92,RAW_PERFORMANCE!F93,RAW_PERFORMANCE!F94) | E36: =AVERAGE(RAW_PERFORMANCE!G92,RAW_PERFORMANCE!G93,RAW_PERFORMANCE!G94) | F36: =AVERAGE(RAW_PERFORMANCE!H92,RAW_PERFORMANCE!H93,RAW_PERFORMANCE!H94) | G36: =AVERAGE(RAW_PERFORMANCE!I92,RAW_PERFORMANCE!I93,RAW_PERFORMANCE!I94) | H36: 1 | I36: =COUNT(RAW_PERFORMANCE!F92,RAW_PERFORMANCE!F93,RAW_PERFORMANCE!F94) | J36: =AVERAGE(RAW_PERFORMANCE!K92,RAW_PERFORMANCE!K93,RAW_PERFORMANCE!K94) | K36: =AVERAGE(RAW_PERFORMANCE!L92,RAW_PERFORMANCE!L93,RAW_PERFORMANCE!L94) | L36: =AVERAGE(RAW_PERFORMANCE!M92,RAW_PERFORMANCE!M93,RAW_PERFORMANCE!M94) | M36: =AVERAGE(RAW_PERFORMANCE!J92,RAW_PERFORMANCE!J93,RAW_PERFORMANCE!J94) | N36: =AVERAGE(RAW_PERFORMANCE!P92,RAW_PERFORMANCE!P93,RAW_PERFORMANCE!P94) | O36: COMPLETED DEVELOPMENT
A37: D005__TECO15 | B37: D005 | C37: TECO15 | D37: =AVERAGE(RAW_PERFORMANCE!F95,RAW_PERFORMANCE!F96,RAW_PERFORMANCE!F97) | E37: =AVERAGE(RAW_PERFORMANCE!G95,RAW_PERFORMANCE!G96,RAW_PERFORMANCE!G97) | F37: =AVERAGE(RAW_PERFORMANCE!H95,RAW_PERFORMANCE!H96,RAW_PERFORMANCE!H97) | G37: =AVERAGE(RAW_PERFORMANCE!I95,RAW_PERFORMANCE!I96,RAW_PERFORMANCE!I97) | H37: 0 | I37: =COUNT(RAW_PERFORMANCE!F95,RAW_PERFORMANCE!F96,RAW_PERFORMANCE!F97) | J37: =AVERAGE(RAW_PERFORMANCE!K95,RAW_PERFORMANCE!K96,RAW_PERFORMANCE!K97) | K37: =AVERAGE(RAW_PERFORMANCE!L95,RAW_PERFORMANCE!L96,RAW_PERFORMANCE!L97) | L37: =AVERAGE(RAW_PERFORMANCE!M95,RAW_PERFORMANCE!M96,RAW_PERFORMANCE!M97) | M37: =AVERAGE(RAW_PERFORMANCE!J95,RAW_PERFORMANCE!J96,RAW_PERFORMANCE!J97) | N37: =AVERAGE(RAW_PERFORMANCE!P95,RAW_PERFORMANCE!P96,RAW_PERFORMANCE!P97) | O37: COMPLETED DEVELOPMENT
A38: D006__SP | B38: D006 | C38: SP | D38: =AVERAGE(RAW_PERFORMANCE!F98,RAW_PERFORMANCE!F99,RAW_PERFORMANCE!F100) | E38: =AVERAGE(RAW_PERFORMANCE!G98,RAW_PERFORMANCE!G99,RAW_PERFORMANCE!G100) | F38: =AVERAGE(RAW_PERFORMANCE!H98,RAW_PERFORMANCE!H99,RAW_PERFORMANCE!H100) | G38: =AVERAGE(RAW_PERFORMANCE!I98,RAW_PERFORMANCE!I99,RAW_PERFORMANCE!I100) | H38: 1 | I38: =COUNT(RAW_PERFORMANCE!F98,RAW_PERFORMANCE!F99,RAW_PERFORMANCE!F100) | J38: =AVERAGE(RAW_PERFORMANCE!K98,RAW_PERFORMANCE!K99,RAW_PERFORMANCE!K100) | K38: =AVERAGE(RAW_PERFORMANCE!L98,RAW_PERFORMANCE!L99,RAW_PERFORMANCE!L100) | L38: =AVERAGE(RAW_PERFORMANCE!M98,RAW_PERFORMANCE!M99,RAW_PERFORMANCE!M100) | M38: =AVERAGE(RAW_PERFORMANCE!J98,RAW_PERFORMANCE!J99,RAW_PERFORMANCE!J100) | N38: =AVERAGE(RAW_PERFORMANCE!P98,RAW_PERFORMANCE!P99,RAW_PERFORMANCE!P100) | O38: COMPLETED DEVELOPMENT
A39: D006__DTT | B39: D006 | C39: DTT | D39: =AVERAGE(RAW_PERFORMANCE!F101,RAW_PERFORMANCE!F102,RAW_PERFORMANCE!F103) | E39: =AVERAGE(RAW_PERFORMANCE!G101,RAW_PERFORMANCE!G102,RAW_PERFORMANCE!G103) | F39: =AVERAGE(RAW_PERFORMANCE!H101,RAW_PERFORMANCE!H102,RAW_PERFORMANCE!H103) | G39: =AVERAGE(RAW_PERFORMANCE!I101,RAW_PERFORMANCE!I102,RAW_PERFORMANCE!I103) | H39: 1 | I39: =COUNT(RAW_PERFORMANCE!F101,RAW_PERFORMANCE!F102,RAW_PERFORMANCE!F103) | J39: =AVERAGE(RAW_PERFORMANCE!K101,RAW_PERFORMANCE!K102,RAW_PERFORMANCE!K103) | K39: =AVERAGE(RAW_PERFORMANCE!L101,RAW_PERFORMANCE!L102,RAW_PERFORMANCE!L103) | L39: =AVERAGE(RAW_PERFORMANCE!M101,RAW_PERFORMANCE!M102,RAW_PERFORMANCE!M103) | M39: =AVERAGE(RAW_PERFORMANCE!J101,RAW_PERFORMANCE!J102,RAW_PERFORMANCE!J103) | N39: =AVERAGE(RAW_PERFORMANCE!P101,RAW_PERFORMANCE!P102,RAW_PERFORMANCE!P103) | O39: COMPLETED DEVELOPMENT
A40: D006__ECO | B40: D006 | C40: ECO | D40: =AVERAGE(RAW_PERFORMANCE!F104,RAW_PERFORMANCE!F105,RAW_PERFORMANCE!F106) | E40: =AVERAGE(RAW_PERFORMANCE!G104,RAW_PERFORMANCE!G105,RAW_PERFORMANCE!G106) | F40: =AVERAGE(RAW_PERFORMANCE!H104,RAW_PERFORMANCE!H105,RAW_PERFORMANCE!H106) | G40: =AVERAGE(RAW_PERFORMANCE!I104,RAW_PERFORMANCE!I105,RAW_PERFORMANCE!I106) | H40: 1 | I40: =COUNT(RAW_PERFORMANCE!F104,RAW_PERFORMANCE!F105,RAW_PERFORMANCE!F106) | J40: =AVERAGE(RAW_PERFORMANCE!K104,RAW_PERFORMANCE!K105,RAW_PERFORMANCE!K106) | K40: =AVERAGE(RAW_PERFORMANCE!L104,RAW_PERFORMANCE!L105,RAW_PERFORMANCE!L106) | L40: =AVERAGE(RAW_PERFORMANCE!M104,RAW_PERFORMANCE!M105,RAW_PERFORMANCE!M106) | M40: =AVERAGE(RAW_PERFORMANCE!J104,RAW_PERFORMANCE!J105,RAW_PERFORMANCE!J106) | N40: =AVERAGE(RAW_PERFORMANCE!P104,RAW_PERFORMANCE!P105,RAW_PERFORMANCE!P106) | O40: COMPLETED DEVELOPMENT
A41: D006__TECO05 | B41: D006 | C41: TECO05 | D41: =AVERAGE(RAW_PERFORMANCE!F107,RAW_PERFORMANCE!F108,RAW_PERFORMANCE!F109) | E41: =AVERAGE(RAW_PERFORMANCE!G107,RAW_PERFORMANCE!G108,RAW_PERFORMANCE!G109) | F41: =AVERAGE(RAW_PERFORMANCE!H107,RAW_PERFORMANCE!H108,RAW_PERFORMANCE!H109) | G41: =AVERAGE(RAW_PERFORMANCE!I107,RAW_PERFORMANCE!I108,RAW_PERFORMANCE!I109) | H41: 0 | I41: =COUNT(RAW_PERFORMANCE!F107,RAW_PERFORMANCE!F108,RAW_PERFORMANCE!F109) | J41: =AVERAGE(RAW_PERFORMANCE!K107,RAW_PERFORMANCE!K108,RAW_PERFORMANCE!K109) | K41: =AVERAGE(RAW_PERFORMANCE!L107,RAW_PERFORMANCE!L108,RAW_PERFORMANCE!L109) | L41: =AVERAGE(RAW_PERFORMANCE!M107,RAW_PERFORMANCE!M108,RAW_PERFORMANCE!M109) | M41: =AVERAGE(RAW_PERFORMANCE!J107,RAW_PERFORMANCE!J108,RAW_PERFORMANCE!J109) | N41: =AVERAGE(RAW_PERFORMANCE!P107,RAW_PERFORMANCE!P108,RAW_PERFORMANCE!P109) | O41: COMPLETED DEVELOPMENT
A42: D006__TECO10 | B42: D006 | C42: TECO10 | D42: =AVERAGE(RAW_PERFORMANCE!F110,RAW_PERFORMANCE!F111,RAW_PERFORMANCE!F112) | E42: =AVERAGE(RAW_PERFORMANCE!G110,RAW_PERFORMANCE!G111,RAW_PERFORMANCE!G112) | F42: =AVERAGE(RAW_PERFORMANCE!H110,RAW_PERFORMANCE!H111,RAW_PERFORMANCE!H112) | G42: =AVERAGE(RAW_PERFORMANCE!I110,RAW_PERFORMANCE!I111,RAW_PERFORMANCE!I112) | H42: 1 | I42: =COUNT(RAW_PERFORMANCE!F110,RAW_PERFORMANCE!F111,RAW_PERFORMANCE!F112) | J42: =AVERAGE(RAW_PERFORMANCE!K110,RAW_PERFORMANCE!K111,RAW_PERFORMANCE!K112) | K42: =AVERAGE(RAW_PERFORMANCE!L110,RAW_PERFORMANCE!L111,RAW_PERFORMANCE!L112) | L42: =AVERAGE(RAW_PERFORMANCE!M110,RAW_PERFORMANCE!M111,RAW_PERFORMANCE!M112) | M42: =AVERAGE(RAW_PERFORMANCE!J110,RAW_PERFORMANCE!J111,RAW_PERFORMANCE!J112) | N42: =AVERAGE(RAW_PERFORMANCE!P110,RAW_PERFORMANCE!P111,RAW_PERFORMANCE!P112) | O42: COMPLETED DEVELOPMENT
A43: D006__TECO15 | B43: D006 | C43: TECO15 | D43: =AVERAGE(RAW_PERFORMANCE!F113,RAW_PERFORMANCE!F114,RAW_PERFORMANCE!F115) | E43: =AVERAGE(RAW_PERFORMANCE!G113,RAW_PERFORMANCE!G114,RAW_PERFORMANCE!G115) | F43: =AVERAGE(RAW_PERFORMANCE!H113,RAW_PERFORMANCE!H114,RAW_PERFORMANCE!H115) | G43: =AVERAGE(RAW_PERFORMANCE!I113,RAW_PERFORMANCE!I114,RAW_PERFORMANCE!I115) | H43: 0 | I43: =COUNT(RAW_PERFORMANCE!F113,RAW_PERFORMANCE!F114,RAW_PERFORMANCE!F115) | J43: =AVERAGE(RAW_PERFORMANCE!K113,RAW_PERFORMANCE!K114,RAW_PERFORMANCE!K115) | K43: =AVERAGE(RAW_PERFORMANCE!L113,RAW_PERFORMANCE!L114,RAW_PERFORMANCE!L115) | L43: =AVERAGE(RAW_PERFORMANCE!M113,RAW_PERFORMANCE!M114,RAW_PERFORMANCE!M115) | M43: =AVERAGE(RAW_PERFORMANCE!J113,RAW_PERFORMANCE!J114,RAW_PERFORMANCE!J115) | N43: =AVERAGE(RAW_PERFORMANCE!P113,RAW_PERFORMANCE!P114,RAW_PERFORMANCE!P115) | O43: COMPLETED DEVELOPMENT
A44: D007__SP | B44: D007 | C44: SP | D44: =AVERAGE(RAW_PERFORMANCE!F116,RAW_PERFORMANCE!F117,RAW_PERFORMANCE!F118) | E44: =AVERAGE(RAW_PERFORMANCE!G116,RAW_PERFORMANCE!G117,RAW_PERFORMANCE!G118) | F44: =AVERAGE(RAW_PERFORMANCE!H116,RAW_PERFORMANCE!H117,RAW_PERFORMANCE!H118) | G44: =AVERAGE(RAW_PERFORMANCE!I116,RAW_PERFORMANCE!I117,RAW_PERFORMANCE!I118) | H44: 1 | I44: =COUNT(RAW_PERFORMANCE!F116,RAW_PERFORMANCE!F117,RAW_PERFORMANCE!F118) | J44: =AVERAGE(RAW_PERFORMANCE!K116,RAW_PERFORMANCE!K117,RAW_PERFORMANCE!K118) | K44: =AVERAGE(RAW_PERFORMANCE!L116,RAW_PERFORMANCE!L117,RAW_PERFORMANCE!L118) | L44: =AVERAGE(RAW_PERFORMANCE!M116,RAW_PERFORMANCE!M117,RAW_PERFORMANCE!M118) | M44: =AVERAGE(RAW_PERFORMANCE!J116,RAW_PERFORMANCE!J117,RAW_PERFORMANCE!J118) | N44: =AVERAGE(RAW_PERFORMANCE!P116,RAW_PERFORMANCE!P117,RAW_PERFORMANCE!P118) | O44: COMPLETED DEVELOPMENT
A45: D007__DTT | B45: D007 | C45: DTT | D45: =AVERAGE(RAW_PERFORMANCE!F119,RAW_PERFORMANCE!F120,RAW_PERFORMANCE!F121) | E45: =AVERAGE(RAW_PERFORMANCE!G119,RAW_PERFORMANCE!G120,RAW_PERFORMANCE!G121) | F45: =AVERAGE(RAW_PERFORMANCE!H119,RAW_PERFORMANCE!H120,RAW_PERFORMANCE!H121) | G45: =AVERAGE(RAW_PERFORMANCE!I119,RAW_PERFORMANCE!I120,RAW_PERFORMANCE!I121) | H45: 1 | I45: =COUNT(RAW_PERFORMANCE!F119,RAW_PERFORMANCE!F120,RAW_PERFORMANCE!F121) | J45: =AVERAGE(RAW_PERFORMANCE!K119,RAW_PERFORMANCE!K120,RAW_PERFORMANCE!K121) | K45: =AVERAGE(RAW_PERFORMANCE!L119,RAW_PERFORMANCE!L120,RAW_PERFORMANCE!L121) | L45: =AVERAGE(RAW_PERFORMANCE!M119,RAW_PERFORMANCE!M120,RAW_PERFORMANCE!M121) | M45: =AVERAGE(RAW_PERFORMANCE!J119,RAW_PERFORMANCE!J120,RAW_PERFORMANCE!J121) | N45: =AVERAGE(RAW_PERFORMANCE!P119,RAW_PERFORMANCE!P120,RAW_PERFORMANCE!P121) | O45: COMPLETED DEVELOPMENT
A46: D007__ECO | B46: D007 | C46: ECO | D46: =AVERAGE(RAW_PERFORMANCE!F122,RAW_PERFORMANCE!F123,RAW_PERFORMANCE!F124) | E46: =AVERAGE(RAW_PERFORMANCE!G122,RAW_PERFORMANCE!G123,RAW_PERFORMANCE!G124) | F46: =AVERAGE(RAW_PERFORMANCE!H122,RAW_PERFORMANCE!H123,RAW_PERFORMANCE!H124) | G46: =AVERAGE(RAW_PERFORMANCE!I122,RAW_PERFORMANCE!I123,RAW_PERFORMANCE!I124) | H46: 1 | I46: =COUNT(RAW_PERFORMANCE!F122,RAW_PERFORMANCE!F123,RAW_PERFORMANCE!F124) | J46: =AVERAGE(RAW_PERFORMANCE!K122,RAW_PERFORMANCE!K123,RAW_PERFORMANCE!K124) | K46: =AVERAGE(RAW_PERFORMANCE!L122,RAW_PERFORMANCE!L123,RAW_PERFORMANCE!L124) | L46: =AVERAGE(RAW_PERFORMANCE!M122,RAW_PERFORMANCE!M123,RAW_PERFORMANCE!M124) | M46: =AVERAGE(RAW_PERFORMANCE!J122,RAW_PERFORMANCE!J123,RAW_PERFORMANCE!J124) | N46: =AVERAGE(RAW_PERFORMANCE!P122,RAW_PERFORMANCE!P123,RAW_PERFORMANCE!P124) | O46: COMPLETED DEVELOPMENT
A47: D007__TECO05 | B47: D007 | C47: TECO05 | D47: =AVERAGE(RAW_PERFORMANCE!F125,RAW_PERFORMANCE!F126,RAW_PERFORMANCE!F127) | E47: =AVERAGE(RAW_PERFORMANCE!G125,RAW_PERFORMANCE!G126,RAW_PERFORMANCE!G127) | F47: =AVERAGE(RAW_PERFORMANCE!H125,RAW_PERFORMANCE!H126,RAW_PERFORMANCE!H127) | G47: =AVERAGE(RAW_PERFORMANCE!I125,RAW_PERFORMANCE!I126,RAW_PERFORMANCE!I127) | H47: 0 | I47: =COUNT(RAW_PERFORMANCE!F125,RAW_PERFORMANCE!F126,RAW_PERFORMANCE!F127) | J47: =AVERAGE(RAW_PERFORMANCE!K125,RAW_PERFORMANCE!K126,RAW_PERFORMANCE!K127) | K47: =AVERAGE(RAW_PERFORMANCE!L125,RAW_PERFORMANCE!L126,RAW_PERFORMANCE!L127) | L47: =AVERAGE(RAW_PERFORMANCE!M125,RAW_PERFORMANCE!M126,RAW_PERFORMANCE!M127) | M47: =AVERAGE(RAW_PERFORMANCE!J125,RAW_PERFORMANCE!J126,RAW_PERFORMANCE!J127) | N47: =AVERAGE(RAW_PERFORMANCE!P125,RAW_PERFORMANCE!P126,RAW_PERFORMANCE!P127) | O47: COMPLETED DEVELOPMENT
A48: D007__TECO10 | B48: D007 | C48: TECO10 | D48: =AVERAGE(RAW_PERFORMANCE!F128,RAW_PERFORMANCE!F129,RAW_PERFORMANCE!F130) | E48: =AVERAGE(RAW_PERFORMANCE!G128,RAW_PERFORMANCE!G129,RAW_PERFORMANCE!G130) | F48: =AVERAGE(RAW_PERFORMANCE!H128,RAW_PERFORMANCE!H129,RAW_PERFORMANCE!H130) | G48: =AVERAGE(RAW_PERFORMANCE!I128,RAW_PERFORMANCE!I129,RAW_PERFORMANCE!I130) | H48: 1 | I48: =COUNT(RAW_PERFORMANCE!F128,RAW_PERFORMANCE!F129,RAW_PERFORMANCE!F130) | J48: =AVERAGE(RAW_PERFORMANCE!K128,RAW_PERFORMANCE!K129,RAW_PERFORMANCE!K130) | K48: =AVERAGE(RAW_PERFORMANCE!L128,RAW_PERFORMANCE!L129,RAW_PERFORMANCE!L130) | L48: =AVERAGE(RAW_PERFORMANCE!M128,RAW_PERFORMANCE!M129,RAW_PERFORMANCE!M130) | M48: =AVERAGE(RAW_PERFORMANCE!J128,RAW_PERFORMANCE!J129,RAW_PERFORMANCE!J130) | N48: =AVERAGE(RAW_PERFORMANCE!P128,RAW_PERFORMANCE!P129,RAW_PERFORMANCE!P130) | O48: COMPLETED DEVELOPMENT
A49: D007__TECO15 | B49: D007 | C49: TECO15 | D49: =AVERAGE(RAW_PERFORMANCE!F131,RAW_PERFORMANCE!F132,RAW_PERFORMANCE!F133) | E49: =AVERAGE(RAW_PERFORMANCE!G131,RAW_PERFORMANCE!G132,RAW_PERFORMANCE!G133) | F49: =AVERAGE(RAW_PERFORMANCE!H131,RAW_PERFORMANCE!H132,RAW_PERFORMANCE!H133) | G49: =AVERAGE(RAW_PERFORMANCE!I131,RAW_PERFORMANCE!I132,RAW_PERFORMANCE!I133) | H49: 0 | I49: =COUNT(RAW_PERFORMANCE!F131,RAW_PERFORMANCE!F132,RAW_PERFORMANCE!F133) | J49: =AVERAGE(RAW_PERFORMANCE!K131,RAW_PERFORMANCE!K132,RAW_PERFORMANCE!K133) | K49: =AVERAGE(RAW_PERFORMANCE!L131,RAW_PERFORMANCE!L132,RAW_PERFORMANCE!L133) | L49: =AVERAGE(RAW_PERFORMANCE!M131,RAW_PERFORMANCE!M132,RAW_PERFORMANCE!M133) | M49: =AVERAGE(RAW_PERFORMANCE!J131,RAW_PERFORMANCE!J132,RAW_PERFORMANCE!J133) | N49: =AVERAGE(RAW_PERFORMANCE!P131,RAW_PERFORMANCE!P132,RAW_PERFORMANCE!P133) | O49: COMPLETED DEVELOPMENT
A50: D008__SP | B50: D008 | C50: SP | D50: =AVERAGE(RAW_PERFORMANCE!F134,RAW_PERFORMANCE!F135,RAW_PERFORMANCE!F136) | E50: =AVERAGE(RAW_PERFORMANCE!G134,RAW_PERFORMANCE!G135,RAW_PERFORMANCE!G136) | F50: =AVERAGE(RAW_PERFORMANCE!H134,RAW_PERFORMANCE!H135,RAW_PERFORMANCE!H136) | G50: =AVERAGE(RAW_PERFORMANCE!I134,RAW_PERFORMANCE!I135,RAW_PERFORMANCE!I136) | H50: 1 | I50: =COUNT(RAW_PERFORMANCE!F134,RAW_PERFORMANCE!F135,RAW_PERFORMANCE!F136) | J50: =AVERAGE(RAW_PERFORMANCE!K134,RAW_PERFORMANCE!K135,RAW_PERFORMANCE!K136) | K50: =AVERAGE(RAW_PERFORMANCE!L134,RAW_PERFORMANCE!L135,RAW_PERFORMANCE!L136) | L50: =AVERAGE(RAW_PERFORMANCE!M134,RAW_PERFORMANCE!M135,RAW_PERFORMANCE!M136) | M50: =AVERAGE(RAW_PERFORMANCE!J134,RAW_PERFORMANCE!J135,RAW_PERFORMANCE!J136) | N50: =AVERAGE(RAW_PERFORMANCE!P134,RAW_PERFORMANCE!P135,RAW_PERFORMANCE!P136) | O50: COMPLETED DEVELOPMENT
A51: D008__DTT | B51: D008 | C51: DTT | D51: =AVERAGE(RAW_PERFORMANCE!F137,RAW_PERFORMANCE!F138,RAW_PERFORMANCE!F139) | E51: =AVERAGE(RAW_PERFORMANCE!G137,RAW_PERFORMANCE!G138,RAW_PERFORMANCE!G139) | F51: =AVERAGE(RAW_PERFORMANCE!H137,RAW_PERFORMANCE!H138,RAW_PERFORMANCE!H139) | G51: =AVERAGE(RAW_PERFORMANCE!I137,RAW_PERFORMANCE!I138,RAW_PERFORMANCE!I139) | H51: 1 | I51: =COUNT(RAW_PERFORMANCE!F137,RAW_PERFORMANCE!F138,RAW_PERFORMANCE!F139) | J51: =AVERAGE(RAW_PERFORMANCE!K137,RAW_PERFORMANCE!K138,RAW_PERFORMANCE!K139) | K51: =AVERAGE(RAW_PERFORMANCE!L137,RAW_PERFORMANCE!L138,RAW_PERFORMANCE!L139) | L51: =AVERAGE(RAW_PERFORMANCE!M137,RAW_PERFORMANCE!M138,RAW_PERFORMANCE!M139) | M51: =AVERAGE(RAW_PERFORMANCE!J137,RAW_PERFORMANCE!J138,RAW_PERFORMANCE!J139) | N51: =AVERAGE(RAW_PERFORMANCE!P137,RAW_PERFORMANCE!P138,RAW_PERFORMANCE!P139) | O51: COMPLETED DEVELOPMENT
A52: D008__ECO | B52: D008 | C52: ECO | D52: =AVERAGE(RAW_PERFORMANCE!F140,RAW_PERFORMANCE!F141,RAW_PERFORMANCE!F142) | E52: =AVERAGE(RAW_PERFORMANCE!G140,RAW_PERFORMANCE!G141,RAW_PERFORMANCE!G142) | F52: =AVERAGE(RAW_PERFORMANCE!H140,RAW_PERFORMANCE!H141,RAW_PERFORMANCE!H142) | G52: =AVERAGE(RAW_PERFORMANCE!I140,RAW_PERFORMANCE!I141,RAW_PERFORMANCE!I142) | H52: 1 | I52: =COUNT(RAW_PERFORMANCE!F140,RAW_PERFORMANCE!F141,RAW_PERFORMANCE!F142) | J52: =AVERAGE(RAW_PERFORMANCE!K140,RAW_PERFORMANCE!K141,RAW_PERFORMANCE!K142) | K52: =AVERAGE(RAW_PERFORMANCE!L140,RAW_PERFORMANCE!L141,RAW_PERFORMANCE!L142) | L52: =AVERAGE(RAW_PERFORMANCE!M140,RAW_PERFORMANCE!M141,RAW_PERFORMANCE!M142) | M52: =AVERAGE(RAW_PERFORMANCE!J140,RAW_PERFORMANCE!J141,RAW_PERFORMANCE!J142) | N52: =AVERAGE(RAW_PERFORMANCE!P140,RAW_PERFORMANCE!P141,RAW_PERFORMANCE!P142) | O52: COMPLETED DEVELOPMENT
A53: D008__TECO05 | B53: D008 | C53: TECO05 | D53: =AVERAGE(RAW_PERFORMANCE!F143,RAW_PERFORMANCE!F144,RAW_PERFORMANCE!F145) | E53: =AVERAGE(RAW_PERFORMANCE!G143,RAW_PERFORMANCE!G144,RAW_PERFORMANCE!G145) | F53: =AVERAGE(RAW_PERFORMANCE!H143,RAW_PERFORMANCE!H144,RAW_PERFORMANCE!H145) | G53: =AVERAGE(RAW_PERFORMANCE!I143,RAW_PERFORMANCE!I144,RAW_PERFORMANCE!I145) | H53: 0 | I53: =COUNT(RAW_PERFORMANCE!F143,RAW_PERFORMANCE!F144,RAW_PERFORMANCE!F145) | J53: =AVERAGE(RAW_PERFORMANCE!K143,RAW_PERFORMANCE!K144,RAW_PERFORMANCE!K145) | K53: =AVERAGE(RAW_PERFORMANCE!L143,RAW_PERFORMANCE!L144,RAW_PERFORMANCE!L145) | L53: =AVERAGE(RAW_PERFORMANCE!M143,RAW_PERFORMANCE!M144,RAW_PERFORMANCE!M145) | M53: =AVERAGE(RAW_PERFORMANCE!J143,RAW_PERFORMANCE!J144,RAW_PERFORMANCE!J145) | N53: =AVERAGE(RAW_PERFORMANCE!P143,RAW_PERFORMANCE!P144,RAW_PERFORMANCE!P145) | O53: COMPLETED DEVELOPMENT
A54: D008__TECO10 | B54: D008 | C54: TECO10 | D54: =AVERAGE(RAW_PERFORMANCE!F146,RAW_PERFORMANCE!F147,RAW_PERFORMANCE!F148) | E54: =AVERAGE(RAW_PERFORMANCE!G146,RAW_PERFORMANCE!G147,RAW_PERFORMANCE!G148) | F54: =AVERAGE(RAW_PERFORMANCE!H146,RAW_PERFORMANCE!H147,RAW_PERFORMANCE!H148) | G54: =AVERAGE(RAW_PERFORMANCE!I146,RAW_PERFORMANCE!I147,RAW_PERFORMANCE!I148) | H54: 1 | I54: =COUNT(RAW_PERFORMANCE!F146,RAW_PERFORMANCE!F147,RAW_PERFORMANCE!F148) | J54: =AVERAGE(RAW_PERFORMANCE!K146,RAW_PERFORMANCE!K147,RAW_PERFORMANCE!K148) | K54: =AVERAGE(RAW_PERFORMANCE!L146,RAW_PERFORMANCE!L147,RAW_PERFORMANCE!L148) | L54: =AVERAGE(RAW_PERFORMANCE!M146,RAW_PERFORMANCE!M147,RAW_PERFORMANCE!M148) | M54: =AVERAGE(RAW_PERFORMANCE!J146,RAW_PERFORMANCE!J147,RAW_PERFORMANCE!J148) | N54: =AVERAGE(RAW_PERFORMANCE!P146,RAW_PERFORMANCE!P147,RAW_PERFORMANCE!P148) | O54: COMPLETED DEVELOPMENT
A55: D008__TECO15 | B55: D008 | C55: TECO15 | D55: =AVERAGE(RAW_PERFORMANCE!F149,RAW_PERFORMANCE!F150,RAW_PERFORMANCE!F151) | E55: =AVERAGE(RAW_PERFORMANCE!G149,RAW_PERFORMANCE!G150,RAW_PERFORMANCE!G151) | F55: =AVERAGE(RAW_PERFORMANCE!H149,RAW_PERFORMANCE!H150,RAW_PERFORMANCE!H151) | G55: =AVERAGE(RAW_PERFORMANCE!I149,RAW_PERFORMANCE!I150,RAW_PERFORMANCE!I151) | H55: 0 | I55: =COUNT(RAW_PERFORMANCE!F149,RAW_PERFORMANCE!F150,RAW_PERFORMANCE!F151) | J55: =AVERAGE(RAW_PERFORMANCE!K149,RAW_PERFORMANCE!K150,RAW_PERFORMANCE!K151) | K55: =AVERAGE(RAW_PERFORMANCE!L149,RAW_PERFORMANCE!L150,RAW_PERFORMANCE!L151) | L55: =AVERAGE(RAW_PERFORMANCE!M149,RAW_PERFORMANCE!M150,RAW_PERFORMANCE!M151) | M55: =AVERAGE(RAW_PERFORMANCE!J149,RAW_PERFORMANCE!J150,RAW_PERFORMANCE!J151) | N55: =AVERAGE(RAW_PERFORMANCE!P149,RAW_PERFORMANCE!P150,RAW_PERFORMANCE!P151) | O55: COMPLETED DEVELOPMENT
A56: D009__SP | B56: D009 | C56: SP | D56: =AVERAGE(RAW_PERFORMANCE!F152,RAW_PERFORMANCE!F153,RAW_PERFORMANCE!F154) | E56: =AVERAGE(RAW_PERFORMANCE!G152,RAW_PERFORMANCE!G153,RAW_PERFORMANCE!G154) | F56: =AVERAGE(RAW_PERFORMANCE!H152,RAW_PERFORMANCE!H153,RAW_PERFORMANCE!H154) | G56: =AVERAGE(RAW_PERFORMANCE!I152,RAW_PERFORMANCE!I153,RAW_PERFORMANCE!I154) | H56: 1 | I56: =COUNT(RAW_PERFORMANCE!F152,RAW_PERFORMANCE!F153,RAW_PERFORMANCE!F154) | J56: =AVERAGE(RAW_PERFORMANCE!K152,RAW_PERFORMANCE!K153,RAW_PERFORMANCE!K154) | K56: =AVERAGE(RAW_PERFORMANCE!L152,RAW_PERFORMANCE!L153,RAW_PERFORMANCE!L154) | L56: =AVERAGE(RAW_PERFORMANCE!M152,RAW_PERFORMANCE!M153,RAW_PERFORMANCE!M154) | M56: =AVERAGE(RAW_PERFORMANCE!J152,RAW_PERFORMANCE!J153,RAW_PERFORMANCE!J154) | N56: =AVERAGE(RAW_PERFORMANCE!P152,RAW_PERFORMANCE!P153,RAW_PERFORMANCE!P154) | O56: COMPLETED DEVELOPMENT
A57: D009__DTT | B57: D009 | C57: DTT | D57: =AVERAGE(RAW_PERFORMANCE!F155,RAW_PERFORMANCE!F156,RAW_PERFORMANCE!F157) | E57: =AVERAGE(RAW_PERFORMANCE!G155,RAW_PERFORMANCE!G156,RAW_PERFORMANCE!G157) | F57: =AVERAGE(RAW_PERFORMANCE!H155,RAW_PERFORMANCE!H156,RAW_PERFORMANCE!H157) | G57: =AVERAGE(RAW_PERFORMANCE!I155,RAW_PERFORMANCE!I156,RAW_PERFORMANCE!I157) | H57: 1 | I57: =COUNT(RAW_PERFORMANCE!F155,RAW_PERFORMANCE!F156,RAW_PERFORMANCE!F157) | J57: =AVERAGE(RAW_PERFORMANCE!K155,RAW_PERFORMANCE!K156,RAW_PERFORMANCE!K157) | K57: =AVERAGE(RAW_PERFORMANCE!L155,RAW_PERFORMANCE!L156,RAW_PERFORMANCE!L157) | L57: =AVERAGE(RAW_PERFORMANCE!M155,RAW_PERFORMANCE!M156,RAW_PERFORMANCE!M157) | M57: =AVERAGE(RAW_PERFORMANCE!J155,RAW_PERFORMANCE!J156,RAW_PERFORMANCE!J157) | N57: =AVERAGE(RAW_PERFORMANCE!P155,RAW_PERFORMANCE!P156,RAW_PERFORMANCE!P157) | O57: COMPLETED DEVELOPMENT
A58: D009__ECO | B58: D009 | C58: ECO | D58: =AVERAGE(RAW_PERFORMANCE!F158,RAW_PERFORMANCE!F159,RAW_PERFORMANCE!F160) | E58: =AVERAGE(RAW_PERFORMANCE!G158,RAW_PERFORMANCE!G159,RAW_PERFORMANCE!G160) | F58: =AVERAGE(RAW_PERFORMANCE!H158,RAW_PERFORMANCE!H159,RAW_PERFORMANCE!H160) | G58: =AVERAGE(RAW_PERFORMANCE!I158,RAW_PERFORMANCE!I159,RAW_PERFORMANCE!I160) | H58: 1 | I58: =COUNT(RAW_PERFORMANCE!F158,RAW_PERFORMANCE!F159,RAW_PERFORMANCE!F160) | J58: =AVERAGE(RAW_PERFORMANCE!K158,RAW_PERFORMANCE!K159,RAW_PERFORMANCE!K160) | K58: =AVERAGE(RAW_PERFORMANCE!L158,RAW_PERFORMANCE!L159,RAW_PERFORMANCE!L160) | L58: =AVERAGE(RAW_PERFORMANCE!M158,RAW_PERFORMANCE!M159,RAW_PERFORMANCE!M160) | M58: =AVERAGE(RAW_PERFORMANCE!J158,RAW_PERFORMANCE!J159,RAW_PERFORMANCE!J160) | N58: =AVERAGE(RAW_PERFORMANCE!P158,RAW_PERFORMANCE!P159,RAW_PERFORMANCE!P160) | O58: COMPLETED DEVELOPMENT
A59: D009__TECO05 | B59: D009 | C59: TECO05 | D59: =AVERAGE(RAW_PERFORMANCE!F161,RAW_PERFORMANCE!F162,RAW_PERFORMANCE!F163) | E59: =AVERAGE(RAW_PERFORMANCE!G161,RAW_PERFORMANCE!G162,RAW_PERFORMANCE!G163) | F59: =AVERAGE(RAW_PERFORMANCE!H161,RAW_PERFORMANCE!H162,RAW_PERFORMANCE!H163) | G59: =AVERAGE(RAW_PERFORMANCE!I161,RAW_PERFORMANCE!I162,RAW_PERFORMANCE!I163) | H59: 0 | I59: =COUNT(RAW_PERFORMANCE!F161,RAW_PERFORMANCE!F162,RAW_PERFORMANCE!F163) | J59: =AVERAGE(RAW_PERFORMANCE!K161,RAW_PERFORMANCE!K162,RAW_PERFORMANCE!K163) | K59: =AVERAGE(RAW_PERFORMANCE!L161,RAW_PERFORMANCE!L162,RAW_PERFORMANCE!L163) | L59: =AVERAGE(RAW_PERFORMANCE!M161,RAW_PERFORMANCE!M162,RAW_PERFORMANCE!M163) | M59: =AVERAGE(RAW_PERFORMANCE!J161,RAW_PERFORMANCE!J162,RAW_PERFORMANCE!J163) | N59: =AVERAGE(RAW_PERFORMANCE!P161,RAW_PERFORMANCE!P162,RAW_PERFORMANCE!P163) | O59: COMPLETED DEVELOPMENT
A60: D009__TECO10 | B60: D009 | C60: TECO10 | D60: =AVERAGE(RAW_PERFORMANCE!F164,RAW_PERFORMANCE!F165,RAW_PERFORMANCE!F166) | E60: =AVERAGE(RAW_PERFORMANCE!G164,RAW_PERFORMANCE!G165,RAW_PERFORMANCE!G166) | F60: =AVERAGE(RAW_PERFORMANCE!H164,RAW_PERFORMANCE!H165,RAW_PERFORMANCE!H166) | G60: =AVERAGE(RAW_PERFORMANCE!I164,RAW_PERFORMANCE!I165,RAW_PERFORMANCE!I166) | H60: 1 | I60: =COUNT(RAW_PERFORMANCE!F164,RAW_PERFORMANCE!F165,RAW_PERFORMANCE!F166) | J60: =AVERAGE(RAW_PERFORMANCE!K164,RAW_PERFORMANCE!K165,RAW_PERFORMANCE!K166) | K60: =AVERAGE(RAW_PERFORMANCE!L164,RAW_PERFORMANCE!L165,RAW_PERFORMANCE!L166) | L60: =AVERAGE(RAW_PERFORMANCE!M164,RAW_PERFORMANCE!M165,RAW_PERFORMANCE!M166) | M60: =AVERAGE(RAW_PERFORMANCE!J164,RAW_PERFORMANCE!J165,RAW_PERFORMANCE!J166) | N60: =AVERAGE(RAW_PERFORMANCE!P164,RAW_PERFORMANCE!P165,RAW_PERFORMANCE!P166) | O60: COMPLETED DEVELOPMENT
A61: D009__TECO15 | B61: D009 | C61: TECO15 | D61: =AVERAGE(RAW_PERFORMANCE!F167,RAW_PERFORMANCE!F168,RAW_PERFORMANCE!F169) | E61: =AVERAGE(RAW_PERFORMANCE!G167,RAW_PERFORMANCE!G168,RAW_PERFORMANCE!G169) | F61: =AVERAGE(RAW_PERFORMANCE!H167,RAW_PERFORMANCE!H168,RAW_PERFORMANCE!H169) | G61: =AVERAGE(RAW_PERFORMANCE!I167,RAW_PERFORMANCE!I168,RAW_PERFORMANCE!I169) | H61: 0 | I61: =COUNT(RAW_PERFORMANCE!F167,RAW_PERFORMANCE!F168,RAW_PERFORMANCE!F169) | J61: =AVERAGE(RAW_PERFORMANCE!K167,RAW_PERFORMANCE!K168,RAW_PERFORMANCE!K169) | K61: =AVERAGE(RAW_PERFORMANCE!L167,RAW_PERFORMANCE!L168,RAW_PERFORMANCE!L169) | L61: =AVERAGE(RAW_PERFORMANCE!M167,RAW_PERFORMANCE!M168,RAW_PERFORMANCE!M169) | M61: =AVERAGE(RAW_PERFORMANCE!J167,RAW_PERFORMANCE!J168,RAW_PERFORMANCE!J169) | N61: =AVERAGE(RAW_PERFORMANCE!P167,RAW_PERFORMANCE!P168,RAW_PERFORMANCE!P169) | O61: COMPLETED DEVELOPMENT
A62: D010__SP | B62: D010 | C62: SP | D62: =AVERAGE(RAW_PERFORMANCE!F170,RAW_PERFORMANCE!F171,RAW_PERFORMANCE!F172) | E62: =AVERAGE(RAW_PERFORMANCE!G170,RAW_PERFORMANCE!G171,RAW_PERFORMANCE!G172) | F62: =AVERAGE(RAW_PERFORMANCE!H170,RAW_PERFORMANCE!H171,RAW_PERFORMANCE!H172) | G62: =AVERAGE(RAW_PERFORMANCE!I170,RAW_PERFORMANCE!I171,RAW_PERFORMANCE!I172) | H62: 1 | I62: =COUNT(RAW_PERFORMANCE!F170,RAW_PERFORMANCE!F171,RAW_PERFORMANCE!F172) | J62: =AVERAGE(RAW_PERFORMANCE!K170,RAW_PERFORMANCE!K171,RAW_PERFORMANCE!K172) | K62: =AVERAGE(RAW_PERFORMANCE!L170,RAW_PERFORMANCE!L171,RAW_PERFORMANCE!L172) | L62: =AVERAGE(RAW_PERFORMANCE!M170,RAW_PERFORMANCE!M171,RAW_PERFORMANCE!M172) | M62: =AVERAGE(RAW_PERFORMANCE!J170,RAW_PERFORMANCE!J171,RAW_PERFORMANCE!J172) | N62: =AVERAGE(RAW_PERFORMANCE!P170,RAW_PERFORMANCE!P171,RAW_PERFORMANCE!P172) | O62: COMPLETED DEVELOPMENT
A63: D010__DTT | B63: D010 | C63: DTT | D63: =AVERAGE(RAW_PERFORMANCE!F173,RAW_PERFORMANCE!F174,RAW_PERFORMANCE!F175) | E63: =AVERAGE(RAW_PERFORMANCE!G173,RAW_PERFORMANCE!G174,RAW_PERFORMANCE!G175) | F63: =AVERAGE(RAW_PERFORMANCE!H173,RAW_PERFORMANCE!H174,RAW_PERFORMANCE!H175) | G63: =AVERAGE(RAW_PERFORMANCE!I173,RAW_PERFORMANCE!I174,RAW_PERFORMANCE!I175) | H63: 1 | I63: =COUNT(RAW_PERFORMANCE!F173,RAW_PERFORMANCE!F174,RAW_PERFORMANCE!F175) | J63: =AVERAGE(RAW_PERFORMANCE!K173,RAW_PERFORMANCE!K174,RAW_PERFORMANCE!K175) | K63: =AVERAGE(RAW_PERFORMANCE!L173,RAW_PERFORMANCE!L174,RAW_PERFORMANCE!L175) | L63: =AVERAGE(RAW_PERFORMANCE!M173,RAW_PERFORMANCE!M174,RAW_PERFORMANCE!M175) | M63: =AVERAGE(RAW_PERFORMANCE!J173,RAW_PERFORMANCE!J174,RAW_PERFORMANCE!J175) | N63: =AVERAGE(RAW_PERFORMANCE!P173,RAW_PERFORMANCE!P174,RAW_PERFORMANCE!P175) | O63: COMPLETED DEVELOPMENT
A64: D010__ECO | B64: D010 | C64: ECO | D64: =AVERAGE(RAW_PERFORMANCE!F176,RAW_PERFORMANCE!F177,RAW_PERFORMANCE!F178) | E64: =AVERAGE(RAW_PERFORMANCE!G176,RAW_PERFORMANCE!G177,RAW_PERFORMANCE!G178) | F64: =AVERAGE(RAW_PERFORMANCE!H176,RAW_PERFORMANCE!H177,RAW_PERFORMANCE!H178) | G64: =AVERAGE(RAW_PERFORMANCE!I176,RAW_PERFORMANCE!I177,RAW_PERFORMANCE!I178) | H64: 1 | I64: =COUNT(RAW_PERFORMANCE!F176,RAW_PERFORMANCE!F177,RAW_PERFORMANCE!F178) | J64: =AVERAGE(RAW_PERFORMANCE!K176,RAW_PERFORMANCE!K177,RAW_PERFORMANCE!K178) | K64: =AVERAGE(RAW_PERFORMANCE!L176,RAW_PERFORMANCE!L177,RAW_PERFORMANCE!L178) | L64: =AVERAGE(RAW_PERFORMANCE!M176,RAW_PERFORMANCE!M177,RAW_PERFORMANCE!M178) | M64: =AVERAGE(RAW_PERFORMANCE!J176,RAW_PERFORMANCE!J177,RAW_PERFORMANCE!J178) | N64: =AVERAGE(RAW_PERFORMANCE!P176,RAW_PERFORMANCE!P177,RAW_PERFORMANCE!P178) | O64: COMPLETED DEVELOPMENT
A65: D010__TECO05 | B65: D010 | C65: TECO05 | D65: =AVERAGE(RAW_PERFORMANCE!F179,RAW_PERFORMANCE!F180,RAW_PERFORMANCE!F181) | E65: =AVERAGE(RAW_PERFORMANCE!G179,RAW_PERFORMANCE!G180,RAW_PERFORMANCE!G181) | F65: =AVERAGE(RAW_PERFORMANCE!H179,RAW_PERFORMANCE!H180,RAW_PERFORMANCE!H181) | G65: =AVERAGE(RAW_PERFORMANCE!I179,RAW_PERFORMANCE!I180,RAW_PERFORMANCE!I181) | H65: 0 | I65: =COUNT(RAW_PERFORMANCE!F179,RAW_PERFORMANCE!F180,RAW_PERFORMANCE!F181) | J65: =AVERAGE(RAW_PERFORMANCE!K179,RAW_PERFORMANCE!K180,RAW_PERFORMANCE!K181) | K65: =AVERAGE(RAW_PERFORMANCE!L179,RAW_PERFORMANCE!L180,RAW_PERFORMANCE!L181) | L65: =AVERAGE(RAW_PERFORMANCE!M179,RAW_PERFORMANCE!M180,RAW_PERFORMANCE!M181) | M65: =AVERAGE(RAW_PERFORMANCE!J179,RAW_PERFORMANCE!J180,RAW_PERFORMANCE!J181) | N65: =AVERAGE(RAW_PERFORMANCE!P179,RAW_PERFORMANCE!P180,RAW_PERFORMANCE!P181) | O65: COMPLETED DEVELOPMENT
A66: D010__TECO10 | B66: D010 | C66: TECO10 | D66: =AVERAGE(RAW_PERFORMANCE!F182,RAW_PERFORMANCE!F183,RAW_PERFORMANCE!F184) | E66: =AVERAGE(RAW_PERFORMANCE!G182,RAW_PERFORMANCE!G183,RAW_PERFORMANCE!G184) | F66: =AVERAGE(RAW_PERFORMANCE!H182,RAW_PERFORMANCE!H183,RAW_PERFORMANCE!H184) | G66: =AVERAGE(RAW_PERFORMANCE!I182,RAW_PERFORMANCE!I183,RAW_PERFORMANCE!I184) | H66: 1 | I66: =COUNT(RAW_PERFORMANCE!F182,RAW_PERFORMANCE!F183,RAW_PERFORMANCE!F184) | J66: =AVERAGE(RAW_PERFORMANCE!K182,RAW_PERFORMANCE!K183,RAW_PERFORMANCE!K184) | K66: =AVERAGE(RAW_PERFORMANCE!L182,RAW_PERFORMANCE!L183,RAW_PERFORMANCE!L184) | L66: =AVERAGE(RAW_PERFORMANCE!M182,RAW_PERFORMANCE!M183,RAW_PERFORMANCE!M184) | M66: =AVERAGE(RAW_PERFORMANCE!J182,RAW_PERFORMANCE!J183,RAW_PERFORMANCE!J184) | N66: =AVERAGE(RAW_PERFORMANCE!P182,RAW_PERFORMANCE!P183,RAW_PERFORMANCE!P184) | O66: COMPLETED DEVELOPMENT
A67: D010__TECO15 | B67: D010 | C67: TECO15 | D67: =AVERAGE(RAW_PERFORMANCE!F185,RAW_PERFORMANCE!F186,RAW_PERFORMANCE!F187) | E67: =AVERAGE(RAW_PERFORMANCE!G185,RAW_PERFORMANCE!G186,RAW_PERFORMANCE!G187) | F67: =AVERAGE(RAW_PERFORMANCE!H185,RAW_PERFORMANCE!H186,RAW_PERFORMANCE!H187) | G67: =AVERAGE(RAW_PERFORMANCE!I185,RAW_PERFORMANCE!I186,RAW_PERFORMANCE!I187) | H67: 0 | I67: =COUNT(RAW_PERFORMANCE!F185,RAW_PERFORMANCE!F186,RAW_PERFORMANCE!F187) | J67: =AVERAGE(RAW_PERFORMANCE!K185,RAW_PERFORMANCE!K186,RAW_PERFORMANCE!K187) | K67: =AVERAGE(RAW_PERFORMANCE!L185,RAW_PERFORMANCE!L186,RAW_PERFORMANCE!L187) | L67: =AVERAGE(RAW_PERFORMANCE!M185,RAW_PERFORMANCE!M186,RAW_PERFORMANCE!M187) | M67: =AVERAGE(RAW_PERFORMANCE!J185,RAW_PERFORMANCE!J186,RAW_PERFORMANCE!J187) | N67: =AVERAGE(RAW_PERFORMANCE!P185,RAW_PERFORMANCE!P186,RAW_PERFORMANCE!P187) | O67: COMPLETED DEVELOPMENT
A68: D011__SP | B68: D011 | C68: SP | D68: =AVERAGE(RAW_PERFORMANCE!F188,RAW_PERFORMANCE!F189,RAW_PERFORMANCE!F190) | E68: =AVERAGE(RAW_PERFORMANCE!G188,RAW_PERFORMANCE!G189,RAW_PERFORMANCE!G190) | F68: =AVERAGE(RAW_PERFORMANCE!H188,RAW_PERFORMANCE!H189,RAW_PERFORMANCE!H190) | G68: =AVERAGE(RAW_PERFORMANCE!I188,RAW_PERFORMANCE!I189,RAW_PERFORMANCE!I190) | H68: 1 | I68: =COUNT(RAW_PERFORMANCE!F188,RAW_PERFORMANCE!F189,RAW_PERFORMANCE!F190) | J68: =AVERAGE(RAW_PERFORMANCE!K188,RAW_PERFORMANCE!K189,RAW_PERFORMANCE!K190) | K68: =AVERAGE(RAW_PERFORMANCE!L188,RAW_PERFORMANCE!L189,RAW_PERFORMANCE!L190) | L68: =AVERAGE(RAW_PERFORMANCE!M188,RAW_PERFORMANCE!M189,RAW_PERFORMANCE!M190) | M68: =AVERAGE(RAW_PERFORMANCE!J188,RAW_PERFORMANCE!J189,RAW_PERFORMANCE!J190) | N68: =AVERAGE(RAW_PERFORMANCE!P188,RAW_PERFORMANCE!P189,RAW_PERFORMANCE!P190) | O68: COMPLETED DEVELOPMENT
A69: D011__DTT | B69: D011 | C69: DTT | D69: =AVERAGE(RAW_PERFORMANCE!F191,RAW_PERFORMANCE!F192,RAW_PERFORMANCE!F193) | E69: =AVERAGE(RAW_PERFORMANCE!G191,RAW_PERFORMANCE!G192,RAW_PERFORMANCE!G193) | F69: =AVERAGE(RAW_PERFORMANCE!H191,RAW_PERFORMANCE!H192,RAW_PERFORMANCE!H193) | G69: =AVERAGE(RAW_PERFORMANCE!I191,RAW_PERFORMANCE!I192,RAW_PERFORMANCE!I193) | H69: 1 | I69: =COUNT(RAW_PERFORMANCE!F191,RAW_PERFORMANCE!F192,RAW_PERFORMANCE!F193) | J69: =AVERAGE(RAW_PERFORMANCE!K191,RAW_PERFORMANCE!K192,RAW_PERFORMANCE!K193) | K69: =AVERAGE(RAW_PERFORMANCE!L191,RAW_PERFORMANCE!L192,RAW_PERFORMANCE!L193) | L69: =AVERAGE(RAW_PERFORMANCE!M191,RAW_PERFORMANCE!M192,RAW_PERFORMANCE!M193) | M69: =AVERAGE(RAW_PERFORMANCE!J191,RAW_PERFORMANCE!J192,RAW_PERFORMANCE!J193) | N69: =AVERAGE(RAW_PERFORMANCE!P191,RAW_PERFORMANCE!P192,RAW_PERFORMANCE!P193) | O69: COMPLETED DEVELOPMENT
A70: D011__ECO | B70: D011 | C70: ECO | D70: =AVERAGE(RAW_PERFORMANCE!F194,RAW_PERFORMANCE!F195,RAW_PERFORMANCE!F196) | E70: =AVERAGE(RAW_PERFORMANCE!G194,RAW_PERFORMANCE!G195,RAW_PERFORMANCE!G196) | F70: =AVERAGE(RAW_PERFORMANCE!H194,RAW_PERFORMANCE!H195,RAW_PERFORMANCE!H196) | G70: =AVERAGE(RAW_PERFORMANCE!I194,RAW_PERFORMANCE!I195,RAW_PERFORMANCE!I196) | H70: 1 | I70: =COUNT(RAW_PERFORMANCE!F194,RAW_PERFORMANCE!F195,RAW_PERFORMANCE!F196) | J70: =AVERAGE(RAW_PERFORMANCE!K194,RAW_PERFORMANCE!K195,RAW_PERFORMANCE!K196) | K70: =AVERAGE(RAW_PERFORMANCE!L194,RAW_PERFORMANCE!L195,RAW_PERFORMANCE!L196) | L70: =AVERAGE(RAW_PERFORMANCE!M194,RAW_PERFORMANCE!M195,RAW_PERFORMANCE!M196) | M70: =AVERAGE(RAW_PERFORMANCE!J194,RAW_PERFORMANCE!J195,RAW_PERFORMANCE!J196) | N70: =AVERAGE(RAW_PERFORMANCE!P194,RAW_PERFORMANCE!P195,RAW_PERFORMANCE!P196) | O70: COMPLETED DEVELOPMENT
A71: D011__TECO05 | B71: D011 | C71: TECO05 | D71: =AVERAGE(RAW_PERFORMANCE!F197,RAW_PERFORMANCE!F198,RAW_PERFORMANCE!F199) | E71: =AVERAGE(RAW_PERFORMANCE!G197,RAW_PERFORMANCE!G198,RAW_PERFORMANCE!G199) | F71: =AVERAGE(RAW_PERFORMANCE!H197,RAW_PERFORMANCE!H198,RAW_PERFORMANCE!H199) | G71: =AVERAGE(RAW_PERFORMANCE!I197,RAW_PERFORMANCE!I198,RAW_PERFORMANCE!I199) | H71: 0 | I71: =COUNT(RAW_PERFORMANCE!F197,RAW_PERFORMANCE!F198,RAW_PERFORMANCE!F199) | J71: =AVERAGE(RAW_PERFORMANCE!K197,RAW_PERFORMANCE!K198,RAW_PERFORMANCE!K199) | K71: =AVERAGE(RAW_PERFORMANCE!L197,RAW_PERFORMANCE!L198,RAW_PERFORMANCE!L199) | L71: =AVERAGE(RAW_PERFORMANCE!M197,RAW_PERFORMANCE!M198,RAW_PERFORMANCE!M199) | M71: =AVERAGE(RAW_PERFORMANCE!J197,RAW_PERFORMANCE!J198,RAW_PERFORMANCE!J199) | N71: =AVERAGE(RAW_PERFORMANCE!P197,RAW_PERFORMANCE!P198,RAW_PERFORMANCE!P199) | O71: COMPLETED DEVELOPMENT
A72: D011__TECO10 | B72: D011 | C72: TECO10 | D72: =AVERAGE(RAW_PERFORMANCE!F200,RAW_PERFORMANCE!F201,RAW_PERFORMANCE!F202) | E72: =AVERAGE(RAW_PERFORMANCE!G200,RAW_PERFORMANCE!G201,RAW_PERFORMANCE!G202) | F72: =AVERAGE(RAW_PERFORMANCE!H200,RAW_PERFORMANCE!H201,RAW_PERFORMANCE!H202) | G72: =AVERAGE(RAW_PERFORMANCE!I200,RAW_PERFORMANCE!I201,RAW_PERFORMANCE!I202) | H72: 1 | I72: =COUNT(RAW_PERFORMANCE!F200,RAW_PERFORMANCE!F201,RAW_PERFORMANCE!F202) | J72: =AVERAGE(RAW_PERFORMANCE!K200,RAW_PERFORMANCE!K201,RAW_PERFORMANCE!K202) | K72: =AVERAGE(RAW_PERFORMANCE!L200,RAW_PERFORMANCE!L201,RAW_PERFORMANCE!L202) | L72: =AVERAGE(RAW_PERFORMANCE!M200,RAW_PERFORMANCE!M201,RAW_PERFORMANCE!M202) | M72: =AVERAGE(RAW_PERFORMANCE!J200,RAW_PERFORMANCE!J201,RAW_PERFORMANCE!J202) | N72: =AVERAGE(RAW_PERFORMANCE!P200,RAW_PERFORMANCE!P201,RAW_PERFORMANCE!P202) | O72: COMPLETED DEVELOPMENT
A73: D011__TECO15 | B73: D011 | C73: TECO15 | D73: =AVERAGE(RAW_PERFORMANCE!F203,RAW_PERFORMANCE!F204,RAW_PERFORMANCE!F205) | E73: =AVERAGE(RAW_PERFORMANCE!G203,RAW_PERFORMANCE!G204,RAW_PERFORMANCE!G205) | F73: =AVERAGE(RAW_PERFORMANCE!H203,RAW_PERFORMANCE!H204,RAW_PERFORMANCE!H205) | G73: =AVERAGE(RAW_PERFORMANCE!I203,RAW_PERFORMANCE!I204,RAW_PERFORMANCE!I205) | H73: 0 | I73: =COUNT(RAW_PERFORMANCE!F203,RAW_PERFORMANCE!F204,RAW_PERFORMANCE!F205) | J73: =AVERAGE(RAW_PERFORMANCE!K203,RAW_PERFORMANCE!K204,RAW_PERFORMANCE!K205) | K73: =AVERAGE(RAW_PERFORMANCE!L203,RAW_PERFORMANCE!L204,RAW_PERFORMANCE!L205) | L73: =AVERAGE(RAW_PERFORMANCE!M203,RAW_PERFORMANCE!M204,RAW_PERFORMANCE!M205) | M73: =AVERAGE(RAW_PERFORMANCE!J203,RAW_PERFORMANCE!J204,RAW_PERFORMANCE!J205) | N73: =AVERAGE(RAW_PERFORMANCE!P203,RAW_PERFORMANCE!P204,RAW_PERFORMANCE!P205) | O73: COMPLETED DEVELOPMENT
A74: D012__SP | B74: D012 | C74: SP | D74: =AVERAGE(RAW_PERFORMANCE!F206,RAW_PERFORMANCE!F207,RAW_PERFORMANCE!F208) | E74: =AVERAGE(RAW_PERFORMANCE!G206,RAW_PERFORMANCE!G207,RAW_PERFORMANCE!G208) | F74: =AVERAGE(RAW_PERFORMANCE!H206,RAW_PERFORMANCE!H207,RAW_PERFORMANCE!H208) | G74: =AVERAGE(RAW_PERFORMANCE!I206,RAW_PERFORMANCE!I207,RAW_PERFORMANCE!I208) | H74: 1 | I74: =COUNT(RAW_PERFORMANCE!F206,RAW_PERFORMANCE!F207,RAW_PERFORMANCE!F208) | J74: =AVERAGE(RAW_PERFORMANCE!K206,RAW_PERFORMANCE!K207,RAW_PERFORMANCE!K208) | K74: =AVERAGE(RAW_PERFORMANCE!L206,RAW_PERFORMANCE!L207,RAW_PERFORMANCE!L208) | L74: =AVERAGE(RAW_PERFORMANCE!M206,RAW_PERFORMANCE!M207,RAW_PERFORMANCE!M208) | M74: =AVERAGE(RAW_PERFORMANCE!J206,RAW_PERFORMANCE!J207,RAW_PERFORMANCE!J208) | N74: =AVERAGE(RAW_PERFORMANCE!P206,RAW_PERFORMANCE!P207,RAW_PERFORMANCE!P208) | O74: COMPLETED DEVELOPMENT
A75: D012__DTT | B75: D012 | C75: DTT | D75: =AVERAGE(RAW_PERFORMANCE!F209,RAW_PERFORMANCE!F210,RAW_PERFORMANCE!F211) | E75: =AVERAGE(RAW_PERFORMANCE!G209,RAW_PERFORMANCE!G210,RAW_PERFORMANCE!G211) | F75: =AVERAGE(RAW_PERFORMANCE!H209,RAW_PERFORMANCE!H210,RAW_PERFORMANCE!H211) | G75: =AVERAGE(RAW_PERFORMANCE!I209,RAW_PERFORMANCE!I210,RAW_PERFORMANCE!I211) | H75: 1 | I75: =COUNT(RAW_PERFORMANCE!F209,RAW_PERFORMANCE!F210,RAW_PERFORMANCE!F211) | J75: =AVERAGE(RAW_PERFORMANCE!K209,RAW_PERFORMANCE!K210,RAW_PERFORMANCE!K211) | K75: =AVERAGE(RAW_PERFORMANCE!L209,RAW_PERFORMANCE!L210,RAW_PERFORMANCE!L211) | L75: =AVERAGE(RAW_PERFORMANCE!M209,RAW_PERFORMANCE!M210,RAW_PERFORMANCE!M211) | M75: =AVERAGE(RAW_PERFORMANCE!J209,RAW_PERFORMANCE!J210,RAW_PERFORMANCE!J211) | N75: =AVERAGE(RAW_PERFORMANCE!P209,RAW_PERFORMANCE!P210,RAW_PERFORMANCE!P211) | O75: COMPLETED DEVELOPMENT
A76: D012__ECO | B76: D012 | C76: ECO | D76: =AVERAGE(RAW_PERFORMANCE!F212,RAW_PERFORMANCE!F213,RAW_PERFORMANCE!F214) | E76: =AVERAGE(RAW_PERFORMANCE!G212,RAW_PERFORMANCE!G213,RAW_PERFORMANCE!G214) | F76: =AVERAGE(RAW_PERFORMANCE!H212,RAW_PERFORMANCE!H213,RAW_PERFORMANCE!H214) | G76: =AVERAGE(RAW_PERFORMANCE!I212,RAW_PERFORMANCE!I213,RAW_PERFORMANCE!I214) | H76: 1 | I76: =COUNT(RAW_PERFORMANCE!F212,RAW_PERFORMANCE!F213,RAW_PERFORMANCE!F214) | J76: =AVERAGE(RAW_PERFORMANCE!K212,RAW_PERFORMANCE!K213,RAW_PERFORMANCE!K214) | K76: =AVERAGE(RAW_PERFORMANCE!L212,RAW_PERFORMANCE!L213,RAW_PERFORMANCE!L214) | L76: =AVERAGE(RAW_PERFORMANCE!M212,RAW_PERFORMANCE!M213,RAW_PERFORMANCE!M214) | M76: =AVERAGE(RAW_PERFORMANCE!J212,RAW_PERFORMANCE!J213,RAW_PERFORMANCE!J214) | N76: =AVERAGE(RAW_PERFORMANCE!P212,RAW_PERFORMANCE!P213,RAW_PERFORMANCE!P214) | O76: COMPLETED DEVELOPMENT
A77: D012__TECO05 | B77: D012 | C77: TECO05 | D77: =AVERAGE(RAW_PERFORMANCE!F215,RAW_PERFORMANCE!F216,RAW_PERFORMANCE!F217) | E77: =AVERAGE(RAW_PERFORMANCE!G215,RAW_PERFORMANCE!G216,RAW_PERFORMANCE!G217) | F77: =AVERAGE(RAW_PERFORMANCE!H215,RAW_PERFORMANCE!H216,RAW_PERFORMANCE!H217) | G77: =AVERAGE(RAW_PERFORMANCE!I215,RAW_PERFORMANCE!I216,RAW_PERFORMANCE!I217) | H77: 0 | I77: =COUNT(RAW_PERFORMANCE!F215,RAW_PERFORMANCE!F216,RAW_PERFORMANCE!F217) | J77: =AVERAGE(RAW_PERFORMANCE!K215,RAW_PERFORMANCE!K216,RAW_PERFORMANCE!K217) | K77: =AVERAGE(RAW_PERFORMANCE!L215,RAW_PERFORMANCE!L216,RAW_PERFORMANCE!L217) | L77: =AVERAGE(RAW_PERFORMANCE!M215,RAW_PERFORMANCE!M216,RAW_PERFORMANCE!M217) | M77: =AVERAGE(RAW_PERFORMANCE!J215,RAW_PERFORMANCE!J216,RAW_PERFORMANCE!J217) | N77: =AVERAGE(RAW_PERFORMANCE!P215,RAW_PERFORMANCE!P216,RAW_PERFORMANCE!P217) | O77: COMPLETED DEVELOPMENT
A78: D012__TECO10 | B78: D012 | C78: TECO10 | D78: =AVERAGE(RAW_PERFORMANCE!F218,RAW_PERFORMANCE!F219,RAW_PERFORMANCE!F220) | E78: =AVERAGE(RAW_PERFORMANCE!G218,RAW_PERFORMANCE!G219,RAW_PERFORMANCE!G220) | F78: =AVERAGE(RAW_PERFORMANCE!H218,RAW_PERFORMANCE!H219,RAW_PERFORMANCE!H220) | G78: =AVERAGE(RAW_PERFORMANCE!I218,RAW_PERFORMANCE!I219,RAW_PERFORMANCE!I220) | H78: 1 | I78: =COUNT(RAW_PERFORMANCE!F218,RAW_PERFORMANCE!F219,RAW_PERFORMANCE!F220) | J78: =AVERAGE(RAW_PERFORMANCE!K218,RAW_PERFORMANCE!K219,RAW_PERFORMANCE!K220) | K78: =AVERAGE(RAW_PERFORMANCE!L218,RAW_PERFORMANCE!L219,RAW_PERFORMANCE!L220) | L78: =AVERAGE(RAW_PERFORMANCE!M218,RAW_PERFORMANCE!M219,RAW_PERFORMANCE!M220) | M78: =AVERAGE(RAW_PERFORMANCE!J218,RAW_PERFORMANCE!J219,RAW_PERFORMANCE!J220) | N78: =AVERAGE(RAW_PERFORMANCE!P218,RAW_PERFORMANCE!P219,RAW_PERFORMANCE!P220) | O78: COMPLETED DEVELOPMENT
A79: D012__TECO15 | B79: D012 | C79: TECO15 | D79: =AVERAGE(RAW_PERFORMANCE!F221,RAW_PERFORMANCE!F222,RAW_PERFORMANCE!F223) | E79: =AVERAGE(RAW_PERFORMANCE!G221,RAW_PERFORMANCE!G222,RAW_PERFORMANCE!G223) | F79: =AVERAGE(RAW_PERFORMANCE!H221,RAW_PERFORMANCE!H222,RAW_PERFORMANCE!H223) | G79: =AVERAGE(RAW_PERFORMANCE!I221,RAW_PERFORMANCE!I222,RAW_PERFORMANCE!I223) | H79: 0 | I79: =COUNT(RAW_PERFORMANCE!F221,RAW_PERFORMANCE!F222,RAW_PERFORMANCE!F223) | J79: =AVERAGE(RAW_PERFORMANCE!K221,RAW_PERFORMANCE!K222,RAW_PERFORMANCE!K223) | K79: =AVERAGE(RAW_PERFORMANCE!L221,RAW_PERFORMANCE!L222,RAW_PERFORMANCE!L223) | L79: =AVERAGE(RAW_PERFORMANCE!M221,RAW_PERFORMANCE!M222,RAW_PERFORMANCE!M223) | M79: =AVERAGE(RAW_PERFORMANCE!J221,RAW_PERFORMANCE!J222,RAW_PERFORMANCE!J223) | N79: =AVERAGE(RAW_PERFORMANCE!P221,RAW_PERFORMANCE!P222,RAW_PERFORMANCE!P223) | O79: COMPLETED DEVELOPMENT
A80: D013__SP | B80: D013 | C80: SP | D80: =AVERAGE(RAW_PERFORMANCE!F224,RAW_PERFORMANCE!F225,RAW_PERFORMANCE!F226) | E80: =AVERAGE(RAW_PERFORMANCE!G224,RAW_PERFORMANCE!G225,RAW_PERFORMANCE!G226) | F80: =AVERAGE(RAW_PERFORMANCE!H224,RAW_PERFORMANCE!H225,RAW_PERFORMANCE!H226) | G80: =AVERAGE(RAW_PERFORMANCE!I224,RAW_PERFORMANCE!I225,RAW_PERFORMANCE!I226) | H80: 1 | I80: =COUNT(RAW_PERFORMANCE!F224,RAW_PERFORMANCE!F225,RAW_PERFORMANCE!F226) | J80: =AVERAGE(RAW_PERFORMANCE!K224,RAW_PERFORMANCE!K225,RAW_PERFORMANCE!K226) | K80: =AVERAGE(RAW_PERFORMANCE!L224,RAW_PERFORMANCE!L225,RAW_PERFORMANCE!L226) | L80: =AVERAGE(RAW_PERFORMANCE!M224,RAW_PERFORMANCE!M225,RAW_PERFORMANCE!M226) | M80: =AVERAGE(RAW_PERFORMANCE!J224,RAW_PERFORMANCE!J225,RAW_PERFORMANCE!J226) | N80: =AVERAGE(RAW_PERFORMANCE!P224,RAW_PERFORMANCE!P225,RAW_PERFORMANCE!P226) | O80: COMPLETED DEVELOPMENT
A81: D013__DTT | B81: D013 | C81: DTT | D81: =AVERAGE(RAW_PERFORMANCE!F227,RAW_PERFORMANCE!F228,RAW_PERFORMANCE!F229) | E81: =AVERAGE(RAW_PERFORMANCE!G227,RAW_PERFORMANCE!G228,RAW_PERFORMANCE!G229) | F81: =AVERAGE(RAW_PERFORMANCE!H227,RAW_PERFORMANCE!H228,RAW_PERFORMANCE!H229) | G81: =AVERAGE(RAW_PERFORMANCE!I227,RAW_PERFORMANCE!I228,RAW_PERFORMANCE!I229) | H81: 1 | I81: =COUNT(RAW_PERFORMANCE!F227,RAW_PERFORMANCE!F228,RAW_PERFORMANCE!F229) | J81: =AVERAGE(RAW_PERFORMANCE!K227,RAW_PERFORMANCE!K228,RAW_PERFORMANCE!K229) | K81: =AVERAGE(RAW_PERFORMANCE!L227,RAW_PERFORMANCE!L228,RAW_PERFORMANCE!L229) | L81: =AVERAGE(RAW_PERFORMANCE!M227,RAW_PERFORMANCE!M228,RAW_PERFORMANCE!M229) | M81: =AVERAGE(RAW_PERFORMANCE!J227,RAW_PERFORMANCE!J228,RAW_PERFORMANCE!J229) | N81: =AVERAGE(RAW_PERFORMANCE!P227,RAW_PERFORMANCE!P228,RAW_PERFORMANCE!P229) | O81: COMPLETED DEVELOPMENT
A82: D013__ECO | B82: D013 | C82: ECO | D82: =AVERAGE(RAW_PERFORMANCE!F230,RAW_PERFORMANCE!F231,RAW_PERFORMANCE!F232) | E82: =AVERAGE(RAW_PERFORMANCE!G230,RAW_PERFORMANCE!G231,RAW_PERFORMANCE!G232) | F82: =AVERAGE(RAW_PERFORMANCE!H230,RAW_PERFORMANCE!H231,RAW_PERFORMANCE!H232) | G82: =AVERAGE(RAW_PERFORMANCE!I230,RAW_PERFORMANCE!I231,RAW_PERFORMANCE!I232) | H82: 1 | I82: =COUNT(RAW_PERFORMANCE!F230,RAW_PERFORMANCE!F231,RAW_PERFORMANCE!F232) | J82: =AVERAGE(RAW_PERFORMANCE!K230,RAW_PERFORMANCE!K231,RAW_PERFORMANCE!K232) | K82: =AVERAGE(RAW_PERFORMANCE!L230,RAW_PERFORMANCE!L231,RAW_PERFORMANCE!L232) | L82: =AVERAGE(RAW_PERFORMANCE!M230,RAW_PERFORMANCE!M231,RAW_PERFORMANCE!M232) | M82: =AVERAGE(RAW_PERFORMANCE!J230,RAW_PERFORMANCE!J231,RAW_PERFORMANCE!J232) | N82: =AVERAGE(RAW_PERFORMANCE!P230,RAW_PERFORMANCE!P231,RAW_PERFORMANCE!P232) | O82: COMPLETED DEVELOPMENT
A83: D013__TECO05 | B83: D013 | C83: TECO05 | D83: =AVERAGE(RAW_PERFORMANCE!F233,RAW_PERFORMANCE!F234,RAW_PERFORMANCE!F235) | E83: =AVERAGE(RAW_PERFORMANCE!G233,RAW_PERFORMANCE!G234,RAW_PERFORMANCE!G235) | F83: =AVERAGE(RAW_PERFORMANCE!H233,RAW_PERFORMANCE!H234,RAW_PERFORMANCE!H235) | G83: =AVERAGE(RAW_PERFORMANCE!I233,RAW_PERFORMANCE!I234,RAW_PERFORMANCE!I235) | H83: 0 | I83: =COUNT(RAW_PERFORMANCE!F233,RAW_PERFORMANCE!F234,RAW_PERFORMANCE!F235) | J83: =AVERAGE(RAW_PERFORMANCE!K233,RAW_PERFORMANCE!K234,RAW_PERFORMANCE!K235) | K83: =AVERAGE(RAW_PERFORMANCE!L233,RAW_PERFORMANCE!L234,RAW_PERFORMANCE!L235) | L83: =AVERAGE(RAW_PERFORMANCE!M233,RAW_PERFORMANCE!M234,RAW_PERFORMANCE!M235) | M83: =AVERAGE(RAW_PERFORMANCE!J233,RAW_PERFORMANCE!J234,RAW_PERFORMANCE!J235) | N83: =AVERAGE(RAW_PERFORMANCE!P233,RAW_PERFORMANCE!P234,RAW_PERFORMANCE!P235) | O83: COMPLETED DEVELOPMENT
A84: D013__TECO10 | B84: D013 | C84: TECO10 | D84: =AVERAGE(RAW_PERFORMANCE!F236,RAW_PERFORMANCE!F237,RAW_PERFORMANCE!F238) | E84: =AVERAGE(RAW_PERFORMANCE!G236,RAW_PERFORMANCE!G237,RAW_PERFORMANCE!G238) | F84: =AVERAGE(RAW_PERFORMANCE!H236,RAW_PERFORMANCE!H237,RAW_PERFORMANCE!H238) | G84: =AVERAGE(RAW_PERFORMANCE!I236,RAW_PERFORMANCE!I237,RAW_PERFORMANCE!I238) | H84: 1 | I84: =COUNT(RAW_PERFORMANCE!F236,RAW_PERFORMANCE!F237,RAW_PERFORMANCE!F238) | J84: =AVERAGE(RAW_PERFORMANCE!K236,RAW_PERFORMANCE!K237,RAW_PERFORMANCE!K238) | K84: =AVERAGE(RAW_PERFORMANCE!L236,RAW_PERFORMANCE!L237,RAW_PERFORMANCE!L238) | L84: =AVERAGE(RAW_PERFORMANCE!M236,RAW_PERFORMANCE!M237,RAW_PERFORMANCE!M238) | M84: =AVERAGE(RAW_PERFORMANCE!J236,RAW_PERFORMANCE!J237,RAW_PERFORMANCE!J238) | N84: =AVERAGE(RAW_PERFORMANCE!P236,RAW_PERFORMANCE!P237,RAW_PERFORMANCE!P238) | O84: COMPLETED DEVELOPMENT
A85: D013__TECO15 | B85: D013 | C85: TECO15 | D85: =AVERAGE(RAW_PERFORMANCE!F239,RAW_PERFORMANCE!F240,RAW_PERFORMANCE!F241) | E85: =AVERAGE(RAW_PERFORMANCE!G239,RAW_PERFORMANCE!G240,RAW_PERFORMANCE!G241) | F85: =AVERAGE(RAW_PERFORMANCE!H239,RAW_PERFORMANCE!H240,RAW_PERFORMANCE!H241) | G85: =AVERAGE(RAW_PERFORMANCE!I239,RAW_PERFORMANCE!I240,RAW_PERFORMANCE!I241) | H85: 0 | I85: =COUNT(RAW_PERFORMANCE!F239,RAW_PERFORMANCE!F240,RAW_PERFORMANCE!F241) | J85: =AVERAGE(RAW_PERFORMANCE!K239,RAW_PERFORMANCE!K240,RAW_PERFORMANCE!K241) | K85: =AVERAGE(RAW_PERFORMANCE!L239,RAW_PERFORMANCE!L240,RAW_PERFORMANCE!L241) | L85: =AVERAGE(RAW_PERFORMANCE!M239,RAW_PERFORMANCE!M240,RAW_PERFORMANCE!M241) | M85: =AVERAGE(RAW_PERFORMANCE!J239,RAW_PERFORMANCE!J240,RAW_PERFORMANCE!J241) | N85: =AVERAGE(RAW_PERFORMANCE!P239,RAW_PERFORMANCE!P240,RAW_PERFORMANCE!P241) | O85: COMPLETED DEVELOPMENT
A86: D014__SP | B86: D014 | C86: SP | D86: =AVERAGE(RAW_PERFORMANCE!F242,RAW_PERFORMANCE!F243,RAW_PERFORMANCE!F244) | E86: =AVERAGE(RAW_PERFORMANCE!G242,RAW_PERFORMANCE!G243,RAW_PERFORMANCE!G244) | F86: =AVERAGE(RAW_PERFORMANCE!H242,RAW_PERFORMANCE!H243,RAW_PERFORMANCE!H244) | G86: =AVERAGE(RAW_PERFORMANCE!I242,RAW_PERFORMANCE!I243,RAW_PERFORMANCE!I244) | H86: 1 | I86: =COUNT(RAW_PERFORMANCE!F242,RAW_PERFORMANCE!F243,RAW_PERFORMANCE!F244) | J86: =AVERAGE(RAW_PERFORMANCE!K242,RAW_PERFORMANCE!K243,RAW_PERFORMANCE!K244) | K86: =AVERAGE(RAW_PERFORMANCE!L242,RAW_PERFORMANCE!L243,RAW_PERFORMANCE!L244) | L86: =AVERAGE(RAW_PERFORMANCE!M242,RAW_PERFORMANCE!M243,RAW_PERFORMANCE!M244) | M86: =AVERAGE(RAW_PERFORMANCE!J242,RAW_PERFORMANCE!J243,RAW_PERFORMANCE!J244) | N86: =AVERAGE(RAW_PERFORMANCE!P242,RAW_PERFORMANCE!P243,RAW_PERFORMANCE!P244) | O86: COMPLETED DEVELOPMENT
A87: D014__DTT | B87: D014 | C87: DTT | D87: =AVERAGE(RAW_PERFORMANCE!F245,RAW_PERFORMANCE!F246,RAW_PERFORMANCE!F247) | E87: =AVERAGE(RAW_PERFORMANCE!G245,RAW_PERFORMANCE!G246,RAW_PERFORMANCE!G247) | F87: =AVERAGE(RAW_PERFORMANCE!H245,RAW_PERFORMANCE!H246,RAW_PERFORMANCE!H247) | G87: =AVERAGE(RAW_PERFORMANCE!I245,RAW_PERFORMANCE!I246,RAW_PERFORMANCE!I247) | H87: 1 | I87: =COUNT(RAW_PERFORMANCE!F245,RAW_PERFORMANCE!F246,RAW_PERFORMANCE!F247) | J87: =AVERAGE(RAW_PERFORMANCE!K245,RAW_PERFORMANCE!K246,RAW_PERFORMANCE!K247) | K87: =AVERAGE(RAW_PERFORMANCE!L245,RAW_PERFORMANCE!L246,RAW_PERFORMANCE!L247) | L87: =AVERAGE(RAW_PERFORMANCE!M245,RAW_PERFORMANCE!M246,RAW_PERFORMANCE!M247) | M87: =AVERAGE(RAW_PERFORMANCE!J245,RAW_PERFORMANCE!J246,RAW_PERFORMANCE!J247) | N87: =AVERAGE(RAW_PERFORMANCE!P245,RAW_PERFORMANCE!P246,RAW_PERFORMANCE!P247) | O87: COMPLETED DEVELOPMENT
A88: D014__ECO | B88: D014 | C88: ECO | D88: =AVERAGE(RAW_PERFORMANCE!F248,RAW_PERFORMANCE!F249,RAW_PERFORMANCE!F250) | E88: =AVERAGE(RAW_PERFORMANCE!G248,RAW_PERFORMANCE!G249,RAW_PERFORMANCE!G250) | F88: =AVERAGE(RAW_PERFORMANCE!H248,RAW_PERFORMANCE!H249,RAW_PERFORMANCE!H250) | G88: =AVERAGE(RAW_PERFORMANCE!I248,RAW_PERFORMANCE!I249,RAW_PERFORMANCE!I250) | H88: 1 | I88: =COUNT(RAW_PERFORMANCE!F248,RAW_PERFORMANCE!F249,RAW_PERFORMANCE!F250) | J88: =AVERAGE(RAW_PERFORMANCE!K248,RAW_PERFORMANCE!K249,RAW_PERFORMANCE!K250) | K88: =AVERAGE(RAW_PERFORMANCE!L248,RAW_PERFORMANCE!L249,RAW_PERFORMANCE!L250) | L88: =AVERAGE(RAW_PERFORMANCE!M248,RAW_PERFORMANCE!M249,RAW_PERFORMANCE!M250) | M88: =AVERAGE(RAW_PERFORMANCE!J248,RAW_PERFORMANCE!J249,RAW_PERFORMANCE!J250) | N88: =AVERAGE(RAW_PERFORMANCE!P248,RAW_PERFORMANCE!P249,RAW_PERFORMANCE!P250) | O88: COMPLETED DEVELOPMENT
A89: D014__TECO05 | B89: D014 | C89: TECO05 | D89: =AVERAGE(RAW_PERFORMANCE!F251,RAW_PERFORMANCE!F252,RAW_PERFORMANCE!F253) | E89: =AVERAGE(RAW_PERFORMANCE!G251,RAW_PERFORMANCE!G252,RAW_PERFORMANCE!G253) | F89: =AVERAGE(RAW_PERFORMANCE!H251,RAW_PERFORMANCE!H252,RAW_PERFORMANCE!H253) | G89: =AVERAGE(RAW_PERFORMANCE!I251,RAW_PERFORMANCE!I252,RAW_PERFORMANCE!I253) | H89: 0 | I89: =COUNT(RAW_PERFORMANCE!F251,RAW_PERFORMANCE!F252,RAW_PERFORMANCE!F253) | J89: =AVERAGE(RAW_PERFORMANCE!K251,RAW_PERFORMANCE!K252,RAW_PERFORMANCE!K253) | K89: =AVERAGE(RAW_PERFORMANCE!L251,RAW_PERFORMANCE!L252,RAW_PERFORMANCE!L253) | L89: =AVERAGE(RAW_PERFORMANCE!M251,RAW_PERFORMANCE!M252,RAW_PERFORMANCE!M253) | M89: =AVERAGE(RAW_PERFORMANCE!J251,RAW_PERFORMANCE!J252,RAW_PERFORMANCE!J253) | N89: =AVERAGE(RAW_PERFORMANCE!P251,RAW_PERFORMANCE!P252,RAW_PERFORMANCE!P253) | O89: COMPLETED DEVELOPMENT
A90: D014__TECO10 | B90: D014 | C90: TECO10 | D90: =AVERAGE(RAW_PERFORMANCE!F254,RAW_PERFORMANCE!F255,RAW_PERFORMANCE!F256) | E90: =AVERAGE(RAW_PERFORMANCE!G254,RAW_PERFORMANCE!G255,RAW_PERFORMANCE!G256) | F90: =AVERAGE(RAW_PERFORMANCE!H254,RAW_PERFORMANCE!H255,RAW_PERFORMANCE!H256) | G90: =AVERAGE(RAW_PERFORMANCE!I254,RAW_PERFORMANCE!I255,RAW_PERFORMANCE!I256) | H90: 1 | I90: =COUNT(RAW_PERFORMANCE!F254,RAW_PERFORMANCE!F255,RAW_PERFORMANCE!F256) | J90: =AVERAGE(RAW_PERFORMANCE!K254,RAW_PERFORMANCE!K255,RAW_PERFORMANCE!K256) | K90: =AVERAGE(RAW_PERFORMANCE!L254,RAW_PERFORMANCE!L255,RAW_PERFORMANCE!L256) | L90: =AVERAGE(RAW_PERFORMANCE!M254,RAW_PERFORMANCE!M255,RAW_PERFORMANCE!M256) | M90: =AVERAGE(RAW_PERFORMANCE!J254,RAW_PERFORMANCE!J255,RAW_PERFORMANCE!J256) | N90: =AVERAGE(RAW_PERFORMANCE!P254,RAW_PERFORMANCE!P255,RAW_PERFORMANCE!P256) | O90: COMPLETED DEVELOPMENT
A91: D014__TECO15 | B91: D014 | C91: TECO15 | D91: =AVERAGE(RAW_PERFORMANCE!F257,RAW_PERFORMANCE!F258,RAW_PERFORMANCE!F259) | E91: =AVERAGE(RAW_PERFORMANCE!G257,RAW_PERFORMANCE!G258,RAW_PERFORMANCE!G259) | F91: =AVERAGE(RAW_PERFORMANCE!H257,RAW_PERFORMANCE!H258,RAW_PERFORMANCE!H259) | G91: =AVERAGE(RAW_PERFORMANCE!I257,RAW_PERFORMANCE!I258,RAW_PERFORMANCE!I259) | H91: 0 | I91: =COUNT(RAW_PERFORMANCE!F257,RAW_PERFORMANCE!F258,RAW_PERFORMANCE!F259) | J91: =AVERAGE(RAW_PERFORMANCE!K257,RAW_PERFORMANCE!K258,RAW_PERFORMANCE!K259) | K91: =AVERAGE(RAW_PERFORMANCE!L257,RAW_PERFORMANCE!L258,RAW_PERFORMANCE!L259) | L91: =AVERAGE(RAW_PERFORMANCE!M257,RAW_PERFORMANCE!M258,RAW_PERFORMANCE!M259) | M91: =AVERAGE(RAW_PERFORMANCE!J257,RAW_PERFORMANCE!J258,RAW_PERFORMANCE!J259) | N91: =AVERAGE(RAW_PERFORMANCE!P257,RAW_PERFORMANCE!P258,RAW_PERFORMANCE!P259) | O91: COMPLETED DEVELOPMENT
A92: D015__SP | B92: D015 | C92: SP | D92: =AVERAGE(RAW_PERFORMANCE!F260,RAW_PERFORMANCE!F261,RAW_PERFORMANCE!F262) | E92: =AVERAGE(RAW_PERFORMANCE!G260,RAW_PERFORMANCE!G261,RAW_PERFORMANCE!G262) | F92: =AVERAGE(RAW_PERFORMANCE!H260,RAW_PERFORMANCE!H261,RAW_PERFORMANCE!H262) | G92: =AVERAGE(RAW_PERFORMANCE!I260,RAW_PERFORMANCE!I261,RAW_PERFORMANCE!I262) | H92: 1 | I92: =COUNT(RAW_PERFORMANCE!F260,RAW_PERFORMANCE!F261,RAW_PERFORMANCE!F262) | J92: =AVERAGE(RAW_PERFORMANCE!K260,RAW_PERFORMANCE!K261,RAW_PERFORMANCE!K262) | K92: =AVERAGE(RAW_PERFORMANCE!L260,RAW_PERFORMANCE!L261,RAW_PERFORMANCE!L262) | L92: =AVERAGE(RAW_PERFORMANCE!M260,RAW_PERFORMANCE!M261,RAW_PERFORMANCE!M262) | M92: =AVERAGE(RAW_PERFORMANCE!J260,RAW_PERFORMANCE!J261,RAW_PERFORMANCE!J262) | N92: =AVERAGE(RAW_PERFORMANCE!P260,RAW_PERFORMANCE!P261,RAW_PERFORMANCE!P262) | O92: COMPLETED DEVELOPMENT
A93: D015__DTT | B93: D015 | C93: DTT | D93: =AVERAGE(RAW_PERFORMANCE!F263,RAW_PERFORMANCE!F264,RAW_PERFORMANCE!F265) | E93: =AVERAGE(RAW_PERFORMANCE!G263,RAW_PERFORMANCE!G264,RAW_PERFORMANCE!G265) | F93: =AVERAGE(RAW_PERFORMANCE!H263,RAW_PERFORMANCE!H264,RAW_PERFORMANCE!H265) | G93: =AVERAGE(RAW_PERFORMANCE!I263,RAW_PERFORMANCE!I264,RAW_PERFORMANCE!I265) | H93: 1 | I93: =COUNT(RAW_PERFORMANCE!F263,RAW_PERFORMANCE!F264,RAW_PERFORMANCE!F265) | J93: =AVERAGE(RAW_PERFORMANCE!K263,RAW_PERFORMANCE!K264,RAW_PERFORMANCE!K265) | K93: =AVERAGE(RAW_PERFORMANCE!L263,RAW_PERFORMANCE!L264,RAW_PERFORMANCE!L265) | L93: =AVERAGE(RAW_PERFORMANCE!M263,RAW_PERFORMANCE!M264,RAW_PERFORMANCE!M265) | M93: =AVERAGE(RAW_PERFORMANCE!J263,RAW_PERFORMANCE!J264,RAW_PERFORMANCE!J265) | N93: =AVERAGE(RAW_PERFORMANCE!P263,RAW_PERFORMANCE!P264,RAW_PERFORMANCE!P265) | O93: COMPLETED DEVELOPMENT
A94: D015__ECO | B94: D015 | C94: ECO | D94: =AVERAGE(RAW_PERFORMANCE!F266,RAW_PERFORMANCE!F267,RAW_PERFORMANCE!F268) | E94: =AVERAGE(RAW_PERFORMANCE!G266,RAW_PERFORMANCE!G267,RAW_PERFORMANCE!G268) | F94: =AVERAGE(RAW_PERFORMANCE!H266,RAW_PERFORMANCE!H267,RAW_PERFORMANCE!H268) | G94: =AVERAGE(RAW_PERFORMANCE!I266,RAW_PERFORMANCE!I267,RAW_PERFORMANCE!I268) | H94: 1 | I94: =COUNT(RAW_PERFORMANCE!F266,RAW_PERFORMANCE!F267,RAW_PERFORMANCE!F268) | J94: =AVERAGE(RAW_PERFORMANCE!K266,RAW_PERFORMANCE!K267,RAW_PERFORMANCE!K268) | K94: =AVERAGE(RAW_PERFORMANCE!L266,RAW_PERFORMANCE!L267,RAW_PERFORMANCE!L268) | L94: =AVERAGE(RAW_PERFORMANCE!M266,RAW_PERFORMANCE!M267,RAW_PERFORMANCE!M268) | M94: =AVERAGE(RAW_PERFORMANCE!J266,RAW_PERFORMANCE!J267,RAW_PERFORMANCE!J268) | N94: =AVERAGE(RAW_PERFORMANCE!P266,RAW_PERFORMANCE!P267,RAW_PERFORMANCE!P268) | O94: COMPLETED DEVELOPMENT
A95: D015__TECO05 | B95: D015 | C95: TECO05 | D95: =AVERAGE(RAW_PERFORMANCE!F269,RAW_PERFORMANCE!F270,RAW_PERFORMANCE!F271) | E95: =AVERAGE(RAW_PERFORMANCE!G269,RAW_PERFORMANCE!G270,RAW_PERFORMANCE!G271) | F95: =AVERAGE(RAW_PERFORMANCE!H269,RAW_PERFORMANCE!H270,RAW_PERFORMANCE!H271) | G95: =AVERAGE(RAW_PERFORMANCE!I269,RAW_PERFORMANCE!I270,RAW_PERFORMANCE!I271) | H95: 0 | I95: =COUNT(RAW_PERFORMANCE!F269,RAW_PERFORMANCE!F270,RAW_PERFORMANCE!F271) | J95: =AVERAGE(RAW_PERFORMANCE!K269,RAW_PERFORMANCE!K270,RAW_PERFORMANCE!K271) | K95: =AVERAGE(RAW_PERFORMANCE!L269,RAW_PERFORMANCE!L270,RAW_PERFORMANCE!L271) | L95: =AVERAGE(RAW_PERFORMANCE!M269,RAW_PERFORMANCE!M270,RAW_PERFORMANCE!M271) | M95: =AVERAGE(RAW_PERFORMANCE!J269,RAW_PERFORMANCE!J270,RAW_PERFORMANCE!J271) | N95: =AVERAGE(RAW_PERFORMANCE!P269,RAW_PERFORMANCE!P270,RAW_PERFORMANCE!P271) | O95: COMPLETED DEVELOPMENT
A96: D015__TECO10 | B96: D015 | C96: TECO10 | D96: =AVERAGE(RAW_PERFORMANCE!F272,RAW_PERFORMANCE!F273,RAW_PERFORMANCE!F274) | E96: =AVERAGE(RAW_PERFORMANCE!G272,RAW_PERFORMANCE!G273,RAW_PERFORMANCE!G274) | F96: =AVERAGE(RAW_PERFORMANCE!H272,RAW_PERFORMANCE!H273,RAW_PERFORMANCE!H274) | G96: =AVERAGE(RAW_PERFORMANCE!I272,RAW_PERFORMANCE!I273,RAW_PERFORMANCE!I274) | H96: 1 | I96: =COUNT(RAW_PERFORMANCE!F272,RAW_PERFORMANCE!F273,RAW_PERFORMANCE!F274) | J96: =AVERAGE(RAW_PERFORMANCE!K272,RAW_PERFORMANCE!K273,RAW_PERFORMANCE!K274) | K96: =AVERAGE(RAW_PERFORMANCE!L272,RAW_PERFORMANCE!L273,RAW_PERFORMANCE!L274) | L96: =AVERAGE(RAW_PERFORMANCE!M272,RAW_PERFORMANCE!M273,RAW_PERFORMANCE!M274) | M96: =AVERAGE(RAW_PERFORMANCE!J272,RAW_PERFORMANCE!J273,RAW_PERFORMANCE!J274) | N96: =AVERAGE(RAW_PERFORMANCE!P272,RAW_PERFORMANCE!P273,RAW_PERFORMANCE!P274) | O96: COMPLETED DEVELOPMENT
A97: D015__TECO15 | B97: D015 | C97: TECO15 | D97: =AVERAGE(RAW_PERFORMANCE!F275,RAW_PERFORMANCE!F276,RAW_PERFORMANCE!F277) | E97: =AVERAGE(RAW_PERFORMANCE!G275,RAW_PERFORMANCE!G276,RAW_PERFORMANCE!G277) | F97: =AVERAGE(RAW_PERFORMANCE!H275,RAW_PERFORMANCE!H276,RAW_PERFORMANCE!H277) | G97: =AVERAGE(RAW_PERFORMANCE!I275,RAW_PERFORMANCE!I276,RAW_PERFORMANCE!I277) | H97: 0 | I97: =COUNT(RAW_PERFORMANCE!F275,RAW_PERFORMANCE!F276,RAW_PERFORMANCE!F277) | J97: =AVERAGE(RAW_PERFORMANCE!K275,RAW_PERFORMANCE!K276,RAW_PERFORMANCE!K277) | K97: =AVERAGE(RAW_PERFORMANCE!L275,RAW_PERFORMANCE!L276,RAW_PERFORMANCE!L277) | L97: =AVERAGE(RAW_PERFORMANCE!M275,RAW_PERFORMANCE!M276,RAW_PERFORMANCE!M277) | M97: =AVERAGE(RAW_PERFORMANCE!J275,RAW_PERFORMANCE!J276,RAW_PERFORMANCE!J277) | N97: =AVERAGE(RAW_PERFORMANCE!P275,RAW_PERFORMANCE!P276,RAW_PERFORMANCE!P277) | O97: COMPLETED DEVELOPMENT
A98: D016__SP | B98: D016 | C98: SP | D98: =AVERAGE(RAW_PERFORMANCE!F278,RAW_PERFORMANCE!F279,RAW_PERFORMANCE!F280) | E98: =AVERAGE(RAW_PERFORMANCE!G278,RAW_PERFORMANCE!G279,RAW_PERFORMANCE!G280) | F98: =AVERAGE(RAW_PERFORMANCE!H278,RAW_PERFORMANCE!H279,RAW_PERFORMANCE!H280) | G98: =AVERAGE(RAW_PERFORMANCE!I278,RAW_PERFORMANCE!I279,RAW_PERFORMANCE!I280) | H98: 1 | I98: =COUNT(RAW_PERFORMANCE!F278,RAW_PERFORMANCE!F279,RAW_PERFORMANCE!F280) | J98: =AVERAGE(RAW_PERFORMANCE!K278,RAW_PERFORMANCE!K279,RAW_PERFORMANCE!K280) | K98: =AVERAGE(RAW_PERFORMANCE!L278,RAW_PERFORMANCE!L279,RAW_PERFORMANCE!L280) | L98: =AVERAGE(RAW_PERFORMANCE!M278,RAW_PERFORMANCE!M279,RAW_PERFORMANCE!M280) | M98: =AVERAGE(RAW_PERFORMANCE!J278,RAW_PERFORMANCE!J279,RAW_PERFORMANCE!J280) | N98: =AVERAGE(RAW_PERFORMANCE!P278,RAW_PERFORMANCE!P279,RAW_PERFORMANCE!P280) | O98: COMPLETED DEVELOPMENT
A99: D016__DTT | B99: D016 | C99: DTT | D99: =AVERAGE(RAW_PERFORMANCE!F281,RAW_PERFORMANCE!F282,RAW_PERFORMANCE!F283) | E99: =AVERAGE(RAW_PERFORMANCE!G281,RAW_PERFORMANCE!G282,RAW_PERFORMANCE!G283) | F99: =AVERAGE(RAW_PERFORMANCE!H281,RAW_PERFORMANCE!H282,RAW_PERFORMANCE!H283) | G99: =AVERAGE(RAW_PERFORMANCE!I281,RAW_PERFORMANCE!I282,RAW_PERFORMANCE!I283) | H99: 1 | I99: =COUNT(RAW_PERFORMANCE!F281,RAW_PERFORMANCE!F282,RAW_PERFORMANCE!F283) | J99: =AVERAGE(RAW_PERFORMANCE!K281,RAW_PERFORMANCE!K282,RAW_PERFORMANCE!K283) | K99: =AVERAGE(RAW_PERFORMANCE!L281,RAW_PERFORMANCE!L282,RAW_PERFORMANCE!L283) | L99: =AVERAGE(RAW_PERFORMANCE!M281,RAW_PERFORMANCE!M282,RAW_PERFORMANCE!M283) | M99: =AVERAGE(RAW_PERFORMANCE!J281,RAW_PERFORMANCE!J282,RAW_PERFORMANCE!J283) | N99: =AVERAGE(RAW_PERFORMANCE!P281,RAW_PERFORMANCE!P282,RAW_PERFORMANCE!P283) | O99: COMPLETED DEVELOPMENT
A100: D016__ECO | B100: D016 | C100: ECO | D100: =AVERAGE(RAW_PERFORMANCE!F284,RAW_PERFORMANCE!F285,RAW_PERFORMANCE!F286) | E100: =AVERAGE(RAW_PERFORMANCE!G284,RAW_PERFORMANCE!G285,RAW_PERFORMANCE!G286) | F100: =AVERAGE(RAW_PERFORMANCE!H284,RAW_PERFORMANCE!H285,RAW_PERFORMANCE!H286) | G100: =AVERAGE(RAW_PERFORMANCE!I284,RAW_PERFORMANCE!I285,RAW_PERFORMANCE!I286) | H100: 1 | I100: =COUNT(RAW_PERFORMANCE!F284,RAW_PERFORMANCE!F285,RAW_PERFORMANCE!F286) | J100: =AVERAGE(RAW_PERFORMANCE!K284,RAW_PERFORMANCE!K285,RAW_PERFORMANCE!K286) | K100: =AVERAGE(RAW_PERFORMANCE!L284,RAW_PERFORMANCE!L285,RAW_PERFORMANCE!L286) | L100: =AVERAGE(RAW_PERFORMANCE!M284,RAW_PERFORMANCE!M285,RAW_PERFORMANCE!M286) | M100: =AVERAGE(RAW_PERFORMANCE!J284,RAW_PERFORMANCE!J285,RAW_PERFORMANCE!J286) | N100: =AVERAGE(RAW_PERFORMANCE!P284,RAW_PERFORMANCE!P285,RAW_PERFORMANCE!P286) | O100: COMPLETED DEVELOPMENT
A101: D016__TECO05 | B101: D016 | C101: TECO05 | D101: =AVERAGE(RAW_PERFORMANCE!F287,RAW_PERFORMANCE!F288,RAW_PERFORMANCE!F289) | E101: =AVERAGE(RAW_PERFORMANCE!G287,RAW_PERFORMANCE!G288,RAW_PERFORMANCE!G289) | F101: =AVERAGE(RAW_PERFORMANCE!H287,RAW_PERFORMANCE!H288,RAW_PERFORMANCE!H289) | G101: =AVERAGE(RAW_PERFORMANCE!I287,RAW_PERFORMANCE!I288,RAW_PERFORMANCE!I289) | H101: 0 | I101: =COUNT(RAW_PERFORMANCE!F287,RAW_PERFORMANCE!F288,RAW_PERFORMANCE!F289) | J101: =AVERAGE(RAW_PERFORMANCE!K287,RAW_PERFORMANCE!K288,RAW_PERFORMANCE!K289) | K101: =AVERAGE(RAW_PERFORMANCE!L287,RAW_PERFORMANCE!L288,RAW_PERFORMANCE!L289) | L101: =AVERAGE(RAW_PERFORMANCE!M287,RAW_PERFORMANCE!M288,RAW_PERFORMANCE!M289) | M101: =AVERAGE(RAW_PERFORMANCE!J287,RAW_PERFORMANCE!J288,RAW_PERFORMANCE!J289) | N101: =AVERAGE(RAW_PERFORMANCE!P287,RAW_PERFORMANCE!P288,RAW_PERFORMANCE!P289) | O101: COMPLETED DEVELOPMENT
A102: D016__TECO10 | B102: D016 | C102: TECO10 | D102: =AVERAGE(RAW_PERFORMANCE!F290,RAW_PERFORMANCE!F291,RAW_PERFORMANCE!F292) | E102: =AVERAGE(RAW_PERFORMANCE!G290,RAW_PERFORMANCE!G291,RAW_PERFORMANCE!G292) | F102: =AVERAGE(RAW_PERFORMANCE!H290,RAW_PERFORMANCE!H291,RAW_PERFORMANCE!H292) | G102: =AVERAGE(RAW_PERFORMANCE!I290,RAW_PERFORMANCE!I291,RAW_PERFORMANCE!I292) | H102: 1 | I102: =COUNT(RAW_PERFORMANCE!F290,RAW_PERFORMANCE!F291,RAW_PERFORMANCE!F292) | J102: =AVERAGE(RAW_PERFORMANCE!K290,RAW_PERFORMANCE!K291,RAW_PERFORMANCE!K292) | K102: =AVERAGE(RAW_PERFORMANCE!L290,RAW_PERFORMANCE!L291,RAW_PERFORMANCE!L292) | L102: =AVERAGE(RAW_PERFORMANCE!M290,RAW_PERFORMANCE!M291,RAW_PERFORMANCE!M292) | M102: =AVERAGE(RAW_PERFORMANCE!J290,RAW_PERFORMANCE!J291,RAW_PERFORMANCE!J292) | N102: =AVERAGE(RAW_PERFORMANCE!P290,RAW_PERFORMANCE!P291,RAW_PERFORMANCE!P292) | O102: COMPLETED DEVELOPMENT
A103: D016__TECO15 | B103: D016 | C103: TECO15 | D103: =AVERAGE(RAW_PERFORMANCE!F293,RAW_PERFORMANCE!F294,RAW_PERFORMANCE!F295) | E103: =AVERAGE(RAW_PERFORMANCE!G293,RAW_PERFORMANCE!G294,RAW_PERFORMANCE!G295) | F103: =AVERAGE(RAW_PERFORMANCE!H293,RAW_PERFORMANCE!H294,RAW_PERFORMANCE!H295) | G103: =AVERAGE(RAW_PERFORMANCE!I293,RAW_PERFORMANCE!I294,RAW_PERFORMANCE!I295) | H103: 0 | I103: =COUNT(RAW_PERFORMANCE!F293,RAW_PERFORMANCE!F294,RAW_PERFORMANCE!F295) | J103: =AVERAGE(RAW_PERFORMANCE!K293,RAW_PERFORMANCE!K294,RAW_PERFORMANCE!K295) | K103: =AVERAGE(RAW_PERFORMANCE!L293,RAW_PERFORMANCE!L294,RAW_PERFORMANCE!L295) | L103: =AVERAGE(RAW_PERFORMANCE!M293,RAW_PERFORMANCE!M294,RAW_PERFORMANCE!M295) | M103: =AVERAGE(RAW_PERFORMANCE!J293,RAW_PERFORMANCE!J294,RAW_PERFORMANCE!J295) | N103: =AVERAGE(RAW_PERFORMANCE!P293,RAW_PERFORMANCE!P294,RAW_PERFORMANCE!P295) | O103: COMPLETED DEVELOPMENT
A104: D017__SP | B104: D017 | C104: SP | D104: =AVERAGE(RAW_PERFORMANCE!F296,RAW_PERFORMANCE!F297,RAW_PERFORMANCE!F298) | E104: =AVERAGE(RAW_PERFORMANCE!G296,RAW_PERFORMANCE!G297,RAW_PERFORMANCE!G298) | F104: =AVERAGE(RAW_PERFORMANCE!H296,RAW_PERFORMANCE!H297,RAW_PERFORMANCE!H298) | G104: =AVERAGE(RAW_PERFORMANCE!I296,RAW_PERFORMANCE!I297,RAW_PERFORMANCE!I298) | H104: 1 | I104: =COUNT(RAW_PERFORMANCE!F296,RAW_PERFORMANCE!F297,RAW_PERFORMANCE!F298) | J104: =AVERAGE(RAW_PERFORMANCE!K296,RAW_PERFORMANCE!K297,RAW_PERFORMANCE!K298) | K104: =AVERAGE(RAW_PERFORMANCE!L296,RAW_PERFORMANCE!L297,RAW_PERFORMANCE!L298) | L104: =AVERAGE(RAW_PERFORMANCE!M296,RAW_PERFORMANCE!M297,RAW_PERFORMANCE!M298) | M104: =AVERAGE(RAW_PERFORMANCE!J296,RAW_PERFORMANCE!J297,RAW_PERFORMANCE!J298) | N104: =AVERAGE(RAW_PERFORMANCE!P296,RAW_PERFORMANCE!P297,RAW_PERFORMANCE!P298) | O104: COMPLETED DEVELOPMENT
...

Sheet VALIDATION
A2: Scientific gates: accounting passes, route ordering fails
A4: Every gate distinguishes computational correctness from decision usefulness. No failed gate is hidden.
A7: Check | B7: Observed value | C7: Criterion / comparison | D7: Status | E7: Interpretation
A8: Development valid runs | B8: 432 | C8: 432 | D8: PASS | E8: 24 contexts x6 settings x3 seeds
A9: Probe valid runs | B9: 232 | C9: 232 | D9: PASS | E9: 4 contexts x2 seeds x29 routes
A10: Development max mass discrepancy | B10: 0.0016944689 | C10: 0.01 | D10: PASS | E10: Native edge mass vs trip accumulated mass
A11: Native algebra max relative error | B11: 6.9449991e-07 | C11: 0.0001 | D11: PASS | E11: mg / vehicle-seconds × time
A12: Selected-path CO2 WAPE | B12: 0.14711924 | C12: 0.25 | D12: PASS | E12: Trip-weighted forecast screening
A13: Selected-path signed bias | B13: -0.00315158 | C13: 0.1 | D13: PASS | E13: Absolute bias criterion
A14: Probe median route Spearman | B14: 0.53571429 | C14: 0.5 | D14: PASS | E14: Eight route-order panels
A15: Probe mean relative selection loss | B15: 0.21620886 | C15: 0.1 | D15: FAIL — MODIFY | E15: Good average error did not ensure good choices
A16: Unchanged original-route replay | B16: 8 | C16: 8 | D16: PASS | E16: Exact seconds / within1e-6g
A17: New main experiment runs | B17: 0 | C17: Scientific release blocked | D17: NOT RUN | E17: Not omitted or fabricated results
A18: New ML fitted | B18: 0 | C18: Scientific release blocked | D18: NOT FITTED | E18: No test performance claimed
A23: Probe context | B23: Seed | C23: Rank correlation | D23: CO2 choice loss | E23: Predicted-best route | F23: Observed-best route | G23: Replay exact?
A24: D001 | B24: 8101 | C24: 0.5182266 | D24: 0.2160506 | E24: P19 | F24: P20 | G24: TRUE
A25: D001 | B25: 8102 | C25: 0.5635468 | D25: 0.056024084 | E25: P19 | F25: P17 | G25: TRUE
A26: D006 | B26: 8101 | C26: 0.5773399 | D26: 0 | E26: P01 | F26: P01 | G26: TRUE
A27: D006 | B27: 8102 | C27: 0.48965517 | D27: 0.78160933 | E27: P19 | F27: P01 | G27: TRUE
A28: D017 | B28: 8101 | C28: -0.098029557 | D28: 0.44136732 | E28: P01 | F28: P29 | G28: TRUE
A29: D017 | B29: 8102 | C29: 0.16059113 | D29: 0.23461954 | E29: P01 | F29: P29 | G29: TRUE
A30: D022 | B30: 8101 | C30: 0.55320197 | D30: 0 | E30: P01 | F30: P01 | G30: TRUE
A31: D022 | B31: 8102 | C31: 0.60689655 | D31: 0 | E31: P01 | F31: P01 | G31: TRUE
A35: Forecast baseline | B35: N matched trips | C35: MAE (g) | D35: RMSE (g) | E35: WAPE | F35: Signed bias
A36: pred_co2_g | B36: 270432 | C36: 208.46978 | D36: 447.76178 | E36: 0.14711924 | F36: -0.00315158
A37: default_pred_co2_g | B37: 270432 | C37: 317.14108 | D37: 473.33696 | E37: 0.22380969 | F37: -0.090377907
A38: warmup_distance_pred_co2_g | B38: 270432 | C38: 522.54028 | D38: 742.6197 | E38: 0.36876199 | F38: -0.35474714
A42: Baseline naming correction | B42: default_pred_co2_g is the frozen 600-s observed snapshot, NOT a free-flow-only forecast.
A45: Uncertainty | B45: 24 designed contexts; 3 seed blocks. Probe screen has only 8 panels. No trip-level pseudo-sample inference.
A48: Excel validation | B48: Recalculated; compared all 144 means and active scores with independent Python; changed inputs; scanned formula errors.
A51: Desktop Excel | B51: Not executed in desktop Excel; native formulas and cached values are exported.

Sheet DATA_DICTIONARY
A2: How to read populations, units and evidence
A4: Each numerical outcome has a population and boundary; named zeros for run counts are not missing measurements.
A7: Variable / term | B7: Unit / type | C7: Definition | D7: Source / restriction
A8: Context | B8: Categorical | C8: One unique factor configuration; replications are not new contexts | D8: SCENARIO_DESIGN
A9: Setting | B9: Categorical | C9: SP/DTT/ECO plus TECO allowance sensitivities | D9: TECO10 core used only for descriptive 4-policy comparison
A10: Seed | B10: Integer | C10: Paired exogenous demand block across settings | D10: 8101–8103 development
A11: Journey | B11: s | C11: arrival minus requested departure; includes insertion wait | D11: Primary cohort requested 600–2400
A12: CO2 | B12: g/veh | C12: In-network modeled tailpipe emissions; CO2_abs/1000 | D12: HBEFA3/PC_G_EU4; no external insertion emissions
A13: P95 | B13: s | C13: Per-run primary type7 quantile; equal mean over replications | D13: Diagnostic; not same-OD day-to-day reliability
A14: Default fraction | B14: Fraction | C14: Defaulted route links / counted route links at assignment | D14: Observer coverage diagnostic
A15: Queue proxy | B15: vehicle-s | C15: Sum native edge waitingTime over full run | D15: All vehicles, all times; not cohort queue length
A16: Network cohort total | B16: g | C16: Primary+background requests in evaluation window, through completion | D16: Distinct from all-vehicles accounting mass
A17: WAPE | B17: Fraction | C17: Sum absolute emission forecast errors / sum actual grams | D17: Trip-weighted; not MAPE
A18: Regret | B18: Normalized cost units | C18: Observed chosen cost minus observed context minimum | D18: Fixed additive references; lower better
... A25: HYPOTHETICAL | B25: Evidence category | C25: Teaching example only | D25: WORKED_EXAMPLE, isolated from experiment

Sheet SOURCES
A2: Verified references and access limitations
A4: Targeted search through 19 September 2026; not a systematic review or proof of first-ever novelty.
A7: ID | B7: Title | C7: Authors | D7: Year | E7: Venue | F7: DOI | G7: URL | H7: Role | I7: Access / verification
A8: R01 | B8: A note on two problems in connexion with graphs | C8: E. W. Dijkstra | D8: 1959 | E8: Numerische Mathematik | F8: 10.1007/bf01386390 | G8: https://doi.org/10.1007/bf01386390 | H8: Dijkstra shortest path | I8: Publisher metadata; standard algorithm
A9: R02 | B9: The effects of route choice decisions on vehicle energy consumption and emissions | C9: Kyoungho Ahn; Hesham Rakha | D9: 2008 | E9: Transportation Research Part D: Transport and Environment | F9: 10.1016/j.trd.2008.01.005 | G9: https://doi.org/10.1016/j.trd.2008.01.005 | H9: Route choice and energy | I9: Publisher abstract
A10: R03 | B10: Eco-Routing Navigation System Based on Multisource Historical and Real-Time Traffic Information | C10: Kanok Boriboonsomsin; Matthew J. Barth; Weihua Zhu; Alexander Vu | D10: 2012 | E10: IEEE Transactions on Intelligent Transportation Systems | F10: 10.1109/tits.2012.2204051 | G10: https://doi.org/10.1109/tits.2012.2204051 | H10: Historical/realtime eco-routing | I10: Bibliography and published abstract; detailed model not replicated
A11: R04 | B11: Application of the support vector machine and heuristic k-shortest path algorithm to determine the most eco-friendly path with a travel time constraint | C11: Weiliang Zeng; Tomio Miwa; Takayuki Morikawa | D11: 2017 | E11: Transportation Research Part D: Transport and Environment | F11: 10.1016/j.trd.2017.10.001 | G11: https://doi.org/10.1016/j.trd.2017.10.001 | H11: Time-constrained CO2 routing | I11: Publisher abstract; no equation number asserted
A12: R05 | B12: Eco-Routing based on a Data Driven Fuel Consumption Model | C12: Xianan Huang; Huei Peng | D12: 2018 | E12: arXiv preprint | F12: Not assigned / not used | G12: https://arxiv.org/abs/1801.08602 | H12: Eco-Routing based on a Data Driven Fuel Consumption Model | I12: Full author preprint inspected; section 2.3 eqs 19-23; soft time constraint differs from our candidate hard filter
A13: R06 | B13: Multi-objective eco-routing for dynamic control of connected & automated vehicles | C13: Shadi Djavadian; Ran Tu; Bilal Farooq; Marianne Hatzopoulou | D13: 2020 | E13: Transportation Research Part D: Transport and Environment | F13: 10.1016/j.trd.2020.102513 | G13: https://doi.org/10.1016/j.trd.2020.102513 | H13: Multiobjective eco-routing | I13: Author full text arXiv:2005.00815, section 3
A14: R07 | B14: Deep Learning Based Proactive Multi-Objective Eco-Routing Strategies for Connected and Automated Vehicles | C14: Lama Alfaseeh; Bilal Farooq | D14: 2020 | E14: Frontiers in Future Transportation | F14: 10.3389/ffutr.2020.594608 | G14: https://doi.org/10.3389/ffutr.2020.594608 | H14: Proactive learned eco-routing | I14: Publisher full text
A15: R08 | B15: The Algorithm Selection Problem | C15: John R. Rice | D15: 1976 | E15: Advances in Computers; Advances in Computers Volume 15 | F15: 10.1016/s0065-2458(08)60520-3 | G15: https://doi.org/10.1016/s0065-2458(08)60520-3 | H15: Algorithm selection | I15: Publisher chapter metadata and abstract
A16: R09 | B16: ASlib: A benchmark library for algorithm selection | C16: Bernd Bischl; Pascal Kerschke; Lars Kotthoff; Marius Lindauer; Yuri Malitsky; Alexandre Fréchette; Holger Hoos; Frank Hutter; Kevin Leyton-Brown; Kevin Tierney; Joaquin Vanschoren | D16: 2016 | E16: Artificial Intelligence | F16: 10.1016/j.artint.2016.04.003 | G16: https://doi.org/10.1016/j.artint.2016.04.003 | H16: ASlib benchmark | I16: Author full text
A17: R10 | B17: SATzilla: Portfolio-based Algorithm Selection for SAT | C17: L. Xu; F. Hutter; H. H. Hoos; K. Leyton-Brown | D17: 2008 | E17: Journal of Artificial Intelligence Research | F17: 10.1613/jair.2490 | G17: https://doi.org/10.1613/jair.2490 | H17: Performance-model portfolio selection | I17: Author full text arXiv:1111.2249
A18: R11 | B18: Smart “Predict, then Optimize” | C18: Adam N. Elmachtoub; Paul Grigas | D18: 2022 | E18: Management Science | F18: 10.1287/mnsc.2020.3922 | G18: https://doi.org/10.1287/mnsc.2020.3922 | H18: Decision loss | I18: Author full text arXiv:1710.08005
A19: R12 | B19: Multiple Attribute Decision Making | C19: Ching-Lai Hwang; Kwangsun Yoon | D19: 1981 | E19: Lecture Notes in Economics and Mathematical Systems | F19: 10.1007/978-3-642-48318-9 | G19: https://doi.org/10.1007/978-3-642-48318-9 | H19: SAW/TOPSIS foundations | I19: Publisher book metadata; method chapter pp.58-191
... A47: R40 | B47: Prediction of vehicle CO2 emission and its application to eco-routing navigation | C47: Weiliang Zeng; Tomio Miwa; Takayuki Morikawa | D47: 2016 | E47: Transportation Research Part C: Emerging Technologies | F47: 10.1016/j.trc.2016.04.007 | G47: https://www.sciencedirect.com/science/article/pii/S0968090X16300110 | H47: Prediction then environmental routing | I47: Publisher record and Crossref metadata; full equations not retrieved

Sheet REGIME_TRANSITION
A2: Regime structure of routing-policy preference
A4: Switching margin m = C(SP) - C(DTT) in common cost units, balanced profile. Negative: SP preferred. Derived from the 432 completed runs; no new simulation.
A7: Signal | B7: Restriction | C7: m @ q=720 | D7: m @ q=1200 | E7: m @ q=1680 | F7: Crossing bracket (veh/h)
A8: Balanced | B8: None | C8: -0.055097117 | D8: 0.42037693 | E8: 1.0139358 | F8: (720, 1200]
A9: Balanced | B9: U | C9: -0.051482651 | D9: 0.43818481 | E9: 0.94184088 | F9: (720, 1200]
A10: Balanced | B10: C | C10: -0.019478681 | D10: 0.80555896 | E10: 1.1136829 | F10: (720, 1200]
A11: Balanced | B11: L | C11: -0.056220787 | D11: 0.41956985 | E11: 1.0134209 | F11: (720, 1200]
A12: Arterial | B12: None | C12: -0.018376342 | D12: -0.1268756 | E12: 0.32485416 | F12: (1200, 1680]
A13: Arterial | B13: U | C13: -0.019833535 | D13: -0.13175667 | E13: 0.31654828 | F13: (1200, 1680]
A14: Arterial | B14: C | C14: -0.042302736 | D14: 0.048793553 | E14: 0.38933725 | F14: (720, 1200]
A15: Arterial | B15: L | C15: -0.010981471 | D15: -0.095412381 | E15: 0.29522519 | F15: (1200, 1680]
A18: Worst-policy regret by demand
A19: q=720 | B19: 0.034221665
A20: q=1200 | B20: 0.3228937
A21: q=1680 | B21: 0.67610567
A23: Seed stability
A24: contexts with identical winner in all 3 seeds | B24: 20 | C24: of 24
A25: contexts with stable margin sign | B25: 22 | C25: of 24
A26: unstable contexts | B26: D005, D009, D011, D015
A27: LIMITATION | B27: Demand grid is 480 veh/h coarse: the reversal is BRACKETED, not localised. No threshold estimate is made.

Sheet DECISION_EVALUATION
A2: Held-out routing-policy selection (leave-one-context-out)
A4: Portfolio SP/DTT/TECO10. Model and reference scales refit per fold; test context never seen. No new simulation.
A7: Method | B7: Mean regret | C7: Max regret | D7: Optimal /24 | E7: Within 1% /24
A8: Fixed SP | B8: 0.31824793 | C8: 1.1136829 | D8: 11 | E8: 11
A9: Fixed DTT (best fixed) | B9: 0.030184952 | C9: 0.13175667 | D9: 10 | E9: 11
A10: Fixed TECO10 | B10: 0.20756955 | C10: 1.0139358 | D10: 9 | E10: 9
A11: Adaptive selector (held-out) | B11: 0.0060589344 | C11: 0.11544781 | D11: 21 | E11: 22
A12: Hindsight Best-Policy Benchmark | B12: 0 | C12: 0 | D12: 24 | E12: 24
A14: Available headroom (fixed DTT -> hindsight) | B14: 0.030184952
A15: Headroom captured (%) | B15: 79.927301
A16: Prediction MAE time (s) | B16: 44.63257
A17: Prediction RMSE time (s) | B17: 79.728814
A18: Prediction MAE CO2 (g) | B18: 82.381773
A19: Prediction RMSE CO2 (g) | B19: 122.09228
A22: EXTRAPOLATION STRESS TEST (hold out an entire demand regime)
A23: Held-out q | B23: Selector mean regret | C23: Fixed DTT mean regret | D23: Selector chose
A24: 720 | B24: 0.02456165 | C24: 0.034221665 | D24: DTT, TECO10
A25: 1200 | B25: 0.05633319 | C25: 0.05633319 | D25: DTT
A26: 1680 | B26: 0.14856085 | C26: 0 | D26: DTT, TECO10
A27: POOLED | B27: 0.076485229 | C27: 0.030184952 | D27: captured -153.4% -> selector WORSE than fixed
A29: Per-context held-out decisions
A30: Context | B30: Selected policy
A31: D001 | B31: SP
A32: D002 | B32: SP
A33: D003 | B33: SP
A34: D004 | B34: SP
A35: D005 | B35: SP
A36: D006 | B36: SP
A37: D007 | B37: SP
A38: D008 | B38: SP
A39: D009 | B39: DTT
A40: D010 | B40: TECO10
A41: D011 | B41: DTT
... A54: D024 | B54: DTT

Sheet NEGATIVE_CONTROLS
A2: Audited negative controls
A4: Retained, not deleted. These delimit what the positive result means.
A7: Control | B7: Observed value | C7: Interpretation
A8: ECO outcome-identical to SP | B8: 21/24 contexts | C8: No independent environmental decision dimension; ECO removed from portfolio
A9: Observer route-order selection loss | B9: 21.62% | C9: Fails declared 10% screen despite 14.71% aggregate WAPE
A10: Observer best-route hits | B10: 3/8 panels | C10: Good average prediction did not confer correct ranking
A11: Selector decisions across w_time 0..1 | B11: identical in all 24 contexts | C11: Preference layer is near-inert; regime pattern is NOT a weight artefact
A12: Hindsight label change across weights | B12: 1/24 contexts (D011) | C12: Only at the pure-emissions extreme
A13: Insertion-boundary winner flips | B13: 0/24 contexts | C13: Regime structure not an artefact of the emission accounting boundary
A14: Pilot adaptive headroom | B14: 0 (DTT best in 30/30) | C14: Earlier environment had no regime reversal
